Workbook

Sheet 表结构清单
B2: 数据表 | C2: 数据表名称 | D2: 表归类
B3: =HYPERLINK("#AUDIT_INFO!A1","AUDIT_INFO") | C3: 审计信息 | D3: 评估机构
B4: =HYPERLINK("#APPRAISAL_AGENCY!A1","APPRAISAL_AGENCY") | C4: 评估机构
B5: =HYPERLINK("#APPRAISAL_AGENCY_APPLY!A1","APPRAISAL_AGENCY_APPLY") | C5: 评估机构申请信息表
B6: =HYPERLINK("#APPRAISAL_AGENCY_APPRAISE!A1","APPRAISAL_AGENCY_APPRAISE") | C6: 评价调查信息管理
B7: =HYPERLINK("#APPRAISAL_AGENCY_COOPERATION!A1","APPRAISAL_AGENCY_COOPERATION") | C7: 评估机构合作协议
B8: =HYPERLINK("#APPRAISAL_AGENCY_EVENT!A1","APPRAISAL_AGENCY_EVENT") | C8: 评估机构事件表
B9: =HYPERLINK("#APPRAISAL_AGENCY_EXPENSES!A1","APPRAISAL_AGENCY_EXPENSES") | C9: 评估机构费用
B10: =HYPERLINK("#APPRAISAL_AGENCY_FILE!A1","APPRAISAL_AGENCY_FILE") | C10: 评级机构附件
B11: =HYPERLINK("#APPRAISAL_AGENCY_INFORMATION!A1","APPRAISAL_AGENCY_INFORMATION") | C11: 评估公司相关信息
B12: =HYPERLINK("#APPRAISAL_AGENCY_QUALIFICATION!A1","APPRAISAL_AGENCY_QUALIFICATION") | C12: 评估机构资质表
B13: =HYPERLINK("#APPRAISAL_APPLY_RELATIVE!A1","APPRAISAL_APPLY_RELATIVE") | C13: 评级机构申请关联表
B14: =HYPERLINK("#AWE_BIZFILE_INFO!A1","AWE_BIZFILE_INFO") | C14: 业务文件详情 | D14: 底层表
B15: =HYPERLINK("#AWE_DICT_ERRMSG!A1","AWE_DICT_ERRMSG") | C15: 系统错误报告
B16: =HYPERLINK("#AWE_DO_CATALOG!A1","AWE_DO_CATALOG") | C16: OW显示模板场景
B17: =HYPERLINK("#AWE_DO_COL_VALIDATE!A1","AWE_DO_COL_VALIDATE") | C17: DW字段验证规则
B18: =HYPERLINK("#AWE_DO_EVENT!A1","AWE_DO_EVENT") | C18: OW字段事件
B19: =HYPERLINK("#AWE_DO_FUNCTION!A1","AWE_DO_FUNCTION") | C19: OW脚本方法
B20: =HYPERLINK("#AWE_DO_GROUP!A1","AWE_DO_GROUP") | C20: OW分组信息
B21: =HYPERLINK("#AWE_DO_JS_FUNCTION!A1","AWE_DO_JS_FUNCTION") | C21: OW通用js方法
B22: =HYPERLINK("#AWE_DO_KEYFILTER!A1","AWE_DO_KEYFILTER") | C22: OW关键字查询
B23: =HYPERLINK("#AWE_DO_LIBRARY!A1","AWE_DO_LIBRARY") | C23: OW显示模板字段信息
B24: =HYPERLINK("#AWE_DO_MODES!A1","AWE_DO_MODES") | C24: OW显示模板样式表
B25: =HYPERLINK("#AWE_DO_VALIDATE!A1","AWE_DO_VALIDATE") | C25: 数据验证类
B26: =HYPERLINK("#AWE_DO_VALIDATE_CATALOG!A1","AWE_DO_VALIDATE_CATALOG") | C26: 数据验证业务分类
B27: =HYPERLINK("#AWE_DW_CONTEXT!A1","AWE_DW_CONTEXT") | C27: 显示模型上下文环境
B28: =HYPERLINK("#AWE_FUNCTION_INFO!A1","AWE_FUNCTION_INFO") | C28: 功能点信息
B29: =HYPERLINK("#AWE_FUNCTION_URL!A1","AWE_FUNCTION_URL") | C29: 功能点URL
B30: =HYPERLINK("#AWE_GROUP_CATALOG!A1","AWE_GROUP_CATALOG") | C30: 组合页面目录信息
B31: =HYPERLINK("#CODE_CATALOG!A1","CODE_CATALOG") | C31: 代码类别表;代码类别表
B32: =HYPERLINK("#CODE_LIBRARY!A1","CODE_LIBRARY") | C32: 代码表;代码库
B33: =HYPERLINK("#OBJECTTYPE_CATALOG!A1","OBJECTTYPE_CATALOG") | C33: 对象类型信息表
B34: =HYPERLINK("#OBJECTTYPE_RELA!A1","OBJECTTYPE_RELA") | C34: 对象关联信息表
B35: =HYPERLINK("#OBJECT_ATTRIBUTE!A1","OBJECT_ATTRIBUTE") | C35: 对象属性信息表
B36: =HYPERLINK("#OBJECT_MAXSN!A1","OBJECT_MAXSN") | C36: 系统流水表;系统流水号表
B37: =HYPERLINK("#ROLE_RIGHT!A1","ROLE_RIGHT") | C37: 角色权限表
B38: =HYPERLINK("#SECURITY_AUDIT!A1","SECURITY_AUDIT") | C38: 安全审计
B39: =HYPERLINK("#SELECT_CATALOG!A1","SELECT_CATALOG") | C39: 查询信息表
B40: =HYPERLINK("#USER_FAILEDLIST!A1","USER_FAILEDLIST") | C40: 用户登录失败表;用户痕迹表
B41: =HYPERLINK("#USER_LIST!A1","USER_LIST") | C41: 用户登录表;用户登录列表
B42: =HYPERLINK("#USER_LOGON_SESSION!A1","USER_LOGON_SESSION") | C42: 用户登录session
B43: =HYPERLINK("#USER_MARKINFO!A1","USER_MARKINFO") | C43: 用户记录表;用户痕迹表
B44: =HYPERLINK("#USER_RIGHT!A1","USER_RIGHT") | C44: 用户权限表
B45: =HYPERLINK("#USER_RUNTIME!A1","USER_RUNTIME") | C45: 用户运行时信息
B46: =HYPERLINK("#AWE_GROUP_CLASSIFY!A1","AWE_GROUP_CLASSIFY") | C46: 组合页面分类信息表
B47: =HYPERLINK("#AWE_GROUP_ITEM!A1","AWE_GROUP_ITEM") | C47: 组合页面详细信息表
B48: =HYPERLINK("#AWE_HREF_INFO!A1","AWE_HREF_INFO") | C48: 链接信息
B49: =HYPERLINK("#AWE_JSP_RUNTIME!A1","AWE_JSP_RUNTIME") | C49: jsp页面访问统计表
B50: =HYPERLINK("#AWE_MENU_INFO!A1","AWE_MENU_INFO") | C50: 菜单表;系统菜单表
B51: =HYPERLINK("#AWE_MESSAGE_INFO!A1","AWE_MESSAGE_INFO") | C51: 站内信对象
B52: =HYPERLINK("#AWE_MESSAGE_USER!A1","AWE_MESSAGE_USER") | C52: 站内信发送/关联用户
B53: =HYPERLINK("#AWE_QUERY_INFO!A1","AWE_QUERY_INFO") | C53: 查询配置基本信息
B54: =HYPERLINK("#AWE_QUERY_USER!A1","AWE_QUERY_USER") | C54: 异步查询下载
B55: =HYPERLINK("#AWE_QUICK_HREF!A1","AWE_QUICK_HREF") | C55: 快捷链接
B56: =HYPERLINK("#AWE_RECORD_INFO!A1","AWE_RECORD_INFO") | C56: 特殊信息记录表
B57: =HYPERLINK("#AWE_RIGHT_MENU!A1","AWE_RIGHT_MENU") | C57: 菜单权限表
B58: =HYPERLINK("#AWE_ROLE_FUNCTION!A1","AWE_ROLE_FUNCTION") | C58: 角色和功能点关联表
B59: =HYPERLINK("#AWE_ROLE_MENU!A1","AWE_ROLE_MENU") | C59: 角色菜单表;菜单角色表
B60: =HYPERLINK("#AWE_ROLE_RIGHT!A1","AWE_ROLE_RIGHT") | C60: 角色权限系统表
B61: =HYPERLINK("#AWE_ROLE_URL!A1","AWE_ROLE_URL") | C61: 角色权限URL
B62: =HYPERLINK("#AWE_SHORTCUT!A1","AWE_SHORTCUT") | C62: 系统默认快捷菜单表
B63: =HYPERLINK("#AWE_SHORTCUTITEM!A1","AWE_SHORTCUTITEM") | C63: 系统功能库
B64: =HYPERLINK("#AWE_TASK_INFO!A1","AWE_TASK_INFO") | C64: 任务信息表
B65: =HYPERLINK("#AWE_TASK_PROCESS!A1","AWE_TASK_PROCESS") | C65: 任务进度信息
B66: =HYPERLINK("#AWE_WIZARD_CATALOG!A1","AWE_WIZARD_CATALOG") | C66: 向导目录
B67: =HYPERLINK("#AWE_WIZARD_LIBRARY!A1","AWE_WIZARD_LIBRARY") | C67: 向导定义表;向导定义
B68: =HYPERLINK("#AWE_WIZARD_RUNNER!A1","AWE_WIZARD_RUNNER") | C68: 向导运行记录表
B69: =HYPERLINK("#CLASS_CATALOG!A1","CLASS_CATALOG") | C69: 类定义
B70: =HYPERLINK("#CLASS_METHOD!A1","CLASS_METHOD") | C70: 方法
B71: =HYPERLINK("#CLR_REGISTER_RECORD!A1","CLR_REGISTER_RECORD") | C71: 抵质押登记记录 | D71: 抵质押登记管理
B72: =HYPERLINK("#CLR_COMMODITY_MARKET!A1","CLR_COMMODITY_MARKET") | C72: 大宗商品盯市数据表 | D72: 盯市管理
B73: =HYPERLINK("#CLR_FUND_MARKET!A1","CLR_FUND_MARKET") | C73: 基金盯市数据表
B74: =HYPERLINK("#CLR_FUND_MARKET_DETAIL!A1","CLR_FUND_MARKET_DETAIL") | C74: 基金盯市数据明细表
B75: =HYPERLINK("#CLR_MATERIAL_CATALOG!A1","CLR_MATERIAL_CATALOG") | C75: 商品类别信息表
B76: =HYPERLINK("#CLR_STOCK_MARKET!A1","CLR_STOCK_MARKET") | C76: 股票盯市数据表
B77: =HYPERLINK("#CLR_STOCK_MARKET_DETAIL!A1","CLR_STOCK_MARKET_DETAIL") | C77: 股票盯市数据明细表
B78: =HYPERLINK("#SCENARIO_ARGS!A1","SCENARIO_ARGS") | C78: 风险探测参数信息表 | D78: 风险探测
B79: =HYPERLINK("#SCENARIO_CATALOG!A1","SCENARIO_CATALOG") | C79: 场景分类
B80: =HYPERLINK("#SCENARIO_GROUP!A1","SCENARIO_GROUP") | C80: 场景分组
B81: =HYPERLINK("#SCENARIO_MODEL!A1","SCENARIO_MODEL") | C81: 场景模型
B82: =HYPERLINK("#SCENARIO_RELATIVE!A1","SCENARIO_RELATIVE") | C82: 场景关联表
B83: =HYPERLINK("#USER_WORKTIPS!A1","USER_WORKTIPS") | C83: 用户工作日志表 | D83: 工作台
B84: =HYPERLINK("#WORKTIP_CONDITION!A1","WORKTIP_CONDITION") | C84: 工作情况
B85: =HYPERLINK("#WORKTIP_SUMMARY!A1","WORKTIP_SUMMARY") | C85: 工作汇总
B86: =HYPERLINK("#CLR_VERIFICATION_INFO!A1","CLR_VERIFICATION_INFO") | C86: 核押详情 | D86: 核押信息登记
B87: =HYPERLINK("#CLR_VERIFICATION_RECORD!A1","CLR_VERIFICATION_RECORD") | C87: 核押信息记录
B88: =HYPERLINK("#WF_INSTANCE!A1","WF_INSTANCE") | C88: 流程实例 | D88: 流程表
B89: wf_opinion | C89: 流程意见记录
B90: =HYPERLINK("#WF_WORKITEM!A1","WF_WORKITEM") | C90: 流程工作项(任务)
B91: =HYPERLINK("#WF_ACTIVEINSTANCE!A1","WF_ACTIVEINSTANCE") | C91: 流程的活动(节点)实例
B92: =HYPERLINK("#FLOW_ACTIVITIES!A1","FLOW_ACTIVITIES") | C92: 流程活动(节点)
B93: =HYPERLINK("#FLOW_ATTRIBUTEGROUP!A1","FLOW_ATTRIBUTEGROUP") | C93: 流程活动的属性分组
B94: =HYPERLINK("#FLOW_BUTTONGROUP!A1","FLOW_BUTTONGROUP") | C94: 流程按钮组
B95: =HYPERLINK("#FLOW_BUTTONITEM!A1","FLOW_BUTTONITEM") | C95: 流程按钮
B96: =HYPERLINK("#FLOW_DEF!A1","FLOW_DEF") | C96: 流程定义
B97: =HYPERLINK("#FLOW_DEPLOY!A1","FLOW_DEPLOY") | C97: 流程部署
B98: =HYPERLINK("#FLOW_GROUP!A1","FLOW_GROUP") | C98: 流程分组
B99: =HYPERLINK("#FLOW_HI_MODEL!A1","FLOW_HI_MODEL") | C99: 流程模型的历史
B100: =HYPERLINK("#FLOW_MESSAGE!A1","FLOW_MESSAGE") | C100: 流程信息
B101: =HYPERLINK("#FLOW_PHASETYPE!A1","FLOW_PHASETYPE") | C101: 流程阶段类型
...

Sheet 表结构清单 (2)
B2: 数据表 | C2: 数据表名称 | D2: 表归类
B3: =HYPERLINK("#AUDIT_INFO!A1","AUDIT_INFO") | C3: 审计信息 | D3: 评估机构
B4: =HYPERLINK("#APPRAISAL_AGENCY!A1","APPRAISAL_AGENCY") | C4: 评估机构
B5: =HYPERLINK("#APPRAISAL_AGENCY_APPLY!A1","APPRAISAL_AGENCY_APPLY") | C5: 评估机构申请信息表
B6: =HYPERLINK("#APPRAISAL_AGENCY_APPRAISE!A1","APPRAISAL_AGENCY_APPRAISE") | C6: 评价调查信息管理
B7: =HYPERLINK("#APPRAISAL_AGENCY_COOPERATION!A1","APPRAISAL_AGENCY_COOPERATION") | C7: 评估机构合作协议
B8: =HYPERLINK("#APPRAISAL_AGENCY_EVENT!A1","APPRAISAL_AGENCY_EVENT") | C8: 评估机构事件表
B9: =HYPERLINK("#APPRAISAL_AGENCY_EXPENSES!A1","APPRAISAL_AGENCY_EXPENSES") | C9: 评估机构费用
B10: =HYPERLINK("#APPRAISAL_AGENCY_FILE!A1","APPRAISAL_AGENCY_FILE") | C10: 评级机构附件
B11: =HYPERLINK("#APPRAISAL_AGENCY_INFORMATION!A1","APPRAISAL_AGENCY_INFORMATION") | C11: 评估公司相关信息
B12: =HYPERLINK("#APPRAISAL_AGENCY_QUALIFICATION!A1","APPRAISAL_AGENCY_QUALIFICATION") | C12: 评估机构资质表
B13: =HYPERLINK("#APPRAISAL_APPLY_RELATIVE!A1","APPRAISAL_APPLY_RELATIVE") | C13: 评级机构申请关联表
B14: =HYPERLINK("#AWE_BIZFILE_INFO!A1","AWE_BIZFILE_INFO") | C14: 业务文件详情 | D14: 底层表
B15: =HYPERLINK("#AWE_DICT_ERRMSG!A1","AWE_DICT_ERRMSG") | C15: 系统错误报告
B16: =HYPERLINK("#AWE_DO_CATALOG!A1","AWE_DO_CATALOG") | C16: OW显示模板场景
B17: =HYPERLINK("#AWE_DO_COL_VALIDATE!A1","AWE_DO_COL_VALIDATE") | C17: DW字段验证规则
B18: =HYPERLINK("#AWE_DO_EVENT!A1","AWE_DO_EVENT") | C18: OW字段事件
B19: =HYPERLINK("#AWE_DO_FUNCTION!A1","AWE_DO_FUNCTION") | C19: OW脚本方法
B20: =HYPERLINK("#AWE_DO_GROUP!A1","AWE_DO_GROUP") | C20: OW分组信息
B21: =HYPERLINK("#AWE_DO_JS_FUNCTION!A1","AWE_DO_JS_FUNCTION") | C21: OW通用js方法
B22: =HYPERLINK("#AWE_DO_KEYFILTER!A1","AWE_DO_KEYFILTER") | C22: OW关键字查询
B23: =HYPERLINK("#AWE_DO_LIBRARY!A1","AWE_DO_LIBRARY") | C23: OW显示模板字段信息
B24: =HYPERLINK("#AWE_DO_MODES!A1","AWE_DO_MODES") | C24: OW显示模板样式表
B25: =HYPERLINK("#AWE_DO_VALIDATE!A1","AWE_DO_VALIDATE") | C25: 数据验证类
B26: =HYPERLINK("#AWE_DO_VALIDATE_CATALOG!A1","AWE_DO_VALIDATE_CATALOG") | C26: 数据验证业务分类
B27: =HYPERLINK("#AWE_DW_CONTEXT!A1","AWE_DW_CONTEXT") | C27: 显示模型上下文环境
B28: =HYPERLINK("#AWE_FUNCTION_INFO!A1","AWE_FUNCTION_INFO") | C28: 功能点信息
B29: =HYPERLINK("#AWE_FUNCTION_URL!A1","AWE_FUNCTION_URL") | C29: 功能点URL
B30: =HYPERLINK("#AWE_GROUP_CATALOG!A1","AWE_GROUP_CATALOG") | C30: 组合页面目录信息
B31: =HYPERLINK("#CODE_CATALOG!A1","CODE_CATALOG") | C31: 代码类别表;代码类别表
B32: =HYPERLINK("#CODE_LIBRARY!A1","CODE_LIBRARY") | C32: 代码表;代码库
B33: =HYPERLINK("#OBJECTTYPE_CATALOG!A1","OBJECTTYPE_CATALOG") | C33: 对象类型信息表
B34: =HYPERLINK("#OBJECTTYPE_RELA!A1","OBJECTTYPE_RELA") | C34: 对象关联信息表
B35: =HYPERLINK("#OBJECT_ATTRIBUTE!A1","OBJECT_ATTRIBUTE") | C35: 对象属性信息表
B36: =HYPERLINK("#OBJECT_MAXSN!A1","OBJECT_MAXSN") | C36: 系统流水表;系统流水号表
B37: =HYPERLINK("#ROLE_RIGHT!A1","ROLE_RIGHT") | C37: 角色权限表
B38: =HYPERLINK("#SECURITY_AUDIT!A1","SECURITY_AUDIT") | C38: 安全审计
B39: =HYPERLINK("#SELECT_CATALOG!A1","SELECT_CATALOG") | C39: 查询信息表
B40: =HYPERLINK("#USER_FAILEDLIST!A1","USER_FAILEDLIST") | C40: 用户登录失败表;用户痕迹表
B41: =HYPERLINK("#USER_LIST!A1","USER_LIST") | C41: 用户登录表;用户登录列表
B42: =HYPERLINK("#USER_LOGON_SESSION!A1","USER_LOGON_SESSION") | C42: 用户登录session
B43: =HYPERLINK("#USER_MARKINFO!A1","USER_MARKINFO") | C43: 用户记录表;用户痕迹表
B44: =HYPERLINK("#USER_RIGHT!A1","USER_RIGHT") | C44: 用户权限表
B45: =HYPERLINK("#USER_RUNTIME!A1","USER_RUNTIME") | C45: 用户运行时信息
B46: =HYPERLINK("#AWE_GROUP_CLASSIFY!A1","AWE_GROUP_CLASSIFY") | C46: 组合页面分类信息表
B47: =HYPERLINK("#AWE_GROUP_ITEM!A1","AWE_GROUP_ITEM") | C47: 组合页面详细信息表
B48: =HYPERLINK("#AWE_HREF_INFO!A1","AWE_HREF_INFO") | C48: 链接信息
B49: =HYPERLINK("#AWE_JSP_RUNTIME!A1","AWE_JSP_RUNTIME") | C49: jsp页面访问统计表
B50: =HYPERLINK("#AWE_MENU_INFO!A1","AWE_MENU_INFO") | C50: 菜单表;系统菜单表
B51: =HYPERLINK("#AWE_MESSAGE_INFO!A1","AWE_MESSAGE_INFO") | C51: 站内信对象
B52: =HYPERLINK("#AWE_MESSAGE_USER!A1","AWE_MESSAGE_USER") | C52: 站内信发送/关联用户
B53: =HYPERLINK("#AWE_QUERY_INFO!A1","AWE_QUERY_INFO") | C53: 查询配置基本信息
B54: =HYPERLINK("#AWE_QUERY_USER!A1","AWE_QUERY_USER") | C54: 异步查询下载
B55: =HYPERLINK("#AWE_QUICK_HREF!A1","AWE_QUICK_HREF") | C55: 快捷链接
B56: =HYPERLINK("#AWE_RECORD_INFO!A1","AWE_RECORD_INFO") | C56: 特殊信息记录表
B57: =HYPERLINK("#AWE_RIGHT_MENU!A1","AWE_RIGHT_MENU") | C57: 菜单权限表
B58: =HYPERLINK("#AWE_ROLE_FUNCTION!A1","AWE_ROLE_FUNCTION") | C58: 角色和功能点关联表
B59: =HYPERLINK("#AWE_ROLE_MENU!A1","AWE_ROLE_MENU") | C59: 角色菜单表;菜单角色表
B60: =HYPERLINK("#AWE_ROLE_RIGHT!A1","AWE_ROLE_RIGHT") | C60: 角色权限系统表
B61: =HYPERLINK("#AWE_ROLE_URL!A1","AWE_ROLE_URL") | C61: 角色权限URL
B62: =HYPERLINK("#AWE_SHORTCUT!A1","AWE_SHORTCUT") | C62: 系统默认快捷菜单表
B63: =HYPERLINK("#AWE_SHORTCUTITEM!A1","AWE_SHORTCUTITEM") | C63: 系统功能库
B64: =HYPERLINK("#AWE_TASK_INFO!A1","AWE_TASK_INFO") | C64: 任务信息表
B65: =HYPERLINK("#AWE_TASK_PROCESS!A1","AWE_TASK_PROCESS") | C65: 任务进度信息
B66: =HYPERLINK("#AWE_WIZARD_CATALOG!A1","AWE_WIZARD_CATALOG") | C66: 向导目录
B67: =HYPERLINK("#AWE_WIZARD_LIBRARY!A1","AWE_WIZARD_LIBRARY") | C67: 向导定义表;向导定义
B68: =HYPERLINK("#AWE_WIZARD_RUNNER!A1","AWE_WIZARD_RUNNER") | C68: 向导运行记录表
B69: =HYPERLINK("#CLASS_CATALOG!A1","CLASS_CATALOG") | C69: 类定义
B70: =HYPERLINK("#CLASS_METHOD!A1","CLASS_METHOD") | C70: 方法
B71: =HYPERLINK("#CLR_REGISTER_RECORD!A1","CLR_REGISTER_RECORD") | C71: 抵质押登记记录 | D71: 抵质押登记管理
B72: =HYPERLINK("#CLR_COMMODITY_MARKET!A1","CLR_COMMODITY_MARKET") | C72: 大宗商品盯市数据表 | D72: 盯市管理
B73: =HYPERLINK("#CLR_FUND_MARKET!A1","CLR_FUND_MARKET") | C73: 基金盯市数据表
B74: =HYPERLINK("#CLR_FUND_MARKET_DETAIL!A1","CLR_FUND_MARKET_DETAIL") | C74: 基金盯市数据明细表
B75: =HYPERLINK("#CLR_MATERIAL_CATALOG!A1","CLR_MATERIAL_CATALOG") | C75: 商品类别信息表
B76: =HYPERLINK("#CLR_STOCK_MARKET!A1","CLR_STOCK_MARKET") | C76: 股票盯市数据表
B77: =HYPERLINK("#CLR_STOCK_MARKET_DETAIL!A1","CLR_STOCK_MARKET_DETAIL") | C77: 股票盯市数据明细表
B78: =HYPERLINK("#SCENARIO_ARGS!A1","SCENARIO_ARGS") | C78: 风险探测参数信息表 | D78: 风险探测
B79: =HYPERLINK("#SCENARIO_CATALOG!A1","SCENARIO_CATALOG") | C79: 场景分类
B80: =HYPERLINK("#SCENARIO_GROUP!A1","SCENARIO_GROUP") | C80: 场景分组
B81: =HYPERLINK("#SCENARIO_MODEL!A1","SCENARIO_MODEL") | C81: 场景模型
B82: =HYPERLINK("#SCENARIO_RELATIVE!A1","SCENARIO_RELATIVE") | C82: 场景关联表
B83: =HYPERLINK("#USER_WORKTIPS!A1","USER_WORKTIPS") | C83: 用户工作日志表 | D83: 工作台
B84: =HYPERLINK("#WORKTIP_CONDITION!A1","WORKTIP_CONDITION") | C84: 工作情况
B85: =HYPERLINK("#WORKTIP_SUMMARY!A1","WORKTIP_SUMMARY") | C85: 工作汇总
B86: =HYPERLINK("#CLR_VERIFICATION_INFO!A1","CLR_VERIFICATION_INFO") | C86: 核押详情 | D86: 核押信息登记
B87: =HYPERLINK("#CLR_VERIFICATION_RECORD!A1","CLR_VERIFICATION_RECORD") | C87: 核押信息记录
B88: =HYPERLINK("#WF_INSTANCE!A1","WF_INSTANCE") | C88: 流程实例 | D88: 流程表
B89: wf_opinion | C89: 流程意见记录
B90: =HYPERLINK("#WF_WORKITEM!A1","WF_WORKITEM") | C90: 流程工作项(任务)
B91: =HYPERLINK("#WF_ACTIVEINSTANCE!A1","WF_ACTIVEINSTANCE") | C91: 流程的活动(节点)实例
B92: =HYPERLINK("#FLOW_ACTIVITIES!A1","FLOW_ACTIVITIES") | C92: 流程活动(节点)
B93: =HYPERLINK("#FLOW_ATTRIBUTEGROUP!A1","FLOW_ATTRIBUTEGROUP") | C93: 流程活动的属性分组
B94: =HYPERLINK("#FLOW_BUTTONGROUP!A1","FLOW_BUTTONGROUP") | C94: 流程按钮组
B95: =HYPERLINK("#FLOW_BUTTONITEM!A1","FLOW_BUTTONITEM") | C95: 流程按钮
B96: =HYPERLINK("#FLOW_DEF!A1","FLOW_DEF") | C96: 流程定义
B97: =HYPERLINK("#FLOW_DEPLOY!A1","FLOW_DEPLOY") | C97: 流程部署
B98: =HYPERLINK("#FLOW_GROUP!A1","FLOW_GROUP") | C98: 流程分组
B99: =HYPERLINK("#FLOW_HI_MODEL!A1","FLOW_HI_MODEL") | C99: 流程模型的历史
B100: =HYPERLINK("#FLOW_MESSAGE!A1","FLOW_MESSAGE") | C100: 流程信息
B101: =HYPERLINK("#FLOW_PHASETYPE!A1","FLOW_PHASETYPE") | C101: 流程阶段类型
...

Sheet Sheet1
A1: AUDIT_INFO | B1: 审计信息
A2: APPRAISAL_AGENCY | B2: 评估机构
A3: APPRAISAL_AGENCY_APPLY | B3: 评估机构申请信息表
A4: APPRAISAL_AGENCY_APPRAISE | B4: 评价调查信息管理
A5: APPRAISAL_AGENCY_COOPERATION | B5: 评估机构合作协议
A6: APPRAISAL_AGENCY_EVENT | B6: 评估机构事件表
A7: APPRAISAL_AGENCY_EXPENSES | B7: 评估机构费用
A8: APPRAISAL_AGENCY_FILE | B8: 评级机构附件
A9: APPRAISAL_AGENCY_INFORMATION | B9: 评估公司相关信息
A10: APPRAISAL_AGENCY_QUALIFICATION | B10: 评估机构资质表
A11: APPRAISAL_APPLY_RELATIVE | B11: 评级机构申请关联表
A12: CLR_REGISTER_RECORD | B12: 抵质押登记记录
... A70: CCMS_PARTYINF | B70: 支付系统—行名行号表
A71: 审计信息 | B71: AUDIT_INFO | C71: SERIALNO | D71: VARCHAR(32) | E71: NO | F71: 流水号 | H71: VARCHAR | I71: 32
A72: 审计信息 | B72: AUDIT_INFO | C72: OPERATOR | D72: VARCHAR(80) | E72: YES | F72: 操作人 | H72: VARCHAR | I72: 80
A73: 审计信息 | B73: AUDIT_INFO | C73: SERVERADDRESS | D73: VARCHAR(80) | E73: YES | F73: 服务器地址 | H73: VARCHAR | I73: 80
A74: 审计信息 | B74: AUDIT_INFO | C74: CLIENTADDRESS | D74: VARCHAR(80) | E74: YES | F74: 客户端地址 | H74: VARCHAR | I74: 80
A75: 审计信息 | B75: AUDIT_INFO | C75: APPLICATION | D75: VARCHAR(200) | E75: YES | F75: 应用 | H75: VARCHAR | I75: 200
A76: 审计信息 | B76: AUDIT_INFO | C76: ADDITIONALINFO | D76: VARCHAR(200) | E76: YES | F76: 附加信息 | H76: VARCHAR | I76: 200
A77: 审计信息 | B77: AUDIT_INFO | C77: RECORDTYPE | D77: VARCHAR(32) | E77: YES | F77: 记录类型 | H77: VARCHAR | I77: 32
A78: 审计信息 | B78: AUDIT_INFO | C78: RECORDACTION | D78: VARCHAR(32) | E78: YES | F78: 记录动作 | H78: VARCHAR | I78: 32
A79: 审计信息 | B79: AUDIT_INFO | C79: RECORDTARGET | D79: VARCHAR(200) | E79: YES | F79: 记录目标 | H79: VARCHAR | I79: 200
A80: 审计信息 | B80: AUDIT_INFO | C80: AUDITTIME | D80: VARCHAR(32) | E80: YES | F80: 修改时间 | H80: VARCHAR | I80: 32
A81: 审计信息 | B81: AUDIT_INFO | C81: INPUTORGID | D81: VARCHAR(32) | E81: YES | F81: 登记机构 | H81: VARCHAR | I81: 32
A82: 审计信息 | B82: AUDIT_INFO | C82: INPUTUSERID | D82: VARCHAR(32) | E82: YES | F82: 登记人 | H82: VARCHAR | I82: 32
... A92: 评估机构 | B92: APPRAISAL_AGENCY | C92: APPRAISALORGSTATUS | D92: VARCHAR(6) | E92: YES | F92: 评估机构状态 | H92: VARCHAR | I92: 6
A93: 评估机构 | B93: APPRAISAL_AGENCY | C93: REGISTERDATE | D93: DATETIME | E93: YES | F93: 机构成立日期 | H93: DATETIME
A94: 评估机构 | B94: APPRAISAL_AGENCY | C94: ASSETSTYPE | D94: VARCHAR(18) | E94: YES | F94: 可评估资产类型 | H94: VARCHAR | I94: 18
A95: 评估机构 | B95: APPRAISAL_AGENCY | C95: QUALIFYLEVEL | D95: VARCHAR(18) | E95: YES | F95: 执业资质等级 | H95: VARCHAR | I95: 18
A96: 评估机构 | B96: APPRAISAL_AGENCY | C96: ASSESSAREA | D96: VARCHAR(80) | E96: YES | F96: 可估价地域范围 | H96: VARCHAR | I96: 80
A97: 评估机构 | B97: APPRAISAL_AGENCY | C97: CERTNAME | D97: VARCHAR(80) | E97: YES | F97: 资质证书名称 | H97: VARCHAR | I97: 80
A98: 评估机构 | B98: APPRAISAL_AGENCY | C98: CERTID | D98: VARCHAR(32) | E98: YES | F98: 资质证书标号 | H98: VARCHAR | I98: 32
A99: 评估机构 | B99: APPRAISAL_AGENCY | C99: APPROVEDATE | D99: DATETIME | E99: YES | F99: 资质核准日期 | H99: DATETIME
A100: 评估机构 | B100: APPRAISAL_AGENCY | C100: APPROVEENDDATE | D100: DATETIME | E100: YES | F100: 资质到期日期 | H100: DATETIME
A101: 评估机构 | B101: APPRAISAL_AGENCY | C101: DEPARTMENTCARE | D101: VARCHAR(6) | E101: YES | F101: 行业主管部门是否年审 | H101: VARCHAR | I101: 6
A102: 评估机构 | B102: APPRAISAL_AGENCY | C102: INPUTUSER | D102: VARCHAR(80) | E102: YES | F102: 基本信息录入岗 | H102: VARCHAR | I102: 80
A103: 评估机构 | B103: APPRAISAL_AGENCY | C103: CONTINUETIME | D103: INT | E103: YES | F103: 连续执业时间 | H103: INT
A104: 评估机构 | B104: APPRAISAL_AGENCY | C104: BUSINESSSCOPE | D104: VARCHAR(500) | E104: YES | F104: 经营范围 | H104: VARCHAR | I104: 500
A105: 评估机构 | B105: APPRAISAL_AGENCY | C105: REGISTERCAPITAL | D105: DECIMAL(24,6) | E105: YES | F105: 注册资金 | H105: DECIMAL | I105: 24,6
A106: 评估机构 | B106: APPRAISAL_AGENCY | C106: LEGALREP | D106: VARCHAR(80) | E106: YES | F106: 法人代表 | H106: VARCHAR | I106: 80
A107: 评估机构 | B107: APPRAISAL_AGENCY | C107: ORGTELEPHONE | D107: VARCHAR(18) | E107: YES | F107: 评估机构电话 | H107: VARCHAR | I107: 18
A108: 评估机构 | B108: APPRAISAL_AGENCY | C108: ORGFAX | D108: VARCHAR(18) | E108: YES | F108: 评估机构传真电话 | H108: VARCHAR | I108: 18
A109: 评估机构 | B109: APPRAISAL_AGENCY | C109: ORGEMAIL | D109: VARCHAR(32) | E109: YES | F109: 评估机构电子邮箱 | H109: VARCHAR | I109: 32
A110: 评估机构 | B110: APPRAISAL_AGENCY | C110: APPRAISERNUM | D110: INT | E110: YES | F110: 评估师数量 | H110: INT
A111: 评估机构 | B111: APPRAISAL_AGENCY | C111: ISINBLACKLIST | D111: CHAR(1) | E111: YES | F111: 是否黑名单 | H111: CHAR | I111: 1
A112: 评估机构 | B112: APPRAISAL_AGENCY | C112: PARENTORGID | D112: VARCHAR(80) | E112: YES | F112: 所属分行 | H112: VARCHAR | I112: 80
A113: 评估机构 | B113: APPRAISAL_AGENCY | C113: APPRAISALCERTID | D113: VARCHAR(32) | E113: YES | F113: 评估机构证件号码 | H113: VARCHAR | I113: 32
A114: 评估机构 | B114: APPRAISAL_AGENCY | C114: APPRAISALCERTTYPE | D114: VARCHAR(18) | E114: YES | F114: 评估机构证件类型 | H114: VARCHAR | I114: 18
A115: 评估机构 | B115: APPRAISAL_AGENCY | C115: RELACERTID | D115: VARCHAR(32) | E115: YES | F115: 关联机构 | H115: VARCHAR | I115: 32
A116: 评估机构 | B116: APPRAISAL_AGENCY | C116: TEMPSAVEFLAG | D116: CHAR(1) | E116: YES | F116: 暂存标志 | H116: CHAR | I116: 1
A117: 评估机构 | B117: APPRAISAL_AGENCY | C117: ISINALERTLIST | D117: CHAR(1) | E117: YES | F117: 警示标识 | H117: CHAR | I117: 1
A118: 评估机构 | B118: APPRAISAL_AGENCY | C118: INPUTUSERID | D118: VARCHAR(32) | E118: YES | F118: 登记人 | H118: VARCHAR | I118: 32
A119: 评估机构 | B119: APPRAISAL_AGENCY | C119: INPUTORGID | D119: VARCHAR(32) | E119: YES | F119: 登记机构 | H119: VARCHAR | I119: 32
A120: 评估机构 | B120: APPRAISAL_AGENCY | C120: INPUTDATE | D120: DATETIME | E120: YES | F120: 登记日期 | H120: DATETIME
A121: 评估机构 | B121: APPRAISAL_AGENCY | C121: UPDATEUSERID | D121: VARCHAR(32) | E121: YES | F121: 更新人 | H121: VARCHAR | I121: 32
A122: 评估机构 | B122: APPRAISAL_AGENCY | C122: UPDATEORGID | D122: VARCHAR(32) | E122: YES | F122: 更新机构 | H122: VARCHAR | I122: 32
A123: 评估机构 | B123: APPRAISAL_AGENCY | C123: UPDATEDATE | D123: DATETIME | E123: YES | F123: 更新日期 | H123: DATETIME
A124: 评估机构 | B124: APPRAISAL_AGENCY | C124: REMARK | D124: VARCHAR(1000) | E124: YES | F124: 备注 | H124: VARCHAR | I124: 1000
A125: 评估机构 | B125: APPRAISAL_AGENCY | C125: CORPORGID | D125: VARCHAR(32) | E125: YES | F125: 法人机构编号 | H125: VARCHAR | I125: 32
A126: 评估机构 | B126: APPRAISAL_AGENCY | C126: ISONLINE | D126: VARCHAR(6) | E126: YES | F126: 线上评估是否启用 | H126: VARCHAR | I126: 6
A127: 评估机构申请信息表 | B127: APPRAISAL_AGENCY_APPLY | C127: EVENTSERIALNO | D127: VARCHAR(32) | E127: NO | F127: 评估机构事件编号 | H127: VARCHAR | I127: 32
A128: 评估机构申请信息表 | B128: APPRAISAL_AGENCY_APPLY | C128: APPLYTYPE | D128: VARCHAR(32) | E128: YES | F128: 申请类型 | H128: VARCHAR | I128: 32
A129: 评估机构申请信息表 | B129: APPRAISAL_AGENCY_APPLY | C129: APPROVESTATUS | D129: VARCHAR(32) | E129: YES | F129: 申请状态 | H129: VARCHAR | I129: 32
A130: 评估机构申请信息表 | B130: APPRAISAL_AGENCY_APPLY | C130: FLOWTYPE | D130: VARCHAR(32) | E130: YES | F130: 流程类型 | H130: VARCHAR | I130: 32
A131: 评估机构申请信息表 | B131: APPRAISAL_AGENCY_APPLY | C131: INPUTUSERID | D131: VARCHAR(32) | E131: YES | F131: 登记人 | H131: VARCHAR | I131: 32
A132: 评估机构申请信息表 | B132: APPRAISAL_AGENCY_APPLY | C132: INPUTORGID | D132: VARCHAR(32) | E132: YES | F132: 登记机构 | H132: VARCHAR | I132: 32
A133: 评估机构申请信息表 | B133: APPRAISAL_AGENCY_APPLY | C133: INPUTDATE | D133: DATETIME | E133: YES | F133: 登记日期 | H133: DATETIME
A134: 评估机构申请信息表 | B134: APPRAISAL_AGENCY_APPLY | C134: UPDATEUSERID | D134: VARCHAR(32) | E134: YES | F134: 更新人 | H134: VARCHAR | I134: 32
A135: 评估机构申请信息表 | B135: APPRAISAL_AGENCY_APPLY | C135: UPDATEORGID | D135: VARCHAR(32) | E135: YES | F135: 更新机构 | H135: VARCHAR | I135: 32
A136: 评估机构申请信息表 | B136: APPRAISAL_AGENCY_APPLY | C136: UPDATEDATE | D136: DATETIME | E136: YES | F136: 更新日期 | H136: DATETIME
A137: 评估机构申请信息表 | B137: APPRAISAL_AGENCY_APPLY | C137: REMARK | D137: VARCHAR(500) | E137: YES | F137: 备注 | H137: VARCHAR | I137: 500
A138: 评估机构申请信息表 | B138: APPRAISAL_AGENCY_APPLY | C138: CORPORGID | D138: VARCHAR(32) | E138: YES | F138: 法人机构编号 | H138: VARCHAR | I138: 32
A139: 评价调查信息管理 | B139: APPRAISAL_AGENCY_APPRAISE | C139: EVENTSERIALNO | D139: VARCHAR(32) | E139: NO | F139: 评估机构事件编号 | H139: VARCHAR | I139: 32
A140: 评价调查信息管理 | B140: APPRAISAL_AGENCY_APPRAISE | C140: EVENTTYPE | D140: VARCHAR(32) | E140: YES | F140: 事件类型 | H140: VARCHAR | I140: 32
A141: 评价调查信息管理 | B141: APPRAISAL_AGENCY_APPRAISE | C141: CLRID | D141: VARCHAR(32) | E141: YES | F141: 抵质押品编号 | H141: VARCHAR | I141: 32
A142: 评价调查信息管理 | B142: APPRAISAL_AGENCY_APPRAISE | C142: BUSINESSTYPE | D142: VARCHAR(18) | E142: YES | F142: 委托业务类型 | H142: VARCHAR | I142: 18
A143: 评价调查信息管理 | B143: APPRAISAL_AGENCY_APPRAISE | C143: PERSONFEEDBACK | D143: VARCHAR(1000) | E143: YES | F143: 人员反馈事项 | H143: VARCHAR | I143: 1000
A144: 评价调查信息管理 | B144: APPRAISAL_AGENCY_APPRAISE | C144: OTHERFEEDBACK | D144: VARCHAR(1000) | E144: YES | F144: 其他反馈事项 | H144: VARCHAR | I144: 1000
A145: 评价调查信息管理 | B145: APPRAISAL_AGENCY_APPRAISE | C145: FEEDMATTERADD | D145: VARCHAR(1000) | E145: YES | F145: 人员反馈事项补充 | H145: VARCHAR | I145: 1000
A146: 评价调查信息管理 | B146: APPRAISAL_AGENCY_APPRAISE | C146: APPRAISALDATE | D146: DATETIME | E146: YES | F146: 评价日期 | H146: DATETIME
A147: 评价调查信息管理 | B147: APPRAISAL_AGENCY_APPRAISE | C147: INPUTUSERID | D147: VARCHAR(32) | E147: YES | F147: 登记人 | H147: VARCHAR | I147: 32
A148: 评价调查信息管理 | B148: APPRAISAL_AGENCY_APPRAISE | C148: INPUTORGID | D148: VARCHAR(32) | E148: YES | F148: 登记机构 | H148: VARCHAR | I148: 32
A149: 评价调查信息管理 | B149: APPRAISAL_AGENCY_APPRAISE | C149: INPUTDATE | D149: DATETIME | E149: YES | F149: 登记日期 | H149: DATETIME
A150: 评价调查信息管理 | B150: APPRAISAL_AGENCY_APPRAISE | C150: UPDATEUSERID | D150: VARCHAR(32) | E150: YES | F150: 更新人 | H150: VARCHAR | I150: 32
A151: 评价调查信息管理 | B151: APPRAISAL_AGENCY_APPRAISE | C151: UPDATEORGID | D151: VARCHAR(32) | E151: YES | F151: 更新机构 | H151: VARCHAR | I151: 32
A152: 评价调查信息管理 | B152: APPRAISAL_AGENCY_APPRAISE | C152: UPDATEDATE | D152: DATETIME | E152: YES | F152: 更新日期 | H152: DATETIME
A153: 评价调查信息管理 | B153: APPRAISAL_AGENCY_APPRAISE | C153: REMARK | D153: VARCHAR(1000) | E153: YES | F153: 备注 | H153: VARCHAR | I153: 1000
A154: 评价调查信息管理 | B154: APPRAISAL_AGENCY_APPRAISE | C154: CORPORGID | D154: VARCHAR(32) | E154: YES | F154: 法人机构编号 | H154: VARCHAR | I154: 32
A155: 评价调查信息管理 | B155: APPRAISAL_AGENCY_APPRAISE | C155: OPINION | D155: VARCHAR(4000) | E155: YES | F155: 人员总体意见 | H155: VARCHAR | I155: 4000
A156: 评估机构合作协议 | B156: APPRAISAL_AGENCY_COOPERATION | C156: SERIALNO | D156: VARCHAR(32) | E156: NO | F156: 流水号 | H156: VARCHAR | I156: 32
A157: 评估机构合作协议 | B157: APPRAISAL_AGENCY_COOPERATION | C157: AGRMID | D157: VARCHAR(32) | E157: YES | F157: 合作协议编号 | H157: VARCHAR | I157: 32
A158: 评估机构合作协议 | B158: APPRAISAL_AGENCY_COOPERATION | C158: APPRAISALORGID | D158: VARCHAR(32) | E158: YES | F158: 评估机构编号 | H158: VARCHAR | I158: 32
A159: 评估机构合作协议 | B159: APPRAISAL_AGENCY_COOPERATION | C159: APPRAISALAPPLYNO | D159: VARCHAR(32) | E159: YES | F159: 评估机构流程申请编号 | H159: VARCHAR | I159: 32
A160: 评估机构合作协议 | B160: APPRAISAL_AGENCY_COOPERATION | C160: EFFECTIVEDATE | D160: DATETIME | E160: YES | F160: 生效日期 | H160: DATETIME
A161: 评估机构合作协议 | B161: APPRAISAL_AGENCY_COOPERATION | C161: EXPIRYDATE | D161: DATETIME | E161: YES | F161: 失效日期 | H161: DATETIME
A162: 评估机构合作协议 | B162: APPRAISAL_AGENCY_COOPERATION | C162: STATUS | D162: VARCHAR(6) | E162: YES | F162: 状态 | H162: VARCHAR | I162: 6
A163: 评估机构合作协议 | B163: APPRAISAL_AGENCY_COOPERATION | C163: BUSINESSTYPE | D163: VARCHAR(18) | E163: YES | F163: 开展业务种类 | H163: VARCHAR | I163: 18
A164: 评估机构合作协议 | B164: APPRAISAL_AGENCY_COOPERATION | C164: RISKDEPOSIT | D164: DECIMAL(24,6) | E164: YES | F164: 风险保证金金额 | H164: DECIMAL | I164: 24,6
A165: 评估机构合作协议 | B165: APPRAISAL_AGENCY_COOPERATION | C165: PAYDEPOSITDATE | D165: DATETIME | E165: YES | F165: 风险保证金交存日期 | H165: DATETIME
A166: 评估机构合作协议 | B166: APPRAISAL_AGENCY_COOPERATION | C166: RELIEVEDEPOSITDATES | D166: DATETIME | E166: YES | F166: 合作协议解除日期 | H166: DATETIME
...

Sheet Sheet2

Sheet 新增字段查找
K2: EQ
S3: 列名 | T3: 长度 | V3: 注释 | W3: 码值 | X3: 备注 | AA3: 备注
C4: 开始票据区间 | D4: BILLRANGESTART | E4: varchar(20) | F4: YES | G4: 开始票据区间 | N4: =O4&P4&Q4 | O4: =IFERROR(VLOOKUP( | P4: V4 | Q4: ,新增字段查找!C4:I500,2,FALSE),"") | S4: =IFERROR(VLOOKUP(V4,新增字段查找!C4:I500,2,FALSE),"") | T4: =IFERROR(VLOOKUP(V4,新增字段查找!C4:I500,3,FALSE),"") | U4: YES | V4: 客户名称 | W4: =IFERROR(VLOOKUP(V4,新增字段查找!C4:I500,6,FALSE),"") | X4: =IFERROR(VLOOKUP(V4,新增字段查找!C4:I500,7,FALSE),"") | AA4: =IFERROR(VLOOKUP(P4,新增字段查找!C4:I37,7,FALSE),"")
C5: 截止票据区间 | D5: BILLRANGEEND | E5: varchar(20) | F5: YES | G5: 截止票据区间 | M5: =VLOOKUP("YES",F4:G37,2,FALSE) | N5: =O5&P5&Q5 | O5: =IFERROR(VLOOKUP( | P5: V5 | Q5: ,新增字段查找!C4:I500,2,FALSE),"") | S5: =IFERROR(VLOOKUP(V5,新增字段查找!C4:I500,2,FALSE),"") | T5: =IFERROR(VLOOKUP(V5,新增字段查找!C4:I500,3,FALSE),"") | U5: YES | V5: 客户号 | W5: =IFERROR(VLOOKUP(V5,新增字段查找!C4:I500,6,FALSE),"") | X5: =IFERROR(VLOOKUP(V5,新增字段查找!C4:I500,7,FALSE),"") | AA5: =IFERROR(VLOOKUP(P5,新增字段查找!C4:I37,7,FALSE),"")
C6: 冻结止付编号 | D6: FRZNO | E6: varchar(32) | F6: YES | G6: 冻结止付编号 | N6: =O6&P6&Q6 | O6: =IFERROR(VLOOKUP( | P6: V6 | Q6: ,新增字段查找!C4:I500,2,FALSE),"") | S6: =IFERROR(VLOOKUP(V6,新增字段查找!C4:I500,2,FALSE),"") | T6: =IFERROR(VLOOKUP(V6,新增字段查找!C4:I500,3,FALSE),"") | U6: YES | V6: 项目立项批文文号 | W6: =IFERROR(VLOOKUP(V6,新增字段查找!C4:I500,6,FALSE),"") | X6: =IFERROR(VLOOKUP(V6,新增字段查找!C4:I500,7,FALSE),"") | AA6: =IFERROR(VLOOKUP(P6,新增字段查找!C4:I37,7,FALSE),"")
C7: 存单介质/票据介质 | D7: BILLMEDIUM | E7: varchar(6) | F7: YES | G7: 存单介质/票据介质 | I7: 1-纸质、2-电子 | N7: =O7&P7&Q7 | O7: =IFERROR(VLOOKUP( | P7: V7 | Q7: ,新增字段查找!C4:I500,2,FALSE),"") | S7: =IFERROR(VLOOKUP(V7,新增字段查找!C4:I500,2,FALSE),"") | T7: =IFERROR(VLOOKUP(V7,新增字段查找!C4:I500,3,FALSE),"") | U7: YES | V7: 收费权确认文号 | W7: =IFERROR(VLOOKUP(V7,新增字段查找!C4:I500,6,FALSE),"") | X7: =IFERROR(VLOOKUP(V7,新增字段查找!C4:I500,7,FALSE),"") | AA7: =IFERROR(VLOOKUP(P7,新增字段查找!C4:I37,7,FALSE),"")
C8: 质押物登记情况 | D8: REGISTERINFO | E8: varchar(500) | F8: YES | G8: 质押物登记情况 | N8: =O8&P8&Q8 | O8: =IFERROR(VLOOKUP( | P8: V8 | Q8: ,新增字段查找!C4:I500,2,FALSE),"") | S8: =IFERROR(VLOOKUP(V8,新增字段查找!C4:I500,2,FALSE),"") | T8: =IFERROR(VLOOKUP(V8,新增字段查找!C4:I500,3,FALSE),"") | U8: YES | V8: 可质押批复文号 | W8: =IFERROR(VLOOKUP(V8,新增字段查找!C4:I500,6,FALSE),"") | X8: =IFERROR(VLOOKUP(V8,新增字段查找!C4:I500,7,FALSE),"") | AA8: =IFERROR(VLOOKUP(P8,新增字段查找!C4:I37,7,FALSE),"")
C9: 冻结状态/冻结类型 | D9: FRZSTATUS | E9: varchar(6) | F9: YES | G9: 冻结状态/冻结类型 | I9: 冻结类型：1.冻结 2.未冻结 | N9: =O9&P9&Q9 | O9: =IFERROR(VLOOKUP( | P9: V9 | Q9: ,新增字段查找!C4:I500,2,FALSE),"") | S9: =IFERROR(VLOOKUP(V9,新增字段查找!C4:I500,2,FALSE),"") | T9: =IFERROR(VLOOKUP(V9,新增字段查找!C4:I500,3,FALSE),"") | U9: YES | V9: 币种 | W9: =IFERROR(VLOOKUP(V9,新增字段查找!C4:I500,6,FALSE),"") | X9: =IFERROR(VLOOKUP(V9,新增字段查找!C4:I500,7,FALSE),"") | AA9: =IFERROR(VLOOKUP(P9,新增字段查找!C4:I37,7,FALSE),"")
C10: 支出类型 | D10: PAYOUTTYPE | E10: varchar(6) | F10: YES | G10: 支出类型 | I10: 01 -密码 、 02- 证件 、03 -印鉴 | N10: =O10&P10&Q10 | O10: =IFERROR(VLOOKUP( | P10: V10 | Q10: ,新增字段查找!C4:I500,2,FALSE),"") | S10: =IFERROR(VLOOKUP(V10,新增字段查找!C4:I500,2,FALSE),"") | T10: =IFERROR(VLOOKUP(V10,新增字段查找!C4:I500,3,FALSE),"") | U10: YES | V10: 权利取得价值 | W10: =IFERROR(VLOOKUP(V10,新增字段查找!C4:I500,6,FALSE),"") | X10: =IFERROR(VLOOKUP(V10,新增字段查找!C4:I500,7,FALSE),"") | AA10: =IFERROR(VLOOKUP(P10,新增字段查找!C4:I37,7,FALSE),"")
C11: 出质人贷款卡号 | D11: LOANCARDNO | E11: varchar(32) | F11: YES | G11: 出质人贷款卡号 | N11: =O11&P11&Q11 | O11: =IFERROR(VLOOKUP( | P11: V11 | Q11: ,新增字段查找!C4:I500,2,FALSE),"") | S11: =IFERROR(VLOOKUP(V11,新增字段查找!C4:I500,2,FALSE),"") | T11: =IFERROR(VLOOKUP(V11,新增字段查找!C4:I500,3,FALSE),"") | U11: YES | V11: 是否在人行应收账款系统登记 | W11: =IFERROR(VLOOKUP(V11,新增字段查找!C4:I500,6,FALSE),"") | X11: =IFERROR(VLOOKUP(V11,新增字段查找!C4:I500,7,FALSE),"") | AA11: =IFERROR(VLOOKUP(P11,新增字段查找!C4:I37,7,FALSE),"")
C12: 款项 | D12: SELLAGRENO | E12: varchar(32) | F12: YES | G12: 款项 | N12: =O12&P12&Q12 | O12: =IFERROR(VLOOKUP( | P12: V12 | Q12: ,新增字段查找!C4:I500,2,FALSE),"") | S12: =IFERROR(VLOOKUP(V12,新增字段查找!C4:I500,2,FALSE),"") | T12: =IFERROR(VLOOKUP(V12,新增字段查找!C4:I500,3,FALSE),"") | U12: YES | V12: 贷款卡卡号/出质人贷款卡卡号 | W12: =IFERROR(VLOOKUP(V12,新增字段查找!C4:I500,6,FALSE),"") | X12: =IFERROR(VLOOKUP(V12,新增字段查找!C4:I500,7,FALSE),"") | AA12: =IFERROR(VLOOKUP(P12,新增字段查找!C4:I37,7,FALSE),"")
C13: 预计变现值 | D13: REALIZATIONVALUE | E13: decimal(24,6) | F13: YES | G13: 预计变现值 | K13: =I14 | N13: =O13&P13&Q13 | O13: =IFERROR(VLOOKUP( | P13: V13 | Q13: ,新增字段查找!C4:I500,2,FALSE),"") | S13: =IFERROR(VLOOKUP(V13,新增字段查找!C4:I500,2,FALSE),"") | T13: =IFERROR(VLOOKUP(V13,新增字段查找!C4:I500,3,FALSE),"") | U13: YES | V13: 是否需要约定回款路径 | W13: =IFERROR(VLOOKUP(V13,新增字段查找!C4:I500,6,FALSE),"") | X13: =IFERROR(VLOOKUP(V13,新增字段查找!C4:I500,7,FALSE),"") | AA13: =IFERROR(VLOOKUP(P13,新增字段查找!C4:I37,7,FALSE),"")
C14: 预计变现成本 | D14: REALIZATIONCOST | E14: decimal(24,6) | F14: YES | G14: 预计变现成本 | N14: =O14&P14&Q14 | O14: =IFERROR(VLOOKUP( | P14: V14 | Q14: ,新增字段查找!C4:I500,2,FALSE),"") | S14: =IFERROR(VLOOKUP(V14,新增字段查找!C4:I500,2,FALSE),"") | T14: =IFERROR(VLOOKUP(V14,新增字段查找!C4:I500,3,FALSE),"") | U14: YES | V14: 帐龄 | W14: =IFERROR(VLOOKUP(V14,新增字段查找!C4:I500,6,FALSE),"") | X14: =IFERROR(VLOOKUP(V14,新增字段查找!C4:I500,7,FALSE),"") | AA14: =IFERROR(VLOOKUP(P14,新增字段查找!C4:I37,7,FALSE),"")
C15: 是否我行存单 | D15: ISOWNDEPOSIT | E15: varchar(6) | F15: YES | G15: 是否我行存单 | N15: =O15&P15&Q15 | O15: =IFERROR(VLOOKUP( | P15: V15 | Q15: ,新增字段查找!C4:I500,2,FALSE),"") | S15: =IFERROR(VLOOKUP(V15,新增字段查找!C4:I500,2,FALSE),"") | T15: =IFERROR(VLOOKUP(V15,新增字段查找!C4:I500,3,FALSE),"") | U15: YES | V15: 应收账款渠道类型 | W15: =IFERROR(VLOOKUP(V15,新增字段查找!C4:I500,6,FALSE),"") | X15: =IFERROR(VLOOKUP(V15,新增字段查找!C4:I500,7,FALSE),"") | AA15: =IFERROR(VLOOKUP(P15,新增字段查找!C4:I37,7,FALSE),"")
C16: 保证金比例/持有股权比例 | D16: MARGINRATIO | E16: decimal(18,8) | F16: YES | G16: 保证金比例/持有股权比例 | N16: =O16&P16&Q16 | O16: =IFERROR(VLOOKUP( | P16: V16 | Q16: ,新增字段查找!C4:I500,2,FALSE),"") | S16: =IFERROR(VLOOKUP(V16,新增字段查找!C4:I500,2,FALSE),"") | T16: =IFERROR(VLOOKUP(V16,新增字段查找!C4:I500,3,FALSE),"") | U16: YES | V16: 预计变现值 | W16: =IFERROR(VLOOKUP(V16,新增字段查找!C4:I500,6,FALSE),"") | X16: =IFERROR(VLOOKUP(V16,新增字段查找!C4:I500,7,FALSE),"") | AA16: =IFERROR(VLOOKUP(P16,新增字段查找!C4:I37,7,FALSE),"")
C17: 其他特别约定 | D17: OTHERAGREEMENTS | E17: varchar(200) | F17: YES | G17: 其他特别约定 | N17: =O17&P17&Q17 | O17: =IFERROR(VLOOKUP( | P17: V17 | Q17: ,新增字段查找!C4:I500,2,FALSE),"") | S17: =IFERROR(VLOOKUP(V17,新增字段查找!C4:I500,2,FALSE),"") | T17: =IFERROR(VLOOKUP(V17,新增字段查找!C4:I500,3,FALSE),"") | U17: YES | V17: 预计变现成本 | W17: =IFERROR(VLOOKUP(V17,新增字段查找!C4:I500,6,FALSE),"") | X17: =IFERROR(VLOOKUP(V17,新增字段查找!C4:I500,7,FALSE),"") | AA17: =IFERROR(VLOOKUP(P17,新增字段查找!C4:I37,7,FALSE),"")
C18: 核保时间 | D18: UNDERWRITINGDATE | E18: datetime | F18: YES | G18: 核保时间 | N18: =O18&P18&Q18 | O18: =IFERROR(VLOOKUP( | P18: V18 | Q18: ,新增字段查找!C4:I500,2,FALSE),"") | S18: =IFERROR(VLOOKUP(V18,新增字段查找!C4:I500,2,FALSE),"") | T18: =IFERROR(VLOOKUP(V18,新增字段查找!C4:I500,3,FALSE),"") | U18: YES | V18: 权证号码 | W18: =IFERROR(VLOOKUP(V18,新增字段查找!C4:I500,6,FALSE),"") | X18: =IFERROR(VLOOKUP(V18,新增字段查找!C4:I500,7,FALSE),"") | AA18: =IFERROR(VLOOKUP(P18,新增字段查找!C4:I37,7,FALSE),"")
C19: 核保人 | D19: UNDERWRITER | E19: varchar(32) | F19: YES | G19: 核保人 | N19: =O19&P19&Q19 | O19: =IFERROR(VLOOKUP( | P19: V19 | Q19: ,新增字段查找!C4:I500,2,FALSE),"") | S19: =IFERROR(VLOOKUP(V19,新增字段查找!C4:I500,2,FALSE),"") | T19: =IFERROR(VLOOKUP(V19,新增字段查找!C4:I500,3,FALSE),"") | U19: YES | V19: 买方客户号 | W19: =IFERROR(VLOOKUP(V19,新增字段查找!C4:I500,6,FALSE),"") | X19: =IFERROR(VLOOKUP(V19,新增字段查找!C4:I500,7,FALSE),"") | AA19: =IFERROR(VLOOKUP(P19,新增字段查找!C4:I37,7,FALSE),"")
C20: 接待人姓名 | D20: RECEPTIONISTNAME | E20: varchar(32) | F20: YES | G20: 接待人姓名 | N20: =O20&P20&Q20 | O20: =IFERROR(VLOOKUP( | P20: V20 | Q20: ,新增字段查找!C4:I500,2,FALSE),"") | S20: =IFERROR(VLOOKUP(V20,新增字段查找!C4:I500,2,FALSE),"") | T20: =IFERROR(VLOOKUP(V20,新增字段查找!C4:I500,3,FALSE),"") | U20: YES | V20: MDM核心企业编码 | W20: =IFERROR(VLOOKUP(V20,新增字段查找!C4:I500,6,FALSE),"") | X20: =IFERROR(VLOOKUP(V20,新增字段查找!C4:I500,7,FALSE),"") | AA20: =IFERROR(VLOOKUP(P20,新增字段查找!C4:I37,7,FALSE),"")
C21: 接待人职务 | D21: RECEPTIONISTPOSITION | E21: varchar(32) | F21: YES | G21: 接待人职务 | N21: =O21&P21&Q21 | O21: =IFERROR(VLOOKUP( | P21: V21 | Q21: ,新增字段查找!C4:I500,2,FALSE),"") | S21: =IFERROR(VLOOKUP(V21,新增字段查找!C4:I500,2,FALSE),"") | T21: =IFERROR(VLOOKUP(V21,新增字段查找!C4:I500,3,FALSE),"") | U21: YES | V21: 卖方客户号 | W21: =IFERROR(VLOOKUP(V21,新增字段查找!C4:I500,6,FALSE),"") | X21: =IFERROR(VLOOKUP(V21,新增字段查找!C4:I500,7,FALSE),"") | AA21: =IFERROR(VLOOKUP(P21,新增字段查找!C4:I37,7,FALSE),"")
C22: 担保意见 | D22: GUARANTEEOPINION | E22: varchar(200) | F22: YES | G22: 担保意见 | N22: =O22&P22&Q22 | O22: =IFERROR(VLOOKUP( | P22: V22 | Q22: ,新增字段查找!C4:I500,2,FALSE),"") | S22: =IFERROR(VLOOKUP(V22,新增字段查找!C4:I500,2,FALSE),"") | T22: =IFERROR(VLOOKUP(V22,新增字段查找!C4:I500,3,FALSE),"") | U22: YES | V22: 应收账款已结算金额及其他扣除项 | W22: =IFERROR(VLOOKUP(V22,新增字段查找!C4:I500,6,FALSE),"") | X22: =IFERROR(VLOOKUP(V22,新增字段查找!C4:I500,7,FALSE),"") | AA22: =IFERROR(VLOOKUP(P22,新增字段查找!C4:I37,7,FALSE),"")
C23: 债券利率类型 | D23: RATETYPE | E23: varchar(6) | F23: YES | G23: 债券利率类型 | N23: =O23&P23&Q23 | O23: =IFERROR(VLOOKUP( | P23: V23 | Q23: ,新增字段查找!C4:I500,2,FALSE),"") | S23: =IFERROR(VLOOKUP(V23,新增字段查找!C4:I500,2,FALSE),"") | T23: =IFERROR(VLOOKUP(V23,新增字段查找!C4:I500,3,FALSE),"") | U23: YES | V23: 应收账款转让申请号 | W23: =IFERROR(VLOOKUP(V23,新增字段查找!C4:I500,6,FALSE),"") | X23: =IFERROR(VLOOKUP(V23,新增字段查找!C4:I500,7,FALSE),"") | AA23: =IFERROR(VLOOKUP(P23,新增字段查找!C4:I37,7,FALSE),"")
C24: 是否需要办理止付 | D24: ISSTOPPAYMENTREQUIRED | E24: varchar(6) | F24: YES | G24: 是否需要办理止付 | N24: =O24&P24&Q24 | O24: =IFERROR(VLOOKUP( | P24: V24 | Q24: ,新增字段查找!C4:I500,2,FALSE),"") | S24: =IFERROR(VLOOKUP(V24,新增字段查找!C4:I500,2,FALSE),"") | T24: =IFERROR(VLOOKUP(V24,新增字段查找!C4:I500,3,FALSE),"") | U24: YES | V24: 应收账款转让申请时间 | W24: =IFERROR(VLOOKUP(V24,新增字段查找!C4:I500,6,FALSE),"") | X24: =IFERROR(VLOOKUP(V24,新增字段查找!C4:I500,7,FALSE),"") | AA24: =IFERROR(VLOOKUP(P24,新增字段查找!C4:I37,7,FALSE),"")
C25: 付款行名称 | D25: PAYINGBANKNAME | E25: varchar(32) | F25: YES | G25: 付款行名称 | N25: =O25&P25&Q25 | O25: =IFERROR(VLOOKUP( | P25: V25 | Q25: ,新增字段查找!C4:I500,2,FALSE),"") | S25: =IFERROR(VLOOKUP(V25,新增字段查找!C4:I500,2,FALSE),"") | T25: =IFERROR(VLOOKUP(V25,新增字段查找!C4:I500,3,FALSE),"") | U25: YES | V25: 融资卖方额度号 | W25: =IFERROR(VLOOKUP(V25,新增字段查找!C4:I500,6,FALSE),"") | X25: =IFERROR(VLOOKUP(V25,新增字段查找!C4:I500,7,FALSE),"") | AA25: =IFERROR(VLOOKUP(P25,新增字段查找!C4:I37,7,FALSE),"")
C26: 是否具有真实的商品交易背景 | D26: HASREALTRADEBACKGROUND | E26: varchar(6) | F26: YES | G26: 是否具有真实的商品交易背景 | N26: =O26&P26&Q26 | O26: =IFERROR(VLOOKUP( | P26: V26 | Q26: ,新增字段查找!C4:I500,2,FALSE),"") | S26: =IFERROR(VLOOKUP(V26,新增字段查找!C4:I500,2,FALSE),"") | T26: =IFERROR(VLOOKUP(V26,新增字段查找!C4:I500,3,FALSE),"") | U26: YES | V26: 单笔/池 | W26: =IFERROR(VLOOKUP(V26,新增字段查找!C4:I500,6,FALSE),"") | X26: =IFERROR(VLOOKUP(V26,新增字段查找!C4:I500,7,FALSE),"") | AA26: =IFERROR(VLOOKUP(P26,新增字段查找!C4:I37,7,FALSE),"")
C27: 托收收款保证金账号 | D27: MARGINACCOUNT | E27: varchar(32) | F27: YES | G27: 托收收款保证金账号 | N27: =O27&P27&Q27 | O27: =IFERROR(VLOOKUP( | P27: V27 | Q27: ,新增字段查找!C4:I500,2,FALSE),"") | S27: =IFERROR(VLOOKUP(V27,新增字段查找!C4:I500,2,FALSE),"") | T27: =IFERROR(VLOOKUP(V27,新增字段查找!C4:I500,3,FALSE),"") | U27: YES | V27: 池编号 | W27: =IFERROR(VLOOKUP(V27,新增字段查找!C4:I500,6,FALSE),"") | X27: =IFERROR(VLOOKUP(V27,新增字段查找!C4:I500,7,FALSE),"") | AA27: =IFERROR(VLOOKUP(P27,新增字段查找!C4:I37,7,FALSE),"")
C28: 上市公司是否盈利 | D28: ISPROFITABLE | E28: varchar(6) | F28: YES | G28: 上市公司是否盈利 | N28: =O28&P28&Q28 | O28: =IFERROR(VLOOKUP( | P28: V28 | Q28: ,新增字段查找!C4:I500,2,FALSE),"") | S28: =IFERROR(VLOOKUP(V28,新增字段查找!C4:I500,2,FALSE),"") | T28: =IFERROR(VLOOKUP(V28,新增字段查找!C4:I500,3,FALSE),"") | U28: YES | V28: 期限（天） | W28: =IFERROR(VLOOKUP(V28,新增字段查找!C4:I500,6,FALSE),"") | X28: =IFERROR(VLOOKUP(V28,新增字段查找!C4:I500,7,FALSE),"") | AA28: =IFERROR(VLOOKUP(P28,新增字段查找!C4:I37,7,FALSE),"")
C29: 质押基金份额占总额 | D29: SHARERATIO | E29: decimal(18,8) | F29: YES | G29: 质押基金份额占总额 | N29: =O29&P29&Q29 | O29: =IFERROR(VLOOKUP( | P29: V29 | Q29: ,新增字段查找!C4:I500,2,FALSE),"") | S29: =IFERROR(VLOOKUP(V29,新增字段查找!C4:I500,2,FALSE),"") | T29: =IFERROR(VLOOKUP(V29,新增字段查找!C4:I500,3,FALSE),"") | U29: YES | V29: 具体单位名称 | W29: =IFERROR(VLOOKUP(V29,新增字段查找!C4:I500,6,FALSE),"") | X29: =IFERROR(VLOOKUP(V29,新增字段查找!C4:I500,7,FALSE),"") | AA29: =IFERROR(VLOOKUP(P29,新增字段查找!C4:I37,7,FALSE),"")
C30: 保单现金价值确认部门 | D30: CONFIRMDEPARTMENT | E30: varchar(32) | F30: YES | G30: 保单现金价值确认部门 | N30: =O30&P30&Q30 | O30: =IFERROR(VLOOKUP( | P30: V30 | Q30: ,新增字段查找!C4:I500,2,FALSE),"") | S30: =IFERROR(VLOOKUP(V30,新增字段查找!C4:I500,2,FALSE),"") | T30: =IFERROR(VLOOKUP(V30,新增字段查找!C4:I500,3,FALSE),"") | U30: YES | V30: 发票完整性 | W30: =IFERROR(VLOOKUP(V30,新增字段查找!C4:I500,6,FALSE),"") | X30: =IFERROR(VLOOKUP(V30,新增字段查找!C4:I500,7,FALSE),"") | AA30: =IFERROR(VLOOKUP(P30,新增字段查找!C4:I37,7,FALSE),"")
C31: 保险费交缴期限 | D31: PAYMENTPERIOD | E31: datetime | F31: YES | G31: 保险费交缴期限 | N31: =O31&P31&Q31 | O31: =IFERROR(VLOOKUP( | P31: V31 | Q31: ,新增字段查找!C4:I500,2,FALSE),"") | S31: =IFERROR(VLOOKUP(V31,新增字段查找!C4:I500,2,FALSE),"") | T31: =IFERROR(VLOOKUP(V31,新增字段查找!C4:I500,3,FALSE),"") | U31: YES | V31: 质押合同编号 | W31: =IFERROR(VLOOKUP(V31,新增字段查找!C4:I500,6,FALSE),"") | X31: =IFERROR(VLOOKUP(V31,新增字段查找!C4:I500,7,FALSE),"") | AA31: =IFERROR(VLOOKUP(P31,新增字段查找!C4:I37,7,FALSE),"")
C32: 理财质押范围 | D32: PLEDGESCOPE | E32: varchar(6) | F32: YES | G32: 理财质押范围 | I32: 01 本金、02 本金及未来收益 | N32: =O32&P32&Q32 | O32: =IFERROR(VLOOKUP( | P32: V32 | Q32: ,新增字段查找!C4:I500,2,FALSE),"") | S32: =IFERROR(VLOOKUP(V32,新增字段查找!C4:I500,2,FALSE),"") | T32: =IFERROR(VLOOKUP(V32,新增字段查找!C4:I500,3,FALSE),"") | U32: YES | V32: 合同名称 | W32: =IFERROR(VLOOKUP(V32,新增字段查找!C4:I500,6,FALSE),"") | X32: =IFERROR(VLOOKUP(V32,新增字段查找!C4:I500,7,FALSE),"") | AA32: =IFERROR(VLOOKUP(P32,新增字段查找!C4:I37,7,FALSE),"")
C33: 受益凭证 | D33: BENEFICIARYCERTIFICATE | E33: varchar(50) | F33: YES | G33: 受益凭证 | N33: =O33&P33&Q33 | O33: =IFERROR(VLOOKUP( | P33: V33 | Q33: ,新增字段查找!C4:I500,2,FALSE),"") | S33: =IFERROR(VLOOKUP(V33,新增字段查找!C4:I500,2,FALSE),"") | T33: =IFERROR(VLOOKUP(V33,新增字段查找!C4:I500,3,FALSE),"") | U33: YES | V33: 贷款企业法人代表姓名 | W33: =IFERROR(VLOOKUP(V33,新增字段查找!C4:I500,6,FALSE),"") | X33: =IFERROR(VLOOKUP(V33,新增字段查找!C4:I500,7,FALSE),"") | AA33: =IFERROR(VLOOKUP(P33,新增字段查找!C4:I37,7,FALSE),"")
C34: 是否保本型 | D34: ISPRINCIPALGUARANTEED | E34: varchar(6) | F34: YES | G34: 是否保本型 | N34: =O34&P34&Q34 | O34: =IFERROR(VLOOKUP( | P34: V34 | Q34: ,新增字段查找!C4:I500,2,FALSE),"") | S34: =IFERROR(VLOOKUP(V34,新增字段查找!C4:I500,2,FALSE),"") | T34: =IFERROR(VLOOKUP(V34,新增字段查找!C4:I500,3,FALSE),"") | U34: YES | V34: 纸质合同相对人名称 | W34: =IFERROR(VLOOKUP(V34,新增字段查找!C4:I500,6,FALSE),"") | X34: =IFERROR(VLOOKUP(V34,新增字段查找!C4:I500,7,FALSE),"") | AA34: =IFERROR(VLOOKUP(P34,新增字段查找!C4:I37,7,FALSE),"")
C35: 户主/姓名 | D35: ACCOUNTNAME | E35: varchar(32) | F35: YES | G35: 户主/姓名 | N35: =O35&P35&Q35 | O35: =IFERROR(VLOOKUP( | P35: V35 | Q35: ,新增字段查找!C4:I500,2,FALSE),"") | S35: =IFERROR(VLOOKUP(V35,新增字段查找!C4:I500,2,FALSE),"") | T35: =IFERROR(VLOOKUP(V35,新增字段查找!C4:I500,3,FALSE),"") | U35: YES | V35: 合同签订日期 | W35: =IFERROR(VLOOKUP(V35,新增字段查找!C4:I500,6,FALSE),"") | X35: =IFERROR(VLOOKUP(V35,新增字段查找!C4:I500,7,FALSE),"") | AA35: =IFERROR(VLOOKUP(P35,新增字段查找!C4:I37,7,FALSE),"")
C36: 权利凭证编号 | D36: RIGHTCERTNO | E36: varchar(32) | F36: YES | G36: 权利凭证编号 | V36: 客户名称
C37: 质押到期日期 | D37: PLEDGEEXPIRATIONDATE | E37: datetime | F37: YES | G37: 质押到期日期 | V37: 客户号
C38: 权利人贷款卡号 | D38: LOANCARDNO | E38: varchar(32) | F38: YES | G38: 权利人贷款卡号 | V38: 项目立项批文文号
C39: 设备现状 | D39: EQUIPSTATUS | E39: varchar(6) | F39: YES | G39: 设备现状 | I39: 01 -出租、02-占用、03-闲置、04-自用、05-其他 | V39: 收费权确认文号
C40: 抵押物说明 | D40: GUARANTYDESCRIPT | E40: varchar(800) | F40: YES | G40: 抵押物说明 | V40: 可质押批复文号
C41: 权证号 | D41: GUARANTYRIGHTID | E41: varchar(800) | F41: YES | G41: 权证号 | V41: 币种
C42: 是否部分抵押 | D42: ISPARTMORTGAGED | E42: varchar(6) | F42: YES | G42: 是否部分抵押 | V42: 权利取得价值
C43: 预计变现值 | D43: REALIZATIONVALUE | E43: decimal(24,6) | F43: YES | G43: 预计变现值
C44: 预计变现成本 | D44: REALIZATIONCOST | E44: decimal(24,6) | F44: YES | G44: 预计变现成本
C45: 他项权证号 | D45: OTHERSRIGHTID | E45: varchar(100) | F45: YES | G45: 他项权证号
C46: 是否有车辆购置附加税证 | D46: HASVEHICLEBUYTAX | E46: varchar(6) | F46: YES | G46: 是否有车辆购置附加税证
C47: 是否有当年车船使用税证 | D47: HASVEHICLEUSETAX | E47: varchar(6) | F47: YES | G47: 是否有当年车船使用税证
C48: 取得他项权证时间 | D48: OTHERSRIGHTDATE | E48: datetime | F48: YES | G48: 取得他项权证时间
C49: 抵押物登记情况 | D49: REGISTERINFO | E49: varchar(500) | F49: YES | G49: 抵押物登记情况
C50: 此抵押物是否当前申请所购/所抵资产 | D50: ISMORTGAGEDSELF | E50: varchar(6) | F50: YES | G50: 此抵押物是否当前申请所购/所抵资产
C51: 底盘编号 | D51: CHASSISNUMBER | E51: varchar(50) | F51: YES | G51: 底盘编号
C52: 合格证编号 | D52: CERTIFICATENUMBER | E52: varchar(50) | F52: YES | G52: 合格证编号
C53: 机动车登记证编号 | D53: VEHICLECERT | E53: varchar(50) | F53: YES | G53: 机动车登记证编号
C54: 车龄 | D54: VEHICLEAGE | E54: INTEGER(4) | F54: YES | G54: 车龄
... C60: 提车日期 | D60: VEHICLEDATE | E60: datetime | F60: YES | G60: 提车日期
C61: 支出类型 | D61: PAYOUTTYPE | E61: varchar(6) | F61: YES | G61: 支出类型 | I61: 01 -密码 、 02- 证件 、03 -印鉴
C62: 年检是否正常 | D62: ISANNUALTEST | E62: varchar(6) | F62: YES | G62: 年检是否正常
C63: 运输工具类型 | D63: VEHICLETYPE | E63: varchar(200) | F63: YES | G63: 运输工具类型
C64: 船籍 | D64: SHIPNATIONALITY | E64: varchar(32) | F64: YES | G64: 船籍
C65: 是否有航运证 | D65: ISSHIPPINGCERT | E65: varchar(6) | F65: YES | G65: 是否有航运证
C66: 已行驶里程数 | D66: MILEAGE | E66: decimal(24,6) | F66: YES | G66: 已行驶里程数
C67: 权利人 | D67: RIGHTHOLDER | E67: varchar(80) | F67: YES | G67: 权利人
C68: 出质人贷款卡号 | D68: LOANCARDNO | E68: varchar(32) | F68: YES | G68: 出质人贷款卡号
C69: 质押物数量 | D69: GUARANTYAMOUNT | E69: decimal(24,6) | F69: YES | G69: 质押物数量
C70: 权证号 | D70: GUARANTYRIGHTID | E70: varchar(800) | F70: YES | G70: 权证号
C71: 存货价值 | D71: GUARANTYVALUE | E71: decimal(24,6) | F71: YES | G71: 存货价值
C72: 质押物原币种 | D72: CURRENCY | E72: varchar(18) | F72: YES | G72: 质押物原币种 | H72: =HYPERLINK("#码值映射清单!B2469","Currency")
C73: 质押物原价值 | D73: ORIGINALVALUE | E73: decimal(24,6) | F73: YES | G73: 质押物原价值
C74: 预计变现值 | D74: REALIZATIONVALUE | E74: decimal(24,6) | F74: YES | G74: 预计变现值
C75: 预计变现成本 | D75: REALIZATIONCOST | E75: decimal(24,6) | F75: YES | G75: 预计变现成本
C76: 货物购入价值 | D76: PURCHASEDVALUE | E76: decimal(24,6) | F76: YES | G76: 货物购入价值
C77: 存放地点/提货地点 | D77: STORAGELOCATION | E77: varchar(200) | F77: YES | G77: 存放地点/提货地点
C78: 供应商名称 | D78: SUPPLIERNAME | E78: varchar(80) | F78: YES | G78: 供应商名称
C79: 应退未退税金额 | D79: DUETAX | E79: decimal(24,6) | F79: YES | G79: 应退未退税金额
C80: 活畜种类 | D80: LIVESTOCKTYPE | E80: varchar(32) | F80: YES | G80: 活畜种类
C81: 权利人 | D81: RIGHTHOLDER | E81: varchar(80) | F81: YES | G81: 权利人
C82: 矿区地址/注册地址 | D82: MININGADDRESS | E82: varchar(32) | F82: YES | G82: 矿区地址/注册地址
C83: 我行抵押权顺位 | D83: RIGHTSRANK | E83: INTEGER(4) | F83: YES | G83: 我行抵押权顺位
C84: 权利人贷款卡号 | D84: LOANCARDNO | E84: varchar(32) | F84: YES | G84: 权利人贷款卡号
... C103: 林地使用权人/海域使用权人 | D103: RIGHTHOLDER | E103: varchar(80) | F103: YES | G103: 林地使用权人/海域使用权人
C104: 资产用途 | D104: ASSETPURPOSE | E104: varchar(6) | F104: YES | G104: 资产用途 | I104: 01-种植业、02-林业、03-畜牧业、04-渔业生产、05-其他
C105: 发证机关 | D105: ISSUINGAUTHORITY | E105: varchar(32) | F105: YES | G105: 发证机关
C106: 发证日期 | D106: ISSUINGDATE | E106: datetime | F106: YES | G106: 发证日期
C107: 生产经营场所地址 | D107: PRDADDRESS | E107: varchar(80) | F107: YES | G107: 生产经营场所地址
C108: 权利地域范围 | D108: RIGHTSGEOSCOPE | E108: varchar(80) | F108: YES | G108: 权利地域范围
C109: 是否双证合一 | D109: ISCOMBINEDCERT | E109: varchar(6) | G109: 是否双证合一
C110: 所属土地宗地号 | D110: LANDNO | E110: varchar(32) | G110: 所属土地宗地号
C111: 配套设施情况 | D111: FACILITIES | E111: varchar(200) | G111: 配套设施情况
C112: 商标注册地址 | D112: TRADEMARKADDRESS | E112: varchar(100) | F112: YES | G112: 商标注册地址
C113: 出质人贷款卡号 | D113: LOANCARDNO | E113: varchar(32) | F113: YES | G113: 出质人贷款卡号
C114: 收费权类型 | D114: GUARANTYSUBTYPE | E114: varchar(6) | F114: YES | G114: 收费权类型 | I114: 1 -商标专用权、2- 专利权、3-著作权
C115: 币种 | D115: CURRENCY | E115: varchar(18) | F115: YES | G115: 币种 | H115: =HYPERLINK("#码值映射清单!B2469","Currency")
C116: 权利证明文件 | D116: RIGHTCERTDOC | E116: varchar(200) | F116: YES | G116: 权利证明文件
C117: 预计变现值 | D117: REALIZATIONVALUE | E117: decimal(24,6) | F117: YES | G117: 预计变现值
C118: 预计变现成本 | D118: REALIZATIONCOST | E118: decimal(24,6) | F118: YES | G118: 预计变现成本
C119: 专利距离保护期届满时间（年） | D119: PATENTREMAIN | E119: integer(4) | F119: YES | G119: 专利距离保护期届满时间（年）
C120: 著作权权利范围 | D120: COPYRIGHTSCOPE | E120: varchar(200) | F120: YES | G120: 著作权权利范围
C121: 是否按揭 | D121: ISMORTGAGE | E121: varchar(6) | F121: YES | G121: 是否按揭
C122: 所在国家 | D122: COUNTRY | E122: varchar(6) | F122: YES | G122: 所在国家
C123: 预抵押登记完成时间 | D123: PREMORTGAGEDTIME | E123: datetime | F123: YES | G123: 预抵押登记完成时间
C124: 交易价值 | D124: TRADEVALUE | E124: decimal(24,6) | F124: YES | G124: 交易价值
...

Sheet 码值映射清单
B2: CODENO | C2: CODENAME | D2: ITEMNO | E2: ITEMNAME
B3: 码值：IndView
B4: IndView | C4: 个人客户详情视图 | D4: 010 | E4: 客户基本信息
B5: IndView | C5: 个人客户详情视图 | D5: 010010 | E5: 个人概况
B6: IndView | C6: 个人客户详情视图 | D6: 010015 | E6: 农户基本情况
B7: IndView | C7: 个人客户详情视图 | D7: 010020 | E7: 个人经营企业信息
B8: IndView | C8: 个人客户详情视图 | D8: 010030 | E8: 个人摊位厂房信息
B9: IndView | C9: 个人客户详情视图 | D9: 010040 | E9: 家庭成员信息
B10: IndView | C10: 个人客户详情视图 | D10: 010050 | E10: 个人学业履历
B11: IndView | C11: 个人客户详情视图 | D11: 010060 | E11: 个人工作履历
B12: IndView | C12: 个人客户详情视图 | D12: 010070 | E12: 客户涉诉信息
B13: IndView | C13: 个人客户详情视图 | D13: 010080 | E13: 客户大事记
B14: IndView | C14: 个人客户详情视图 | D14: 010090 | E14: 客户关联关系图谱
B15: IndView | C15: 个人客户详情视图 | D15: 010100 | E15: 客户担保关联图谱
... B46: IndView | C46: 个人客户详情视图 | D46: 110030 | E46: 客户引入记录
B47: 码值：文化水平
B48: 文化水平 | C48: 文化水平 | D48: 1 | E48: 初中
B49: 文化水平 | C49: 文化水平 | D49: 2 | E49: 高中
B50: 文化水平 | C50: 文化水平 | D50: 3 | E50: 大专
B51: 文化水平 | C51: 文化水平 | D51: 4 | E51: 本科及以上
B52: 码值：CountryRisk
B53: CountryRisk | C53: 国别风险 | D53: CountryRisk01 | E53: 中国
B54: CountryRisk | C54: 国别风险 | D54: CountryRisk02 | E54: 港澳台
B55: CountryRisk | C55: 国别风险 | D55: CountryRisk03 | E55: 欧洲
B56: CountryRisk | C56: 国别风险 | D56: CountryRisk04 | E56: 美国
B57: CountryRisk | C57: 国别风险 | D57: CountryRisk05 | E57: 日本
B58: CountryRisk | C58: 国别风险 | D58: CountryRisk06 | E58: 新加坡
B59: CountryRisk | C59: 国别风险 | D59: CountryRisk07 | E59: 东南亚其他国家
B60: CountryRisk | C60: 国别风险 | D60: CountryRisk08 | E60: 澳洲
B61: CountryRisk | C61: 国别风险 | D61: CountryRisk09 | E61: 北美
B62: CountryRisk | C62: 国别风险 | D62: CountryRisk10 | E62: 其他
B63: 码值：FamilyStatus
B64: FamilyStatus | C64: 居住状况 | D64: 1 | E64: 自置
B65: FamilyStatus | C65: 居住状况 | D65: 2 | E65: 按揭
B66: FamilyStatus | C66: 居住状况 | D66: 3 | E66: 亲属楼宇
B67: FamilyStatus | C67: 居住状况 | D67: 4 | E67: 集体宿舍
B68: FamilyStatus | C68: 居住状况 | D68: 5 | E68: 租房
B69: FamilyStatus | C69: 居住状况 | D69: 6 | E69: 共有住宅
B70: FamilyStatus | C70: 居住状况 | D70: 7 | E70: 其他
B71: FamilyStatus | C71: 居住状况 | D71: 9 | E71: 未知
B72: 码值：KeepType
B73: KeepType | C73: 存货类型 | D73: 01 | E73: 原材料
B74: KeepType | C74: 存货类型 | D74: 02 | E74: 产成品
B75: KeepType | C75: 存货类型 | D75: 03 | E75: 在产品
B76: KeepType | C76: 存货类型 | D76: 06 | E76: 其他
B77: 码值：DemoInternetCompanyType
B78: DemoInternetCompanyType | D78: 01 | E78: 互联网公司
B79: DemoInternetCompanyType | D79: 0101 | E79: 树图
B80: 码值：PProjectView
B81: PProjectView | C81: 合作方项目申请树图 | D81: 0010 | E81: 合作项目基本信息
B82: PProjectView | C82: 合作方项目申请树图 | D82: 0020 | E82: 项目额度信息
B83: PProjectView | C83: 合作方项目申请树图 | D83: 0030 | E83: 担保额度信息
B84: PProjectView | C84: 合作方项目申请树图 | D84: 0040 | E84: 保证金信息
B85: PProjectView | C85: 合作方项目申请树图 | D85: 0050 | E85: 其他合作方
B86: PProjectView | C86: 合作方项目申请树图 | D86: 0060 | E86: 项下业务要求
B87: PProjectView | C87: 合作方项目申请树图 | D87: 0070 | E87: 附属信息
B88: PProjectView | C88: 合作方项目申请树图 | D88: 007010 | E88: 设备信息
B89: PProjectView | C89: 合作方项目申请树图 | D89: 007020 | E89: 车辆信息
B90: PProjectView | C90: 合作方项目申请树图 | D90: 007030 | E90: 楼盘信息
B91: PProjectView | C91: 合作方项目申请树图 | D91: 0080 | E91: 其他重要信息
B92: 码值：DepositAccountType
B93: DepositAccountType | C93: 存款账户类型 | D93: 01 | E93: 卡
B94: DepositAccountType | C94: 存款账户类型 | D94: 02 | E94: 折
B95: 码值：LAWVALIDITYTYPE
B96: LAWVALIDITYTYPE | C96: 法律有效性 | D96: 01 | E96: 担保合法且手续完整
B97: LAWVALIDITYTYPE | C97: 法律有效性 | D97: 02 | E97: 担保不合法或手续不完整
B98: 码值：ReserveSingleView
B99: ReserveSingleView | C99: 减值计提详情树图 | D99: 010010 | E99: 减值计提信息
B100: ReserveSingleView | C100: 减值计提详情树图 | D100: 010020 | E100: 拨备计提历史
B101: ReserveSingleView | C101: 减值计提详情树图 | D101: 010030 | E101: 影像资料
B102: 码值：创新能力
B103: 创新能力 | C103: 创新能力 | D103: 01 | E103: 公司的创新能力极强，有很多还未应用的已申请专利，且研发费用占比远高于同业水平
B104: 创新能力 | C104: 创新能力 | D104: 02 | E104: 公司的创新能力极强，且研发费用占比高于同业水平
B105: 创新能力 | C105: 创新能力 | D105: 03 | E105: 公司的创新能力一般，且研发费用占比基本持平于同业水平
B106: 创新能力 | C106: 创新能力 | D106: 04 | E106: 公司的创新能力差，且研发费用占比低于同业水平
B107: 码值：ScoreLevel
B108: ScoreLevel | C108: 客户信用等级 | D108: 010 | E108: AAA
B109: ScoreLevel | C109: 客户信用等级 | D109: 020 | E109: AA+
B110: ScoreLevel | C110: 客户信用等级 | D110: 030 | E110: AA
B111: ScoreLevel | C111: 客户信用等级 | D111: 040 | E111: AA-
B112: ScoreLevel | C112: 客户信用等级 | D112: 050 | E112: A+
B113: ScoreLevel | C113: 客户信用等级 | D113: 060 | E113: A
B114: ScoreLevel | C114: 客户信用等级 | D114: 070 | E114: A-
B115: ScoreLevel | C115: 客户信用等级 | D115: 080 | E115: BBB+
B116: ScoreLevel | C116: 客户信用等级 | D116: 090 | E116: BBB
B117: ScoreLevel | C117: 客户信用等级 | D117: 100 | E117: BBB-
B118: ScoreLevel | C118: 客户信用等级 | D118: 110 | E118: BB+
B119: ScoreLevel | C119: 客户信用等级 | D119: 120 | E119: BB
... B125: ScoreLevel | C125: 客户信用等级 | D125: 180 | E125: 无
B126: 码值：AccountFlag
B127: AccountFlag | C127: 存款账号性质 | D127: 1 | E127: 本行存款账户
B128: AccountFlag | C128: 存款账号性质 | D128: 2 | E128: 他行账户
B129: AccountFlag | C129: 存款账号性质 | D129: 3 | E129: 本行信用卡账户
B130: AccountFlag | C130: 存款账号性质 | D130: 4 | E130: 第三方账户
B131: AccountFlag | C131: 存款账号性质 | D131: 5 | E131: 内部账户
B132: 码值：GroupForkView
B133: GroupForkView | C133: 集团详情 | D133: 010 | E133: 集团客户基本情况
B134: GroupForkView | C134: 集团详情 | D134: 020 | E134: 集团家谱
B135: GroupForkView | C135: 集团详情 | D135: 030 | E135: 集团家谱历次已认定版本
B136: GroupForkView | C136: 集团详情 | D136: 040 | E136: 集团家谱复核意见
...

Sheet audit_info
A1: =HYPERLINK("#表结构清单!A1","返回") | B1: 审计信息
B2: 表名 | C2: 列名 | D2: 字段类型 | E2: 是否为空 | F2: 字段注释 | G2: 码值 | H2: 备注 | I2: 修订人 | J2: 修订日期
A3: 审计信息 | B3: audit_info | C3: SERIALNO | D3: varchar(32) | E3: NO | F3: 流水号 | J3: 2023/01/12 | K3: =A3 | L3: =B3 | M3: =F3 | N3: =C3 | O3: =IFERROR(LEFT(D3,FIND("(",D3)-1),D3) | P3: =IFERROR(MID(D3,FIND("(",D3)+1,FIND(")",D3)-FIND("(",D3)-1),"")
A4: 审计信息 | B4: audit_info | C4: OPERATOR | D4: varchar(80) | E4: YES | F4: 操作人 | J4: 2023/01/12 | K4: =A4 | L4: =B4 | M4: =F4 | N4: =C4 | O4: =IFERROR(LEFT(D4,FIND("(",D4)-1),D4) | P4: =IFERROR(MID(D4,FIND("(",D4)+1,FIND(")",D4)-FIND("(",D4)-1),"")
A5: 审计信息 | B5: audit_info | C5: SERVERADDRESS | D5: varchar(80) | E5: YES | F5: 服务器地址 | J5: 2023/01/12 | K5: =A5 | L5: =B5 | M5: =F5 | N5: =C5 | O5: =IFERROR(LEFT(D5,FIND("(",D5)-1),D5) | P5: =IFERROR(MID(D5,FIND("(",D5)+1,FIND(")",D5)-FIND("(",D5)-1),"")
A6: 审计信息 | B6: audit_info | C6: CLIENTADDRESS | D6: varchar(80) | E6: YES | F6: 客户端地址 | J6: 2023/01/12 | K6: =A6 | L6: =B6 | M6: =F6 | N6: =C6 | O6: =IFERROR(LEFT(D6,FIND("(",D6)-1),D6) | P6: =IFERROR(MID(D6,FIND("(",D6)+1,FIND(")",D6)-FIND("(",D6)-1),"")
A7: 审计信息 | B7: audit_info | C7: APPLICATION | D7: varchar(200) | E7: YES | F7: 应用 | J7: 2023/01/12 | K7: =A7 | L7: =B7 | M7: =F7 | N7: =C7 | O7: =IFERROR(LEFT(D7,FIND("(",D7)-1),D7) | P7: =IFERROR(MID(D7,FIND("(",D7)+1,FIND(")",D7)-FIND("(",D7)-1),"")
A8: 审计信息 | B8: audit_info | C8: ADDITIONALINFO | D8: varchar(200) | E8: YES | F8: 附加信息 | J8: 2023/01/12 | K8: =A8 | L8: =B8 | M8: =F8 | N8: =C8 | O8: =IFERROR(LEFT(D8,FIND("(",D8)-1),D8) | P8: =IFERROR(MID(D8,FIND("(",D8)+1,FIND(")",D8)-FIND("(",D8)-1),"")
A9: 审计信息 | B9: audit_info | C9: RECORDTYPE | D9: varchar(32) | E9: YES | F9: 记录类型 | J9: 2023/01/12 | K9: =A9 | L9: =B9 | M9: =F9 | N9: =C9 | O9: =IFERROR(LEFT(D9,FIND("(",D9)-1),D9) | P9: =IFERROR(MID(D9,FIND("(",D9)+1,FIND(")",D9)-FIND("(",D9)-1),"")
A10: 审计信息 | B10: audit_info | C10: RECORDACTION | D10: varchar(32) | E10: YES | F10: 记录动作 | J10: 2023/01/12 | K10: =A10 | L10: =B10 | M10: =F10 | N10: =C10 | O10: =IFERROR(LEFT(D10,FIND("(",D10)-1),D10) | P10: =IFERROR(MID(D10,FIND("(",D10)+1,FIND(")",D10)-FIND("(",D10)-1),"")
A11: 审计信息 | B11: audit_info | C11: RECORDTARGET | D11: varchar(200) | E11: YES | F11: 记录目标 | J11: 2023/01/12 | K11: =A11 | L11: =B11 | M11: =F11 | N11: =C11 | O11: =IFERROR(LEFT(D11,FIND("(",D11)-1),D11) | P11: =IFERROR(MID(D11,FIND("(",D11)+1,FIND(")",D11)-FIND("(",D11)-1),"")
A12: 审计信息 | B12: audit_info | C12: AUDITTIME | D12: varchar(32) | E12: YES | F12: 修改时间 | J12: 2023/01/12 | K12: =A12 | L12: =B12 | M12: =F12 | N12: =C12 | O12: =IFERROR(LEFT(D12,FIND("(",D12)-1),D12) | P12: =IFERROR(MID(D12,FIND("(",D12)+1,FIND(")",D12)-FIND("(",D12)-1),"")
A13: 审计信息 | B13: audit_info | C13: INPUTORGID | D13: varchar(32) | E13: YES | F13: 登记机构 | J13: 2023/01/12 | K13: =A13 | L13: =B13 | M13: =F13 | N13: =C13 | O13: =IFERROR(LEFT(D13,FIND("(",D13)-1),D13) | P13: =IFERROR(MID(D13,FIND("(",D13)+1,FIND(")",D13)-FIND("(",D13)-1),"")
A14: 审计信息 | B14: audit_info | C14: INPUTUSERID | D14: varchar(32) | E14: YES | F14: 登记人 | J14: 2023/01/12 | K14: =A14 | L14: =B14 | M14: =F14 | N14: =C14 | O14: =IFERROR(LEFT(D14,FIND("(",D14)-1),D14) | P14: =IFERROR(MID(D14,FIND("(",D14)+1,FIND(")",D14)-FIND("(",D14)-1),"")
... A19: 审计信息 | B19: audit_info | C19: AUDITDATA | D19: varchar(2000) | E19: YES | F19: 审计数据 | J19: 2023/01/12 | K19: =A19 | L19: =B19 | M19: =F19 | N19: =C19 | O19: =IFERROR(LEFT(D19,FIND("(",D19)-1),D19) | P19: =IFERROR(MID(D19,FIND("(",D19)+1,FIND(")",D19)-FIND("(",D19)-1),"")

Sheet appraisal_agency
A1: =HYPERLINK("#表结构清单!A1","返回") | B1: 评估机构
A2: 评估机构 | B2: 表名 | C2: 列名 | D2: 字段类型 | E2: 是否为空 | F2: 字段注释 | G2: 码值 | H2: 备注 | I2: 修订人 | J2: 修订日期
A3: 评估机构 | B3: appraisal_agency | C3: APPRAISALORGID | D3: varchar(32) | E3: NO | F3: 评估机构编号 | J3: 2023/01/12 | K3: =A3 | L3: =B3 | M3: =F3 | N3: =C3 | O3: =IFERROR(LEFT(D3,FIND("(",D3)-1),D3) | P3: =IFERROR(MID(D3,FIND("(",D3)+1,FIND(")",D3)-FIND("(",D3)-1),"")
A4: 评估机构 | B4: appraisal_agency | C4: APPRAISALORGNAME | D4: varchar(80) | E4: YES | F4: 评估机构名称 | J4: 2023/01/12 | K4: =A4 | L4: =B4 | M4: =F4 | N4: =C4 | O4: =IFERROR(LEFT(D4,FIND("(",D4)-1),D4) | P4: =IFERROR(MID(D4,FIND("(",D4)+1,FIND(")",D4)-FIND("(",D4)-1),"")
A5: 评估机构 | B5: appraisal_agency | C5: APPRAISALORGTYPE | D5: varchar(18) | E5: YES | F5: 评估公司类型 02 特殊资产准入 03 特别准入;一次性) | G5: =HYPERLINK("#码值映射清单!B9420","AppraisalOrgType") | J5: 2023/01/12 | K5: =A5 | L5: =B5 | M5: =F5 | N5: =C5 | O5: =IFERROR(LEFT(D5,FIND("(",D5)-1),D5) | P5: =IFERROR(MID(D5,FIND("(",D5)+1,FIND(")",D5)-FIND("(",D5)-1),"")
A6: 评估机构 | B6: appraisal_agency | C6: APPRAISALORGADDRESS | D6: varchar(500) | E6: YES | F6: 机构地址 | J6: 2023/01/12 | K6: =A6 | L6: =B6 | M6: =F6 | N6: =C6 | O6: =IFERROR(LEFT(D6,FIND("(",D6)-1),D6) | P6: =IFERROR(MID(D6,FIND("(",D6)+1,FIND(")",D6)-FIND("(",D6)-1),"")
A7: 评估机构 | B7: appraisal_agency | C7: APPRAISALORGSTATUS | D7: varchar(6) | E7: YES | F7: 评估机构状态 | G7: =HYPERLINK("#码值映射清单!B9986","AgencyStatus") | H7: 1-生效、2-失效 | J7: 45740 | K7: =A7 | L7: =B7 | M7: =F7 | N7: =C7 | O7: =IFERROR(LEFT(D7,FIND("(",D7)-1),D7) | P7: =IFERROR(MID(D7,FIND("(",D7)+1,FIND(")",D7)-FIND("(",D7)-1),"")
A8: 评估机构 | B8: appraisal_agency | C8: REGISTERDATE | D8: datetime | E8: YES | F8: 机构成立日期 | J8: 2023/01/12 | K8: =A8 | L8: =B8 | M8: =F8 | N8: =C8 | O8: =IFERROR(LEFT(D8,FIND("(",D8)-1),D8) | P8: =IFERROR(MID(D8,FIND("(",D8)+1,FIND(")",D8)-FIND("(",D8)-1),"")
A9: 评估机构 | B9: appraisal_agency | C9: ASSETSTYPE | D9: varchar(18) | E9: YES | F9: 可评估资产类型 | G9: =HYPERLINK("#码值映射清单!B8049","AssessAssetsType") | J9: 2023/01/12 | K9: =A9 | L9: =B9 | M9: =F9 | N9: =C9 | O9: =IFERROR(LEFT(D9,FIND("(",D9)-1),D9) | P9: =IFERROR(MID(D9,FIND("(",D9)+1,FIND(")",D9)-FIND("(",D9)-1),"")
A10: 评估机构 | B10: appraisal_agency | C10: QUALIFYLEVEL | D10: varchar(18) | E10: YES | F10: 执业资质等级 | J10: 2023/01/12 | K10: =A10 | L10: =B10 | M10: =F10 | N10: =C10 | O10: =IFERROR(LEFT(D10,FIND("(",D10)-1),D10) | P10: =IFERROR(MID(D10,FIND("(",D10)+1,FIND(")",D10)-FIND("(",D10)-1),"")
A11: 评估机构 | B11: appraisal_agency | C11: ASSESSAREA | D11: varchar(80) | E11: YES | F11: 可估价地域范围 | G11: =HYPERLINK("#码值映射清单!B9045","AssessArea") | J11: 2023/01/12 | K11: =A11 | L11: =B11 | M11: =F11 | N11: =C11 | O11: =IFERROR(LEFT(D11,FIND("(",D11)-1),D11) | P11: =IFERROR(MID(D11,FIND("(",D11)+1,FIND(")",D11)-FIND("(",D11)-1),"")
A12: 评估机构 | B12: appraisal_agency | C12: CERTNAME | D12: varchar(80) | E12: YES | F12: 资质证书名称 | J12: 2023/01/12 | K12: =A12 | L12: =B12 | M12: =F12 | N12: =C12 | O12: =IFERROR(LEFT(D12,FIND("(",D12)-1),D12) | P12: =IFERROR(MID(D12,FIND("(",D12)+1,FIND(")",D12)-FIND("(",D12)-1),"")
A13: 评估机构 | B13: appraisal_agency | C13: CERTID | D13: varchar(32) | E13: YES | F13: 资质证书标号 | J13: 2023/01/12 | K13: =A13 | L13: =B13 | M13: =F13 | N13: =C13 | O13: =IFERROR(LEFT(D13,FIND("(",D13)-1),D13) | P13: =IFERROR(MID(D13,FIND("(",D13)+1,FIND(")",D13)-FIND("(",D13)-1),"")
A14: 评估机构 | B14: appraisal_agency | C14: APPROVEDATE | D14: datetime | E14: YES | F14: 资质核准日期 | J14: 2023/01/12 | K14: =A14 | L14: =B14 | M14: =F14 | N14: =C14 | O14: =IFERROR(LEFT(D14,FIND("(",D14)-1),D14) | P14: =IFERROR(MID(D14,FIND("(",D14)+1,FIND(")",D14)-FIND("(",D14)-1),"")
A15: 评估机构 | B15: appraisal_agency | C15: APPROVEENDDATE | D15: datetime | E15: YES | F15: 资质到期日期 | J15: 2023/01/12 | K15: =A15 | L15: =B15 | M15: =F15 | N15: =C15 | O15: =IFERROR(LEFT(D15,FIND("(",D15)-1),D15) | P15: =IFERROR(MID(D15,FIND("(",D15)+1,FIND(")",D15)-FIND("(",D15)-1),"")
A16: 评估机构 | B16: appraisal_agency | C16: DEPARTMENTCARE | D16: varchar(6) | E16: YES | F16: 行业主管部门是否年审 | G16: =HYPERLINK("#码值映射清单!B5150","YesNo") | J16: 2023/01/12 | K16: =A16 | L16: =B16 | M16: =F16 | N16: =C16 | O16: =IFERROR(LEFT(D16,FIND("(",D16)-1),D16) | P16: =IFERROR(MID(D16,FIND("(",D16)+1,FIND(")",D16)-FIND("(",D16)-1),"")
A17: 评估机构 | B17: appraisal_agency | C17: INPUTUSER | D17: varchar(80) | E17: YES | F17: 基本信息录入岗 | J17: 2023/01/12 | K17: =A17 | L17: =B17 | M17: =F17 | N17: =C17 | O17: =IFERROR(LEFT(D17,FIND("(",D17)-1),D17) | P17: =IFERROR(MID(D17,FIND("(",D17)+1,FIND(")",D17)-FIND("(",D17)-1),"")
A18: 评估机构 | B18: appraisal_agency | C18: CONTINUETIME | D18: int | E18: YES | F18: 连续执业时间 | J18: 2023/01/12 | K18: =A18 | L18: =B18 | M18: =F18 | N18: =C18 | O18: =IFERROR(LEFT(D18,FIND("(",D18)-1),D18) | P18: =IFERROR(MID(D18,FIND("(",D18)+1,FIND(")",D18)-FIND("(",D18)-1),"")
A19: 评估机构 | B19: appraisal_agency | C19: BUSINESSSCOPE | D19: varchar(500) | E19: YES | F19: 经营范围 | J19: 2023/01/12 | K19: =A19 | L19: =B19 | M19: =F19 | N19: =C19 | O19: =IFERROR(LEFT(D19,FIND("(",D19)-1),D19) | P19: =IFERROR(MID(D19,FIND("(",D19)+1,FIND(")",D19)-FIND("(",D19)-1),"")
A20: 评估机构 | B20: appraisal_agency | C20: REGISTERCAPITAL | D20: decimal(24,6) | E20: YES | F20: 注册资金 | J20: 2023/01/12 | K20: =A20 | L20: =B20 | M20: =F20 | N20: =C20 | O20: =IFERROR(LEFT(D20,FIND("(",D20)-1),D20) | P20: =IFERROR(MID(D20,FIND("(",D20)+1,FIND(")",D20)-FIND("(",D20)-1),"")
A21: 评估机构 | B21: appraisal_agency | C21: LEGALREP | D21: varchar(80) | E21: YES | F21: 法人代表 | J21: 2023/01/12 | K21: =A21 | L21: =B21 | M21: =F21 | N21: =C21 | O21: =IFERROR(LEFT(D21,FIND("(",D21)-1),D21) | P21: =IFERROR(MID(D21,FIND("(",D21)+1,FIND(")",D21)-FIND("(",D21)-1),"")
A22: 评估机构 | B22: appraisal_agency | C22: ORGTELEPHONE | D22: varchar(18) | E22: YES | F22: 评估机构电话 | J22: 2023/01/12 | K22: =A22 | L22: =B22 | M22: =F22 | N22: =C22 | O22: =IFERROR(LEFT(D22,FIND("(",D22)-1),D22) | P22: =IFERROR(MID(D22,FIND("(",D22)+1,FIND(")",D22)-FIND("(",D22)-1),"")
A23: 评估机构 | B23: appraisal_agency | C23: ORGFAX | D23: varchar(18) | E23: YES | F23: 评估机构传真电话 | J23: 2023/01/12 | K23: =A23 | L23: =B23 | M23: =F23 | N23: =C23 | O23: =IFERROR(LEFT(D23,FIND("(",D23)-1),D23) | P23: =IFERROR(MID(D23,FIND("(",D23)+1,FIND(")",D23)-FIND("(",D23)-1),"")
A24: 评估机构 | B24: appraisal_agency | C24: ORGEMAIL | D24: varchar(32) | E24: YES | F24: 评估机构电子邮箱 | J24: 2023/01/12 | K24: =A24 | L24: =B24 | M24: =F24 | N24: =C24 | O24: =IFERROR(LEFT(D24,FIND("(",D24)-1),D24) | P24: =IFERROR(MID(D24,FIND("(",D24)+1,FIND(")",D24)-FIND("(",D24)-1),"")
A25: 评估机构 | B25: appraisal_agency | C25: APPRAISERNUM | D25: int | E25: YES | F25: 评估师数量 | J25: 2023/01/12 | K25: =A25 | L25: =B25 | M25: =F25 | N25: =C25 | O25: =IFERROR(LEFT(D25,FIND("(",D25)-1),D25) | P25: =IFERROR(MID(D25,FIND("(",D25)+1,FIND(")",D25)-FIND("(",D25)-1),"")
A26: 评估机构 | B26: appraisal_agency | C26: ISINBLACKLIST | D26: char(1) | E26: YES | F26: 是否黑名单 | G26: =HYPERLINK("#码值映射清单!B5150","YesNo") | J26: 2023/01/12 | K26: =A26 | L26: =B26 | M26: =F26 | N26: =C26 | O26: =IFERROR(LEFT(D26,FIND("(",D26)-1),D26) | P26: =IFERROR(MID(D26,FIND("(",D26)+1,FIND(")",D26)-FIND("(",D26)-1),"")
A27: 评估机构 | B27: appraisal_agency | C27: PARENTORGID | D27: varchar(80) | E27: YES | F27: 所属分行 | J27: 2023/01/12 | K27: =A27 | L27: =B27 | M27: =F27 | N27: =C27 | O27: =IFERROR(LEFT(D27,FIND("(",D27)-1),D27) | P27: =IFERROR(MID(D27,FIND("(",D27)+1,FIND(")",D27)-FIND("(",D27)-1),"")
A28: 评估机构 | B28: appraisal_agency | C28: APPRAISALCERTID | D28: varchar(32) | E28: YES | F28: 评估机构证件号码 | J28: 2023/01/12 | K28: =A28 | L28: =B28 | M28: =F28 | N28: =C28 | O28: =IFERROR(LEFT(D28,FIND("(",D28)-1),D28) | P28: =IFERROR(MID(D28,FIND("(",D28)+1,FIND(")",D28)-FIND("(",D28)-1),"")
A29: 评估机构 | B29: appraisal_agency | C29: APPRAISALCERTTYPE | D29: varchar(18) | E29: YES | F29: 评估机构证件类型 | G29: =HYPERLINK("#码值映射清单!B6810","EntCertType") | J29: 2023/01/12 | K29: =A29 | L29: =B29 | M29: =F29 | N29: =C29 | O29: =IFERROR(LEFT(D29,FIND("(",D29)-1),D29) | P29: =IFERROR(MID(D29,FIND("(",D29)+1,FIND(")",D29)-FIND("(",D29)-1),"")
A30: 评估机构 | B30: appraisal_agency | C30: RELACERTID | D30: varchar(32) | E30: YES | F30: 关联机构 | J30: 2023/01/12 | K30: =A30 | L30: =B30 | M30: =F30 | N30: =C30 | O30: =IFERROR(LEFT(D30,FIND("(",D30)-1),D30) | P30: =IFERROR(MID(D30,FIND("(",D30)+1,FIND(")",D30)-FIND("(",D30)-1),"")
A31: 评估机构 | B31: appraisal_agency | C31: TEMPSAVEFLAG | D31: char(1) | E31: YES | F31: 暂存标志 | J31: 2023/01/12 | K31: =A31 | L31: =B31 | M31: =F31 | N31: =C31 | O31: =IFERROR(LEFT(D31,FIND("(",D31)-1),D31) | P31: =IFERROR(MID(D31,FIND("(",D31)+1,FIND(")",D31)-FIND("(",D31)-1),"")
A32: 评估机构 | B32: appraisal_agency | C32: ISINALERTLIST | D32: char(1) | E32: YES | F32: 警示标识 | J32: 2023/01/12 | K32: =A32 | L32: =B32 | M32: =F32 | N32: =C32 | O32: =IFERROR(LEFT(D32,FIND("(",D32)-1),D32) | P32: =IFERROR(MID(D32,FIND("(",D32)+1,FIND(")",D32)-FIND("(",D32)-1),"")
A33: 评估机构 | B33: appraisal_agency | C33: INPUTUSERID | D33: varchar(32) | E33: YES | F33: 登记人 | J33: 2023/01/12 | K33: =A33 | L33: =B33 | M33: =F33 | N33: =C33 | O33: =IFERROR(LEFT(D33,FIND("(",D33)-1),D33) | P33: =IFERROR(MID(D33,FIND("(",D33)+1,FIND(")",D33)-FIND("(",D33)-1),"")
A34: 评估机构 | B34: appraisal_agency | C34: INPUTORGID | D34: varchar(32) | E34: YES | F34: 登记机构 | J34: 2023/01/12 | K34: =A34 | L34: =B34 | M34: =F34 | N34: =C34 | O34: =IFERROR(LEFT(D34,FIND("(",D34)-1),D34) | P34: =IFERROR(MID(D34,FIND("(",D34)+1,FIND(")",D34)-FIND("(",D34)-1),"")
A35: 评估机构 | B35: appraisal_agency | C35: INPUTDATE | D35: datetime | E35: YES | F35: 登记日期 | J35: 2023/01/12 | K35: =A35 | L35: =B35 | M35: =F35 | N35: =C35 | O35: =IFERROR(LEFT(D35,FIND("(",D35)-1),D35) | P35: =IFERROR(MID(D35,FIND("(",D35)+1,FIND(")",D35)-FIND("(",D35)-1),"")
A36: 评估机构 | B36: appraisal_agency | C36: UPDATEUSERID | D36: varchar(32) | E36: YES | F36: 更新人 | J36: 2023/01/12 | K36: =A36 | L36: =B36 | M36: =F36 | N36: =C36 | O36: =IFERROR(LEFT(D36,FIND("(",D36)-1),D36) | P36: =IFERROR(MID(D36,FIND("(",D36)+1,FIND(")",D36)-FIND("(",D36)-1),"")
A37: 评估机构 | B37: appraisal_agency | C37: UPDATEORGID | D37: varchar(32) | E37: YES | F37: 更新机构 | J37: 2023/01/12 | K37: =A37 | L37: =B37 | M37: =F37 | N37: =C37 | O37: =IFERROR(LEFT(D37,FIND("(",D37)-1),D37) | P37: =IFERROR(MID(D37,FIND("(",D37)+1,FIND(")",D37)-FIND("(",D37)-1),"")
A38: 评估机构 | B38: appraisal_agency | C38: UPDATEDATE | D38: datetime | E38: YES | F38: 更新日期 | J38: 2023/01/12 | K38: =A38 | L38: =B38 | M38: =F38 | N38: =C38 | O38: =IFERROR(LEFT(D38,FIND("(",D38)-1),D38) | P38: =IFERROR(MID(D38,FIND("(",D38)+1,FIND(")",D38)-FIND("(",D38)-1),"")
A39: 评估机构 | B39: appraisal_agency | C39: REMARK | D39: varchar(1000) | E39: YES | F39: 备注 | J39: 2023/01/12 | K39: =A39 | L39: =B39 | M39: =F39 | N39: =C39 | O39: =IFERROR(LEFT(D39,FIND("(",D39)-1),D39) | P39: =IFERROR(MID(D39,FIND("(",D39)+1,FIND(")",D39)-FIND("(",D39)-1),"")
A40: 评估机构 | B40: appraisal_agency | C40: CORPORGID | D40: varchar(32) | E40: YES | F40: 法人机构编号 | J40: 2023/01/12 | K40: =A40 | L40: =B40 | M40: =F40 | N40: =C40 | O40: =IFERROR(LEFT(D40,FIND("(",D40)-1),D40) | P40: =IFERROR(MID(D40,FIND("(",D40)+1,FIND(")",D40)-FIND("(",D40)-1),"")
A41: 评估机构 | B41: appraisal_agency | C41: ISONLINE | D41: varchar(6) | E41: YES | F41: 线上评估是否启用 | G41: =HYPERLINK("#码值映射清单!B5150","YesNo") | J41: 45740 | K41: =A41 | L41: =B41 | M41: =F41 | N41: =C41 | O41: =IFERROR(LEFT(D41,FIND("(",D41)-1),D41) | P41: =IFERROR(MID(D41,FIND("(",D41)+1,FIND(")",D41)-FIND("(",D41)-1),"")

Sheet appraisal_agency_apply
A1: =HYPERLINK("#表结构清单!A1","返回") | B1: 评估机构申请信息表
B2: 表名 | C2: 列名 | D2: 字段类型 | E2: 是否为空 | F2: 字段注释 | G2: 码值 | H2: 备注 | I2: 修订人 | J2: 修订日期
B3: appraisal_agency_apply | C3: EVENTSERIALNO | D3: varchar(32) | E3: NO | F3: 评估机构事件编号 | J3: 2023/01/12
B4: appraisal_agency_apply | C4: APPLYTYPE | D4: varchar(32) | E4: YES | F4: 申请类型 | G4: =HYPERLINK("#码值映射清单!B7547","AppraisalFlowType2") | J4: 2023/01/12
B5: appraisal_agency_apply | C5: APPROVESTATUS | D5: varchar(32) | E5: YES | F5: 申请状态 | G5: =HYPERLINK("#码值映射清单!B1429","ApproveStatus") | J5: 2023/01/12
B6: appraisal_agency_apply | C6: FLOWTYPE | D6: varchar(32) | E6: YES | F6: 流程类型 | J6: 2023/01/12
B7: appraisal_agency_apply | C7: INPUTUSERID | D7: varchar(32) | E7: YES | F7: 登记人 | J7: 2023/01/12
B8: appraisal_agency_apply | C8: INPUTORGID | D8: varchar(32) | E8: YES | F8: 登记机构 | J8: 2023/01/12
B9: appraisal_agency_apply | C9: INPUTDATE | D9: datetime | E9: YES | F9: 登记日期 | J9: 2023/01/12
B10: appraisal_agency_apply | C10: UPDATEUSERID | D10: varchar(32) | E10: YES | F10: 更新人 | J10: 2023/01/12
B11: appraisal_agency_apply | C11: UPDATEORGID | D11: varchar(32) | E11: YES | F11: 更新机构 | J11: 2023/01/12
B12: appraisal_agency_apply | C12: UPDATEDATE | D12: datetime | E12: YES | F12: 更新日期 | J12: 2023/01/12
B13: appraisal_agency_apply | C13: REMARK | D13: varchar(500) | E13: YES | F13: 备注 | G13: =HYPERLINK("#码值映射清单!B5361","AppraisalFlowType") | J13: 2023/01/12
B14: appraisal_agency_apply | C14: CORPORGID | D14: varchar(32) | E14: YES | F14: 法人机构编号 | J14: 2023/01/12

Sheet appraisal_agency_appraise
A1: =HYPERLINK("#表结构清单!A1","返回") | B1: 评价调查信息管理
B2: 表名 | C2: 列名 | D2: 字段类型 | E2: 是否为空 | F2: 字段注释 | G2: 码值 | H2: 备注 | I2: 修订人 | J2: 修订日期
B3: appraisal_agency_appraise | C3: EVENTSERIALNO | D3: varchar(32) | E3: NO | F3: 评估机构事件编号 | J3: 2023/01/12
B4: appraisal_agency_appraise | C4: EVENTTYPE | D4: varchar(32) | E4: YES | F4: 事件类型 | J4: 2023/01/12
B5: appraisal_agency_appraise | C5: CLRID | D5: varchar(32) | E5: YES | F5: 抵质押品编号 | J5: 2023/01/12
B6: appraisal_agency_appraise | C6: BUSINESSTYPE | D6: varchar(18) | E6: YES | F6: 委托业务类型 | J6: 2023/01/12
B7: appraisal_agency_appraise | C7: PERSONFEEDBACK | D7: varchar(1000) | E7: YES | F7: 人员反馈事项 | J7: 2023/01/12
B8: appraisal_agency_appraise | C8: OTHERFEEDBACK | D8: varchar(1000) | E8: YES | F8: 其他反馈事项 | J8: 2023/01/12
B9: appraisal_agency_appraise | C9: FEEDMATTERADD | D9: varchar(1000) | E9: YES | F9: 人员反馈事项补充 | J9: 2023/01/12
B10: appraisal_agency_appraise | C10: APPRAISALDATE | D10: datetime | E10: YES | F10: 评价日期 | J10: 2023/01/12
B11: appraisal_agency_appraise | C11: INPUTUSERID | D11: varchar(32) | E11: YES | F11: 登记人 | J11: 2023/01/12
B12: appraisal_agency_appraise | C12: INPUTORGID | D12: varchar(32) | E12: YES | F12: 登记机构 | J12: 2023/01/12
B13: appraisal_agency_appraise | C13: INPUTDATE | D13: datetime | E13: YES | F13: 登记日期 | J13: 2023/01/12
B14: appraisal_agency_appraise | C14: UPDATEUSERID | D14: varchar(32) | E14: YES | F14: 更新人 | J14: 2023/01/12
... B19: appraisal_agency_appraise | C19: OPINION | D19: varchar(4000) | E19: YES | F19: 人员总体意见 | J19: 2023/01/12

Sheet appraisal_agency_cooperation
A1: =HYPERLINK("#表结构清单!A1","返回") | B1: 评估机构合作协议
B2: 表名 | C2: 列名 | D2: 字段类型 | E2: 是否为空 | F2: 字段注释 | G2: 码值 | H2: 备注 | I2: 修订人 | J2: 修订日期
B3: appraisal_agency_cooperation | C3: SERIALNO | D3: varchar(32) | E3: NO | F3: 流水号 | J3: 2023/01/12
B4: appraisal_agency_cooperation | C4: AGRMID | D4: varchar(32) | E4: YES | F4: 合作协议编号 | J4: 2023/01/12
B5: appraisal_agency_cooperation | C5: APPRAISALORGID | D5: varchar(32) | E5: YES | F5: 评估机构编号 | J5: 2023/01/12
B6: appraisal_agency_cooperation | C6: APPRAISALAPPLYNO | D6: varchar(32) | E6: YES | F6: 评估机构流程申请编号 | J6: 2023/01/12
B7: appraisal_agency_cooperation | C7: EFFECTIVEDATE | D7: datetime | E7: YES | F7: 生效日期 | J7: 2023/01/12
B8: appraisal_agency_cooperation | C8: EXPIRYDATE | D8: datetime | E8: YES | F8: 失效日期 | J8: 2023/01/12
B9: appraisal_agency_cooperation | C9: STATUS | D9: varchar(6) | E9: YES | F9: 状态 | J9: 2023/01/12
B10: appraisal_agency_cooperation | C10: BUSINESSTYPE | D10: varchar(18) | E10: YES | F10: 开展业务种类 | G10: =HYPERLINK("#码值映射清单!B8049","AssessAssetsType") | J10: 2023/01/12
B11: appraisal_agency_cooperation | C11: RISKDEPOSIT | D11: decimal(24,6) | E11: YES | F11: 风险保证金金额 | J11: 2023/01/12
B12: appraisal_agency_cooperation | C12: PAYDEPOSITDATE | D12: datetime | E12: YES | F12: 风险保证金交存日期 | J12: 2023/01/12
B13: appraisal_agency_cooperation | C13: RELIEVEDEPOSITDATES | D13: datetime | E13: YES | F13: 合作协议解除日期 | J13: 2023/01/12
B14: appraisal_agency_cooperation | C14: AGGREEMENTSIGNDATE | D14: datetime | E14: YES | F14: 合作协议书签署日期 | J14: 2023/01/12
B15: appraisal_agency_cooperation | C15: INPUTUSERID | D15: varchar(32) | E15: YES | F15: 登记人 | J15: 2023/01/12
B16: appraisal_agency_cooperation | C16: INPUTORGID | D16: varchar(32) | E16: YES | F16: 登记机构 | J16: 2023/01/12
B17: appraisal_agency_cooperation | C17: INPUTDATE | D17: datetime | E17: YES | F17: 登记日期 | J17: 2023/01/12
B18: appraisal_agency_cooperation | C18: UPDATEUSERID | D18: varchar(32) | E18: YES | F18: 更新人 | J18: 2023/01/12
B19: appraisal_agency_cooperation | C19: UPDATEORGID | D19: varchar(32) | E19: YES | F19: 更新机构 | J19: 2023/01/12
B20: appraisal_agency_cooperation | C20: UPDATEDATE | D20: datetime | E20: YES | F20: 更新日期 | J20: 2023/01/12
B21: appraisal_agency_cooperation | C21: REMARK | D21: varchar(1000) | E21: YES | F21: 备注 | J21: 2023/01/12
B22: appraisal_agency_cooperation | C22: CORPORGID | D22: varchar(32) | E22: YES | F22: 法人机构编号 | J22: 2023/01/12
B23: appraisal_agency_cooperation | C23: AGRMTXT | D23: varchar(4000) | E23: YES | F23: 合作协议文本 | J23: 2023/01/12

Sheet appraisal_agency_event
A1: =HYPERLINK("#表结构清单!A1","返回") | B1: 评估机构事件表
B2: 表名 | C2: 列名 | D2: 字段类型 | E2: 是否为空 | F2: 字段注释 | G2: 码值 | H2: 备注 | I2: 修订人 | J2: 修订日期
B3: appraisal_agency_event | C3: EVENTSERIALNO | D3: varchar(32) | E3: NO | F3: 评估机构事件编号 | J3: 2023/01/12
B4: appraisal_agency_event | C4: RELATIVESERIALNO | D4: varchar(32) | E4: YES | F4: 关联解除事件编号 | J4: 2023/01/12
B5: appraisal_agency_event | C5: EVENTTYPE | D5: varchar(32) | E5: YES | F5: 事件类型 | J5: 2023/01/12
B6: appraisal_agency_event | C6: EVENTSTATUS | D6: varchar(6) | E6: YES | F6: 事件状态 | J6: 2023/01/12
B7: appraisal_agency_event | C7: EVENTRULES | D7: varchar(6) | E7: YES | F7: 事件规则 | J7: 2023/01/12
B8: appraisal_agency_event | C8: EVENTREASON | D8: varchar(500) | E8: YES | F8: 事件说明 | J8: 2023/01/12
B9: appraisal_agency_event | C9: AFFIRMUSERID | D9: varchar(32) | E9: YES | F9: 认定人 | J9: 2023/01/12
B10: appraisal_agency_event | C10: AFFIRMORGID | D10: varchar(32) | E10: YES | F10: 认定机构 | J10: 2023/01/12
B11: appraisal_agency_event | C11: AFFIRMDATE | D11: datetime | E11: YES | F11: 认定时间 | J11: 2023/01/12
B12: appraisal_agency_event | C12: RELEASEUSERID | D12: varchar(32) | E12: YES | F12: 解除人 | J12: 2023/01/12
B13: appraisal_agency_event | C13: RELEASEORGID | D13: varchar(32) | E13: YES | F13: 解除机构 | J13: 2023/01/12
B14: appraisal_agency_event | C14: RELEASEDATE | D14: datetime | E14: YES | F14: 解除时间 | J14: 2023/01/12
... B23: appraisal_agency_event | C23: CORPORGID | D23: varchar(32) | E23: YES | F23: 法人机构编号 | J23: 2023/01/12

Sheet appraisal_agency_expenses
A1: =HYPERLINK("#表结构清单!A1","返回") | B1: 评估机构费用
B2: 表名 | C2: 列名 | D2: 字段类型 | E2: 是否为空 | F2: 字段注释 | G2: 码值 | H2: 备注 | I2: 修订人 | J2: 修订日期
B3: appraisal_agency_expenses | C3: SERIALNO | D3: varchar(32) | E3: NO | F3: 流水号 | J3: 2023/01/12
B4: appraisal_agency_expenses | C4: APPRAISALORGID | D4: varchar(32) | E4: NO | F4: 评估公司组织机构代码证 | J4: 2023/01/12
B5: appraisal_agency_expenses | C5: EVALRECORDID | D5: varchar(32) | E5: YES | F5: 评估记录流水号 | J5: 2023/01/12
B6: appraisal_agency_expenses | C6: FEENAME | D6: varchar(80) | E6: YES | F6: 费用名称 | J6: 2023/01/12
B7: appraisal_agency_expenses | C7: FEEACCOUNT | D7: decimal(24,6) | E7: YES | F7: 费用金额 | J7: 2023/01/12
B8: appraisal_agency_expenses | C8: OCCURDATE | D8: datetime | E8: NO | F8: 费用发生日期 | J8: 2023/01/12
B9: appraisal_agency_expenses | C9: INPUTUSERID | D9: varchar(32) | E9: YES | F9: 登记人 | J9: 2023/01/12
B10: appraisal_agency_expenses | C10: INPUTORGID | D10: varchar(32) | E10: YES | F10: 登记机构 | J10: 2023/01/12
B11: appraisal_agency_expenses | C11: INPUTDATE | D11: datetime | E11: YES | F11: 登记日期 | J11: 2023/01/12
B12: appraisal_agency_expenses | C12: UPDATEUSERID | D12: varchar(32) | E12: YES | F12: 更新人 | J12: 2023/01/12
B13: appraisal_agency_expenses | C13: UPDATEORGID | D13: varchar(32) | E13: YES | F13: 更新机构 | J13: 2023/01/12
B14: appraisal_agency_expenses | C14: UPDATEDATE | D14: datetime | E14: YES | F14: 更新日期 | J14: 2023/01/12
... B16: appraisal_agency_expenses | C16: CORPORGID | D16: varchar(32) | E16: YES | F16: 法人机构编号 | J16: 2023/01/12

Sheet appraisal_agency_file
A1: =HYPERLINK("#表结构清单!A1","返回") | B1: 评级机构附件
B2: 表名 | C2: 列名 | D2: 字段类型 | E2: 是否为空 | F2: 字段注释 | G2: 码值 | H2: 备注 | I2: 修订人 | J2: 修订日期
B3: appraisal_agency_file | C3: FILENO | D3: varchar(32) | E3: NO | F3: 文档编号 | J3: 2023/01/12
B4: appraisal_agency_file | C4: APPRAISALORGID | D4: varchar(32) | E4: NO | F4: 评估公司组织机构代码证 | J4: 2023/01/12
B5: appraisal_agency_file | C5: FILENAME | D5: varchar(80) | E5: YES | F5: 文档名称 | J5: 2023/01/12
B6: appraisal_agency_file | C6: INPUTUSERID | D6: varchar(32) | E6: YES | F6: 登记人 | J6: 2023/01/12
B7: appraisal_agency_file | C7: INPUTORGID | D7: varchar(32) | E7: YES | F7: 登记机构 | J7: 2023/01/12
B8: appraisal_agency_file | C8: INPUTDATE | D8: datetime | E8: YES | F8: 登记日期 | J8: 2023/01/12
B9: appraisal_agency_file | C9: UPDATEUSERID | D9: varchar(32) | E9: YES | F9: 更新人 | J9: 2023/01/12
B10: appraisal_agency_file | C10: UPDATEORGID | D10: varchar(32) | E10: YES | F10: 更新机构 | J10: 2023/01/12
B11: appraisal_agency_file | C11: UPDATEDATE | D11: datetime | E11: YES | F11: 更新日期 | J11: 2023/01/12
B12: appraisal_agency_file | C12: REMARK | D12: varchar(500) | E12: YES | F12: 备注 | J12: 2023/01/12
B13: appraisal_agency_file | C13: CORPORGID | D13: varchar(32) | E13: YES | F13: 法人机构编号 | J13: 2023/01/12

Sheet appraisal_agency_information
A1: =HYPERLINK("#表结构清单!A1","返回") | B1: 评估公司相关信息
B2: 表名 | C2: 列名 | D2: 字段类型 | E2: 是否为空 | F2: 字段注释 | G2: 码值 | H2: 备注 | I2: 修订人 | J2: 修订日期
B3: appraisal_agency_information | C3: SERIALNO | D3: varchar(32) | E3: NO | F3: 流水号 | J3: 2023/01/12
B4: appraisal_agency_information | C4: APPRAISALORGID | D4: varchar(32) | E4: NO | F4: 评估公司组织机构代码证 | J4: 2023/01/12
B5: appraisal_agency_information | C5: INFORMATIONTYPE | D5: varchar(18) | E5: YES | F5: 信息类型 | G5: =HYPERLINK("#码值映射清单!B10076","AgencyInformationType") | J5: 2023/01/12
B6: appraisal_agency_information | C6: ATTRIBUTE1 | D6: varchar(80) | E6: YES | F6: 联系人列表_姓名;资质情况_资质证书名称，专家信息_姓名，大事信息_标题 | J6: 2023/01/12
B7: appraisal_agency_information | C7: ATTRIBUTE2 | D7: varchar(32) | E7: YES | F7: 联系人列表_电话;资质情况_资质证书标号，专家信息_电话，大事信息_无 | J7: 2023/01/12
B8: appraisal_agency_information | C8: ATTRIBUTE3 | D8: varchar(32) | E8: YES | F8: 联系人列表_所属部门;资质情况_无，专家信息_所属部门，大事信息_无 | J8: 2023/01/12
B9: appraisal_agency_information | C9: ATTRIBUTE4 | D9: varchar(18) | E9: YES | F9: 联系人列表_是否有效;资质情况_执业资质等级，专家信息_无，大事信息_是否有效 | G9: =HYPERLINK("#码值映射清单!B5150","YesNo") | J9: 2023/01/12
B10: appraisal_agency_information | C10: ATTRIBUTE6 | D10: datetime | E10: YES | F10: 联系人列表_无;资质情况_资质核准日期，专家信息_无，大事信息_发生日期 | J10: 2023/01/12
B11: appraisal_agency_information | C11: ATTRIBUTE7 | D11: datetime | E11: YES | F11: 联系人列表_无;资质情况_资质到期日期，专家信息_无，大事信息_无 | J11: 2023/01/12
B12: appraisal_agency_information | C12: WORKYEARS | D12: varchar(6) | E12: YES | F12: 从业年限 | J12: 2023/01/12
B13: appraisal_agency_information | C13: INPUTUSERID | D13: varchar(32) | E13: YES | F13: 登记人 | J13: 2023/01/12
B14: appraisal_agency_information | C14: INPUTORGID | D14: varchar(32) | E14: YES | F14: 登记机构 | J14: 2023/01/12
B15: appraisal_agency_information | C15: INPUTDATE | D15: datetime | E15: YES | F15: 登记日期 | J15: 2023/01/12
B16: appraisal_agency_information | C16: UPDATEUSERID | D16: varchar(32) | E16: YES | F16: 更新人 | J16: 2023/01/12
B17: appraisal_agency_information | C17: UPDATEORGID | D17: varchar(32) | E17: YES | F17: 更新机构 | J17: 2023/01/12
B18: appraisal_agency_information | C18: UPDATEDATE | D18: datetime | E18: YES | F18: 更新日期 | J18: 2023/01/12
B19: appraisal_agency_information | C19: REMARK | D19: varchar(500) | E19: YES | F19: 备注 | J19: 2023/01/12
B20: appraisal_agency_information | C20: CORPORGID | D20: varchar(32) | E20: YES | F20: 法人机构编号 | J20: 2023/01/12
B21: appraisal_agency_information | C21: ATTRIBUTE5 | D21: varchar(1000) | E21: YES | F21: 联系人列表_无;资质情况_无，专家信息_专业领域，大事信息_事件描述及原因 | J21: 2023/01/12

Sheet appraisal_agency_qualification
A1: =HYPERLINK("#表结构清单!A1","返回") | B1: 评估机构资质表
B2: 表名 | C2: 列名 | D2: 字段类型 | E2: 是否为空 | F2: 字段注释 | G2: 码值 | H2: 备注 | I2: 修订人 | J2: 修订日期
B3: appraisal_agency_qualification | C3: EVENTSERIALNO | D3: varchar(32) | E3: NO | F3: 评估机构事件编号 | J3: 2023/01/12
B4: appraisal_agency_qualification | C4: EVENTTYPE | D4: varchar(32) | E4: YES | F4: 事件类型 | J4: 2023/01/12
B5: appraisal_agency_qualification | C5: ADMITTANCETYPE | D5: varchar(18) | E5: YES | F5: 准入评估类型 | J5: 2023/01/12
B6: appraisal_agency_qualification | C6: ISONCEACCESS | D6: char(1) | E6: YES | F6: 是否曾经准入 | J6: 2023/01/12
B7: appraisal_agency_qualification | C7: ISSPECIALACCESS | D7: char(1) | E7: YES | F7: 是否为特殊准入 | J7: 2023/01/12
B8: appraisal_agency_qualification | C8: COMPOSITESCOPE | D8: decimal(18,8) | E8: YES | F8: 评估机构综合得分 | J8: 2023/01/12
B9: appraisal_agency_qualification | C9: OCCURYEAR | D9: int | E9: YES | F9: 发生年度 | J9: 2023/01/12
B10: appraisal_agency_qualification | C10: OCCURREASON | D10: varchar(500) | E10: YES | F10: 发生原因 | J10: 2023/01/12
B11: appraisal_agency_qualification | C11: REMARK | D11: varchar(500) | E11: YES | F11: 备注 | J11: 2023/01/12
B12: appraisal_agency_qualification | C12: INPUTUSERID | D12: varchar(32) | E12: YES | F12: 登记人 | J12: 2023/01/12
B13: appraisal_agency_qualification | C13: INPUTORGID | D13: varchar(32) | E13: YES | F13: 登记机构 | J13: 2023/01/12
B14: appraisal_agency_qualification | C14: INPUTDATE | D14: datetime | E14: YES | F14: 登记日期 | J14: 2023/01/12
... B18: appraisal_agency_qualification | C18: CORPORGID | D18: varchar(32) | E18: YES | F18: 法人机构编号 | J18: 2023/01/12

Sheet appraisal_apply_relative
A1: =HYPERLINK("#表结构清单!A1","返回") | B1: 评级机构申请关联表
B2: 表名 | C2: 列名 | D2: 字段类型 | E2: 是否为空 | F2: 字段注释 | G2: 码值 | H2: 备注 | I2: 修订人 | J2: 修订日期
B3: appraisal_apply_relative | C3: EVENTSERIALNO | D3: varchar(32) | E3: NO | F3: 评估机构事件编号 | J3: 2023/01/12
B4: appraisal_apply_relative | C4: APPRAISALORGID | D4: varchar(32) | E4: YES | F4: 评估机构编号 | J4: 2023/01/12
B5: appraisal_apply_relative | C5: REMARK | D5: varchar(1000) | E5: YES | F5: 备注 | J5: 2023/01/12
B6: appraisal_apply_relative | C6: INPUTUSERID | D6: varchar(32) | E6: YES | F6: 登记人 | J6: 2023/01/12
B7: appraisal_apply_relative | C7: INPUTORGID | D7: varchar(32) | E7: YES | F7: 登记机构 | J7: 2023/01/12
B8: appraisal_apply_relative | C8: INPUTDATE | D8: datetime | E8: YES | F8: 登记日期 | J8: 2023/01/12
B9: appraisal_apply_relative | C9: UPDATEUSERID | D9: varchar(32) | E9: YES | F9: 更新人 | J9: 2023/01/12
B10: appraisal_apply_relative | C10: UPDATEORGID | D10: varchar(32) | E10: YES | F10: 更新机构 | J10: 2023/01/12
B11: appraisal_apply_relative | C11: UPDATEDATE | D11: datetime | E11: YES | F11: 更新日期 | J11: 2023/01/12

Sheet awe_bizfile_info
A1: =HYPERLINK("#表结构清单!A1","返回") | B1: 业务文件详情
B2: 表名 | C2: 列名 | D2: 字段类型 | E2: 是否为空 | F2: 字段注释 | G2: 码值 | H2: 备注 | I2: 修订人 | J2: 修订日期
B3: awe_bizfile_info | C3: FILENO | D3: varchar(32) | E3: NO | F3: 文件编号; | J3: 2023/01/12
B4: awe_bizfile_info | C4: FILEPATH | D4: varchar(500) | E4: YES | F4: 文件路径; | J4: 2023/01/12
B5: awe_bizfile_info | C5: FILEDESC | D5: varchar(500) | E5: YES | F5: 文件描述; | J5: 2023/01/12
B6: awe_bizfile_info | C6: CATALOGINFO | D6: varchar(500) | E6: YES | F6: 目录详情; | J6: 2023/01/12
B7: awe_bizfile_info | C7: ISTEMPORARY | D7: varchar(18) | E7: YES | F7: 是否临时; | J7: 2023/01/12
B8: awe_bizfile_info | C8: LATESTDOUSERID | D8: varchar(32) | E8: YES | F8: 最新下载用户; | J8: 2023/01/12
B9: awe_bizfile_info | C9: DOWNLOADCOUNT | D9: int | E9: YES | F9: 下载次数; | J9: 2023/01/12
B10: awe_bizfile_info | C10: CREATEUSER | D10: varchar(32) | E10: YES | F10: 创建人; | J10: 2023/01/12
B11: awe_bizfile_info | C11: CREATETIME | D11: varchar(32) | E11: YES | F11: 创建时间 | J11: 2023/01/12

Sheet awe_dict_errmsg
A1: =HYPERLINK("#表结构清单!A1","返回") | B1: 信息提示
B2: 表名 | C2: 列名 | D2: 字段类型 | E2: 是否为空 | F2: 字段注释 | G2: 码值 | H2: 备注 | I2: 修订人 | J2: 修订日期
B3: awe_dict_errmsg | C3: MSGNO | D3: varchar(32) | E3: NO | F3: 错误编号 | J3: 2023/01/12
B4: awe_dict_errmsg | C4: MSGTYPE | D4: varchar(18) | E4: YES | F4: 错误主题 | J4: 2023/01/12
B5: awe_dict_errmsg | C5: MSGTEXT | D5: varchar(500) | E5: YES | F5: 报告内容 | J5: 2023/01/12
B6: awe_dict_errmsg | C6: ENTEXT | D6: varchar(500) | E6: YES | F6: 图片地址 | J6: 2023/01/12
B7: awe_dict_errmsg | C7: INPUTORGID | D7: varchar(32) | E7: YES | F7: 登记机构 | J7: 2023/01/12
B8: awe_dict_errmsg | C8: INPUTUSERID | D8: varchar(32) | E8: YES | F8: 登记人 | J8: 2023/01/12
B9: awe_dict_errmsg | C9: INPUTDATE | D9: datetime | E9: YES | F9: 登记日期 | J9: 2023/01/12
B10: awe_dict_errmsg | C10: UPDATEORGID | D10: varchar(32) | E10: YES | F10: 更新机构 | J10: 2023/01/12
B11: awe_dict_errmsg | C11: UPDATEUSERID | D11: varchar(32) | E11: YES | F11: 更新人 | J11: 2023/01/12
B12: awe_dict_errmsg | C12: UPDATEDATE | D12: datetime | E12: YES | F12: 更新时间 | J12: 2023/01/12
B13: awe_dict_errmsg | C13: INPUTTIME | D13: datetime | E13: YES | F13: 录入时间 | J13: 2023/01/12
B14: awe_dict_errmsg | C14: UPDATETIME | D14: datetime | E14: YES | F14: 更新时间 | J14: 2023/01/12
... B17: awe_dict_errmsg | C17: UPDATEUSER | D17: varchar(80) | E17: YES | F17: 更新人 | J17: 2023/01/12

Sheet awe_do_catalog
A1: =HYPERLINK("#表结构清单!A1","返回") | B1: OW显示模板场景
B2: 表名 | C2: 列名 | D2: 字段类型 | E2: 是否为空 | F2: 字段注释 | G2: 码值 | H2: 备注 | I2: 修订人 | J2: 修订日期
B3: awe_do_catalog | C3: DONO | D3: varchar(80) | E3: NO | F3: 显示模板编号 | J3: 2023/01/12
B4: awe_do_catalog | C4: DONAME | D4: varchar(80) | E4: YES | F4: 名称 | J4: 2023/01/12
B5: awe_do_catalog | C5: DODESCRIBE | D5: varchar(500) | E5: YES | F5: 描述 | J5: 2023/01/12
B6: awe_do_catalog | C6: DOTYPE | D6: varchar(18) | E6: YES | F6: 用途 | J6: 2023/01/12
B7: awe_do_catalog | C7: DOCLASS | D7: varchar(18) | E7: YES | F7: 分类 | J7: 2023/01/12
B8: awe_do_catalog | C8: ISINUSE | D8: varchar(6) | E8: YES | F8: 是否有效 | J8: 2023/01/12
B9: awe_do_catalog | C9: COLCOUNT | D9: char(1) | E9: YES | F9: 分栏数 | J9: 2023/01/12
B10: awe_do_catalog | C10: MODEID | D10: varchar(32) | E10: YES | F10: 风格编号 | J10: 2023/01/12
B11: awe_do_catalog | C11: JBOCLASS | D11: varchar(500) | E11: YES | F11: JBO定义名 | J11: 2023/01/12
B12: awe_do_catalog | C12: JBOFROM | D12: varchar(4000) | E12: YES | F12: from子句 | J12: 2023/01/12
B13: awe_do_catalog | C13: JBOWHERE | D13: varchar(4000) | E13: YES | F13: 查询条件 | J13: 2023/01/12
B14: awe_do_catalog | C14: JBOGROUP | D14: varchar(1000) | E14: YES | F14: 分组 | J14: 2023/01/12
... B25: awe_do_catalog | C25: ISOSFSERVICE | D25: varchar(6) | E25: YES | F25: 是否是OSF服务 | J25: 2023/01/12

Sheet awe_do_col_validate
A1: =HYPERLINK("#表结构清单!A1","返回") | B1: DW字段验证规则
B2: 表名 | C2: 列名 | D2: 字段类型 | E2: 是否为空 | F2: 字段注释 | G2: 码值 | H2: 备注 | I2: 修订人 | J2: 修订日期
B3: awe_do_col_validate | C3: SERIALNO | D3: varchar(32) | E3: NO | F3: 流水号 | J3: 2023/01/12
B4: awe_do_col_validate | C4: DONO | D4: varchar(80) | E4: YES | F4: 显示模板编号 | J4: 2023/01/12
B5: awe_do_col_validate | C5: COLNAME | D5: varchar(80) | E5: YES | F5: jbo属性名 | J5: 2023/01/12
B6: awe_do_col_validate | C6: VALIDATORNAME | D6: varchar(80) | E6: YES | F6: 对应验证规则 | J6: 2023/01/12
B7: awe_do_col_validate | C7: PARAM1 | D7: varchar(4000) | E7: YES | F7: 参数 | J7: 2023/01/12
B8: awe_do_col_validate | C8: PARAM2 | D8: varchar(500) | E8: YES | F8: 参数 | J8: 2023/01/12
B9: awe_do_col_validate | C9: PARAM3 | D9: varchar(500) | E9: YES | F9: 参数 | J9: 2023/01/12
B10: awe_do_col_validate | C10: PARAM4 | D10: varchar(500) | E10: YES | F10: 参数 | J10: 2023/01/12
B11: awe_do_col_validate | C11: PARAM5 | D11: varchar(32) | E11: YES | F11: 参数 | J11: 2023/01/12
B12: awe_do_col_validate | C12: PARAM6 | D12: varchar(32) | E12: YES | F12: 参数 | J12: 2023/01/12
B13: awe_do_col_validate | C13: PARAM7 | D13: varchar(32) | E13: YES | F13: 参数 | J13: 2023/01/12
B14: awe_do_col_validate | C14: PARAM8 | D14: varchar(32) | E14: YES | F14: 参数 | J14: 2023/01/12
... B18: awe_do_col_validate | C18: ISINUSE | D18: char(1) | E18: YES | F18: 是否使用 | J18: 2023/01/12

Sheet awe_do_event
A1: =HYPERLINK("#表结构清单!A1","返回") | B1: OW字段事件
B2: 表名 | C2: 列名 | D2: 字段类型 | E2: 是否为空 | F2: 字段注释 | G2: 码值 | H2: 备注 | I2: 修订人 | J2: 修订日期
B3: awe_do_event | C3: DONO | D3: varchar(80) | E3: NO | F3: 显示模板编号 | J3: 2023/01/12
B4: awe_do_event | C4: COLNAME | D4: varchar(80) | E4: NO | F4: jbo属性名 | J4: 2023/01/12
B5: awe_do_event | C5: EVENT | D5: varchar(80) | E5: NO | F5: 事件名 | J5: 2023/01/12
B6: awe_do_event | C6: EVENTPARAMS | D6: varchar(500) | E6: YES | F6: 方法执行参数 | J6: 2023/01/12
B7: awe_do_event | C7: SCRIPT | D7: varchar(500) | E7: YES | F7: 事件执行方法 | J7: 2023/01/12
B8: awe_do_event | C8: ISINUSE | D8: varchar(6) | E8: YES | F8: 是否有效 | J8: 2023/01/12
B9: awe_do_event | C9: INPUTUSER | D9: varchar(32) | E9: YES | F9: 登记人 | J9: 2023/01/12
B10: awe_do_event | C10: INPUTTIME | D10: datetime | E10: YES | F10: 登记时间 | J10: 2023/01/12
B11: awe_do_event | C11: UPDATEUSER | D11: varchar(32) | E11: YES | F11: 更新人 | J11: 2023/01/12
B12: awe_do_event | C12: UPDATETIME | D12: datetime | E12: YES | F12: 更新时间 | J12: 2023/01/12

Sheet awe_do_function
A1: =HYPERLINK("#表结构清单!A1","返回") | B1: OW脚本方法
B2: 表名 | C2: 列名 | D2: 字段类型 | E2: 是否为空 | F2: 字段注释 | G2: 码值 | H2: 备注 | I2: 修订人 | J2: 修订日期
B3: awe_do_function | C3: FUNCTIONNAME | D3: varchar(80) | E3: NO | F3: 方法名 | J3: 2023/01/12
B4: awe_do_function | C4: DONO | D4: varchar(80) | E4: NO | F4: OW显示模板编号 | J4: 2023/01/12
B5: awe_do_function | C5: FUNCTIONPARAMS | D5: varchar(500) | E5: YES | F5: 方法参数 | J5: 2023/01/12
B6: awe_do_function | C6: FUNCTIONDESC | D6: varchar(500) | E6: YES | F6: 方法描述 | J6: 2023/01/12
B7: awe_do_function | C7: INPUTTIME | D7: datetime | E7: YES | F7: 登记时间 | J7: 2023/01/12
B8: awe_do_function | C8: INPUTUSER | D8: varchar(32) | E8: YES | F8: 登记人 | J8: 2023/01/12
B9: awe_do_function | C9: UPDATETIME | D9: datetime | E9: YES | F9: 更新时间 | J9: 2023/01/12
B10: awe_do_function | C10: UPDATEUSER | D10: varchar(32) | E10: YES | F10: 更新人 | J10: 2023/01/12
B11: awe_do_function | C11: ISINUSE | D11: char(1) | E11: YES | F11: 是否使用 | J11: 2023/01/12
B12: awe_do_function | C12: FUNCTIONBODY | D12: varchar(4000) | E12: YES | F12: 方法体 | J12: 2023/01/12

Sheet awe_do_group
A1: =HYPERLINK("#表结构清单!A1","返回") | B1: OW分组信息
B2: 表名 | C2: 列名 | D2: 字段类型 | E2: 是否为空 | F2: 字段注释 | G2: 码值 | H2: 备注 | I2: 修订人 | J2: 修订日期
B3: awe_do_group | C3: DONO | D3: varchar(80) | E3: NO | F3: 显示模板编号 | J3: 2023/01/12
B4: awe_do_group | C4: DOCKID | D4: varchar(32) | E4: NO | F4: 分组编号 | J4: 2023/01/12
B5: awe_do_group | C5: DOCKNAME | D5: varchar(80) | E5: YES | F5: 分组名称 | J5: 2023/01/12
B6: awe_do_group | C6: INPUTUSER | D6: varchar(32) | E6: YES | F6: 录入人 | J6: 2023/01/12
B7: awe_do_group | C7: INPUTTIME | D7: datetime | E7: YES | F7: 录入时间 | J7: 2023/01/12
B8: awe_do_group | C8: UPDATEUSER | D8: varchar(32) | E8: YES | F8: 更新人 | J8: 2023/01/12
B9: awe_do_group | C9: UPDATETIME | D9: datetime | E9: YES | F9: 更新时间 | J9: 2023/01/12
B10: awe_do_group | C10: INPUTORG | D10: varchar(32) | E10: YES | F10: 录入机构 | J10: 2023/01/12
B11: awe_do_group | C11: SORTNO | D11: varchar(32) | E11: YES | F11: 排序号 | J11: 2023/01/12
B12: awe_do_group | C12: COLCOUNT | D12: int | E12: YES | F12: 每行列数 | J12: 2023/01/12
B13: awe_do_group | C13: STYLEID | D13: varchar(32) | E13: YES | F13: 使用样式编号 | J13: 2023/01/12
B14: awe_do_group | C14: ISEXPAND | D14: char(1) | E14: YES | F14: 分组是否展开 | J14: 2023/01/12
... B19: awe_do_group | C19: GROUPHEAD | D19: varchar(4000) | E19: YES | F19: 分组头 | J19: 2023/01/12

Sheet awe_do_js_function
A1: =HYPERLINK("#表结构清单!A1","返回") | B1: OW通用js方法
B2: 表名 | C2: 列名 | D2: 字段类型 | E2: 是否为空 | F2: 字段注释 | G2: 码值 | H2: 备注 | I2: 修订人 | J2: 修订日期
B3: awe_do_js_function | C3: FUNCTIONNAME | D3: varchar(80) | E3: NO | F3: 函数名 | J3: 2023/01/12
B4: awe_do_js_function | C4: FUNCTIONPARAMS | D4: varchar(500) | E4: YES | F4: 函数参数 | J4: 2023/01/12
B5: awe_do_js_function | C5: INVOKEEXAMPLE | D5: varchar(500) | E5: YES | F5: 函数示例 | J5: 2023/01/12
B6: awe_do_js_function | C6: FUNCTIONTYPE | D6: varchar(80) | E6: YES | F6: 函数分类 | J6: 2023/01/12
B7: awe_do_js_function | C7: ISINUSE | D7: char(1) | E7: YES | F7: 是否使用 | J7: 2023/01/12
B8: awe_do_js_function | C8: FUNCTIONDESC | D8: varchar(500) | E8: YES | F8: 函数描述 | J8: 2023/01/12
B9: awe_do_js_function | C9: INPUTUSER | D9: varchar(32) | E9: YES | F9: 输入人 | J9: 2023/01/12
B10: awe_do_js_function | C10: INPUTTIME | D10: varchar(32) | E10: YES | F10: 输入时间 | J10: 2023/01/12
B11: awe_do_js_function | C11: UPDATEUSER | D11: varchar(32) | E11: YES | F11: 更新人 | J11: 2023/01/12
B12: awe_do_js_function | C12: UPDATETIME | D12: varchar(32) | E12: YES | F12: 更新时间 | J12: 2023/01/12

Sheet awe_do_keyfilter
A1: =HYPERLINK("#表结构清单!A1","返回") | B1: OW关键字查询
B2: 表名 | C2: 列名 | D2: 字段类型 | E2: 是否为空 | F2: 字段注释 | G2: 码值 | H2: 备注 | I2: 修订人 | J2: 修订日期
B3: awe_do_keyfilter | C3: SERIALNO | D3: varchar(32) | E3: NO | F3: 自动编号 | J3: 2023/01/12
B4: awe_do_keyfilter | C4: DONO | D4: varchar(80) | E4: YES | F4: 验证类型 | J4: 2023/01/12
B5: awe_do_keyfilter | C5: COLNAME | D5: varchar(80) | E5: YES | F5: 字段名 | J5: 2023/01/12
B6: awe_do_keyfilter | C6: TRADEKEY | D6: varchar(80) | E6: YES | F6: 关键字 | J6: 2023/01/12
B7: awe_do_keyfilter | C7: TRADEVALUE | D7: varchar(80) | E7: YES | F7: 值 | J7: 2023/01/12
B8: awe_do_keyfilter | C8: INPUTTIME | D8: varchar(32) | E8: YES | F8: 录入时间 | J8: 2023/01/12
B9: awe_do_keyfilter | C9: UPDATETIME | D9: varchar(32) | E9: YES | F9: 更新时间 | J9: 2023/01/12
B10: awe_do_keyfilter | C10: INPUTUSER | D10: varchar(32) | E10: YES | F10: 录入人 | J10: 2023/01/12
B11: awe_do_keyfilter | C11: UPDATEUSER | D11: varchar(32) | E11: YES | F11: 更新人 | J11: 2023/01/12
B12: awe_do_keyfilter | C12: TITLE | D12: varchar(80) | E12: YES | F12: 标题 | J12: 2023/01/12
B13: awe_do_keyfilter | C13: HIT | D13: varchar(18) | E13: YES | F13: 点击次数 | J13: 2023/01/12

Sheet awe_do_library
A1: =HYPERLINK("#表结构清单!A1","返回") | B1: OW显示模板字段信息
B2: 表名 | C2: 列名 | D2: 字段类型 | E2: 是否为空 | F2: 字段注释 | G2: 码值 | H2: 备注 | I2: 修订人 | J2: 修订日期
B3: awe_do_library | C3: DONO | D3: varchar(80) | E3: NO | F3: 显示模板编号 | J3: 2023/01/12
B4: awe_do_library | C4: COLINDEX | D4: varchar(32) | E4: NO | F4: 序号 | J4: 2023/01/12
B5: awe_do_library | C5: SORTNO | D5: varchar(32) | E5: YES | F5: 排序号 | J5: 2023/01/12
B6: awe_do_library | C6: ISINUSE | D6: varchar(6) | E6: YES | F6: 有效 | J6: 2023/01/12
B7: awe_do_library | C7: COLTABLENAME | D7: varchar(200) | E7: YES | F7: JBO类名 | J7: 2023/01/12
B8: awe_do_library | C8: COLACTUALNAME | D8: varchar(200) | E8: YES | F8: 列名 | J8: 2023/01/12
B9: awe_do_library | C9: COLNAME | D9: varchar(200) | E9: YES | F9: 使用名 | J9: 2023/01/12
B10: awe_do_library | C10: COLTYPE | D10: varchar(32) | E10: YES | F10: 值类型 | J10: 2023/01/12
B11: awe_do_library | C11: COLDEFAULTVALUE | D11: varchar(80) | E11: YES | F11: 值类型 | J11: 2023/01/12
B12: awe_do_library | C12: COLHEADER | D12: varchar(200) | E12: YES | F12: 中文显示 | J12: 2023/01/12
B13: awe_do_library | C13: COLUNIT | D13: varchar(500) | E13: YES | F13: 显示后缀 | J13: 2023/01/12
B14: awe_do_library | C14: COLCOLUMNTYPE | D14: varchar(32) | E14: YES | F14: 是否Sum | J14: 2023/01/12
... B42: awe_do_library | C42: AUTOCOMPLETEFUN | D42: varchar(200) | E42: YES | F42: 自动完成触发的js函数; | J42: 2023/01/12

Sheet awe_do_modes
A1: =HYPERLINK("#表结构清单!A1","返回") | B1: OW显示模板样式表
B2: 表名 | C2: 列名 | D2: 字段类型 | E2: 是否为空 | F2: 字段注释 | G2: 码值 | H2: 备注 | I2: 修订人 | J2: 修订日期
B3: awe_do_modes | C3: MODEID | D3: varchar(32) | E3: NO | F3: 编号 | J3: 2023/01/12
B4: awe_do_modes | C4: COLCOUNT | D4: int | E4: YES | F4: 分栏数 | J4: 2023/01/12
B5: awe_do_modes | C5: MODENAME | D5: varchar(80) | E5: YES | F5: 样式名 | J5: 2023/01/12
B6: awe_do_modes | C6: MODEDESC | D6: varchar(500) | E6: YES | F6: 样式描述 | J6: 2023/01/12
B7: awe_do_modes | C7: CONTROLHEAD | D7: varchar(200) | E7: YES | F7: 控制头文件地址 | J7: 2023/01/12
B8: awe_do_modes | C8: CONTROLFOOT | D8: varchar(200) | E8: YES | F8: 控制尾文件地址 | J8: 2023/01/12
B9: awe_do_modes | C9: GROUPBODYPARSER | D9: varchar(500) | E9: YES | F9: 类型体解析 | J9: 2023/01/12
B10: awe_do_modes | C10: HTMLFOOT | D10: text | E10: YES | F10: HTML尾 | J10: 2023/01/12
B11: awe_do_modes | C11: HTMLHEAD | D11: text | E11: YES | F11: HTML头 | J11: 2023/01/12
B12: awe_do_modes | C12: GROUPBODY2 | D12: varchar(4000) | E12: YES | F12: 分组体2 | J12: 2023/01/12
B13: awe_do_modes | C13: GROUPBODY1 | D13: varchar(4000) | E13: YES | F13: 分组体1 | J13: 2023/01/12
B14: awe_do_modes | C14: GROUPFOOT | D14: text | E14: YES | F14: 分组尾信息 | J14: 2023/01/12
B15: awe_do_modes | C15: GROUPHEAD | D15: text | E15: YES | F15: 分组头信息 | J15: 2023/01/12

Sheet awe_do_validate
A1: =HYPERLINK("#表结构清单!A1","返回") | B1: 数据验证类
B2: 表名 | C2: 列名 | D2: 字段类型 | E2: 是否为空 | F2: 字段注释 | G2: 码值 | H2: 备注 | I2: 修订人 | J2: 修订日期
B3: awe_do_validate | C3: VALIDATORNAME | D3: varchar(80) | E3: NO | F3: 验证名 | J3: 2023/01/12
B4: awe_do_validate | C4: VALIDATORTYPE | D4: varchar(18) | E4: YES | F4: 验证类型 | J4: 2023/01/12
B5: awe_do_validate | C5: ERRMSG | D5: varchar(200) | E5: YES | F5: 出错信息 | J5: 2023/01/12
B6: awe_do_validate | C6: CONTROLTO | D6: varchar(80) | E6: YES | F6: 对应控件名 | J6: 2023/01/12
B7: awe_do_validate | C7: REGULAR | D7: varchar(500) | E7: YES | F7: 规则 | J7: 2023/01/12
B8: awe_do_validate | C8: CUSFUNCTION | D8: varchar(200) | E8: YES | F8: 方法 | J8: 2023/01/12
B9: awe_do_validate | C9: COMPARETO | D9: varchar(200) | E9: YES | F9: 比较控件 | J9: 2023/01/12
B10: awe_do_validate | C10: MINVALUE | D10: varchar(80) | E10: YES | F10: 最小值 | J10: 2023/01/12
B11: awe_do_validate | C11: MAXVALUE | D11: varchar(80) | E11: YES | F11: 最大值 | J11: 2023/01/12
B12: awe_do_validate | C12: INPUTTIME | D12: datetime | E12: YES | F12: 输入时间 | J12: 2023/01/12
B13: awe_do_validate | C13: ISSYSTEM | D13: char(1) | E13: YES | F13: 系统保留 | J13: 2023/01/12
B14: awe_do_validate | C14: COMPAREOBJ | D14: varchar(80) | E14: YES | F14: 有条件比较对象 | J14: 2023/01/12
... B16: awe_do_validate | C16: BUSINESSTYPE | D16: varchar(18) | E16: YES | F16: 业务类型 | J16: 2023/01/12

Sheet awe_do_validate_catalog
A1: =HYPERLINK("#表结构清单!A1","返回") | B1: 数据验证业务分类
B2: 表名 | C2: 列名 | D2: 字段类型 | E2: 是否为空 | F2: 字段注释 | G2: 码值 | H2: 备注 | I2: 修订人 | J2: 修订日期
B3: awe_do_validate_catalog | C3: CATALOGNO | D3: varchar(32) | E3: NO | F3: 分类编号 | J3: 2023/01/12
B4: awe_do_validate_catalog | C4: CATALOGTITLE | D4: varchar(80) | E4: YES | F4: 分类标题 | J4: 2023/01/12
B5: awe_do_validate_catalog | C5: SORTNO | D5: varchar(32) | E5: YES | F5: 排序号 | J5: 2023/01/12
B6: awe_do_validate_catalog | C6: ISINUSE | D6: char(1) | E6: YES | F6: 是否使用 | J6: 2023/01/12
B7: awe_do_validate_catalog | C7: ATTRIBUTE1 | D7: varchar(32) | E7: YES | F7: 参数1 | J7: 2023/01/12
B8: awe_do_validate_catalog | C8: ATTRIBUTE2 | D8: varchar(32) | E8: YES | F8: 参数2 | J8: 2023/01/12
B9: awe_do_validate_catalog | C9: ATTRIBUTE3 | D9: varchar(32) | E9: YES | F9: 参数3 | J9: 2023/01/12
B10: awe_do_validate_catalog | C10: ATTRIBUTE4 | D10: varchar(32) | E10: YES | F10: 参数4 | J10: 2023/01/12
B11: awe_do_validate_catalog | C11: ATTRIBUTE5 | D11: varchar(500) | E11: YES | F11: 参数5 | J11: 2023/01/12
B12: awe_do_validate_catalog | C12: ATTRIBUTE6 | D12: varchar(500) | E12: YES | F12: 参数6 | J12: 2023/01/12
B13: awe_do_validate_catalog | C13: ATTRIBUTE7 | D13: varchar(500) | E13: YES | F13: 参数7 | J13: 2023/01/12
B14: awe_do_validate_catalog | C14: ATTRIBUTE8 | D14: varchar(500) | E14: YES | F14: 参数8 | J14: 2023/01/12

Sheet awe_dw_context
A1: =HYPERLINK("#表结构清单!A1","返回") | B1: 显示模板环境
B2: 表名 | C2: 列名 | D2: 字段类型 | E2: 是否为空 | F2: 字段注释 | G2: 码值 | H2: 备注 | I2: 修订人 | J2: 修订日期
B3: awe_dw_context | C3: SERIALNO | D3: varchar(32) | E3: NO | F3: 自动编号 | J3: 2023/01/12
B4: awe_dw_context | C4: OBJECTTYPE | D4: varchar(32) | E4: YES | F4: 对象类型 | J4: 2023/01/12
B5: awe_dw_context | C5: OBJECTNO | D5: varchar(32) | E5: YES | F5: 对象名 | J5: 2023/01/12
B6: awe_dw_context | C6: CONTENT | D6: varchar(4000) | E6: YES | F6: 内容 | J6: 2023/01/12

Sheet awe_function_info
A1: =HYPERLINK("#表结构清单!A1","返回") | B1: 功能点信息
B2: 表名 | C2: 列名 | D2: 字段类型 | E2: 是否为空 | F2: 字段注释 | G2: 码值 | H2: 备注 | I2: 修订人 | J2: 修订日期
B3: awe_function_info | C3: FUNCTIONID | D3: varchar(32) | E3: NO | F3: 功能点id | J3: 2023/01/12
B4: awe_function_info | C4: FUNCTIONNAME | D4: varchar(80) | E4: YES | F4: 功能点名 | J4: 2023/01/12
B5: awe_function_info | C5: SORTNO | D5: varchar(32) | E5: YES | F5: 排序号 | J5: 2023/01/12
B6: awe_function_info | C6: ISINUSE | D6: varchar(6) | E6: YES | F6: 是否可用 | G6: =HYPERLINK("#码值映射清单!B1110","IsInUse") | J6: 2023/01/12
B7: awe_function_info | C7: APPID | D7: varchar(32) | E7: YES | F7: 菜单ID | J7: 2023/01/12
B8: awe_function_info | C8: MODULEID | D8: varchar(32) | E8: YES | F8: 模块ID | J8: 2023/01/12
B9: awe_function_info | C9: MODULENAME | D9: varchar(80) | E9: YES | F9: 模块名 | J9: 2023/01/12
B10: awe_function_info | C10: ENTRYURL | D10: varchar(500) | E10: YES | F10: 允许的URL | J10: 2023/01/12
B11: awe_function_info | C11: REMARK | D11: varchar(500) | E11: YES | F11: 备注 | J11: 2023/01/12
B12: awe_function_info | C12: INPUTORGID | D12: varchar(32) | E12: YES | F12: 登记机构 | J12: 2023/01/12
B13: awe_function_info | C13: INPUTUSERID | D13: varchar(32) | E13: YES | F13: 登记人 | J13: 2023/01/12
B14: awe_function_info | C14: INPUTTIME | D14: datetime | E14: YES | F14: 登记时间 | J14: 2023/01/12
B15: awe_function_info | C15: UPDATEORGID | D15: varchar(32) | E15: YES | F15: 更新机构 | J15: 2023/01/12
B16: awe_function_info | C16: UPDATEUSERID | D16: varchar(32) | E16: YES | F16: 更新人 | J16: 2023/01/12
B17: awe_function_info | C17: UPDATETIME | D17: datetime | E17: YES | F17: 更新时间 | J17: 2023/01/12

Sheet awe_function_url
A1: =HYPERLINK("#表结构清单!A1","返回") | B1: 功能点URL
B2: 表名 | C2: 列名 | D2: 字段类型 | E2: 是否为空 | F2: 字段注释 | G2: 码值 | H2: 备注 | I2: 修订人 | J2: 修订日期
B3: awe_function_url | C3: SERIALNO | D3: varchar(32) | E3: NO | F3: 流水号 | J3: 2023/01/12
B4: awe_function_url | C4: FUNCTIONID | D4: varchar(32) | E4: YES | F4: 功能点ID | J4: 2023/01/12
B5: awe_function_url | C5: RIGHTPOINTTYPE | D5: varchar(80) | E5: NO | F5: 权限类型 | G5: =HYPERLINK("#码值映射清单!B2943","RightPointType") | J5: 2023/01/12
B6: awe_function_url | C6: RIGHTPOINTNAME | D6: varchar(80) | E6: NO | F6: 权限名 | J6: 2023/01/12
B7: awe_function_url | C7: URL | D7: varchar(500) | E7: NO | F7: URL | J7: 2023/01/12
B8: awe_function_url | C8: REMARK | D8: varchar(500) | E8: YES | F8: 备注 | J8: 2023/01/12
B9: awe_function_url | C9: INPUTORGID | D9: varchar(32) | E9: YES | F9: 登记机构 | J9: 2023/01/12
B10: awe_function_url | C10: INPUTUSERID | D10: varchar(32) | E10: YES | F10: 登记用户 | J10: 2023/01/12
B11: awe_function_url | C11: INPUTTIME | D11: varchar(32) | E11: YES | F11: 登记时间 | J11: 2023/01/12
B12: awe_function_url | C12: UPDATEORGID | D12: varchar(32) | E12: YES | F12: 更新机构 | J12: 2023/01/12
B13: awe_function_url | C13: UPDATEUSERID | D13: varchar(32) | E13: YES | F13: 更新用户 | J13: 2023/01/12
B14: awe_function_url | C14: UPDATETIME | D14: varchar(32) | E14: YES | F14: 更新时间 | J14: 2023/01/12

Sheet awe_group_catalog
A1: =HYPERLINK("#表结构清单!A1","返回") | B1: 组合页面目录信息
B2: 表名 | C2: 列名 | D2: 字段类型 | E2: 是否为空 | F2: 字段注释 | G2: 码值 | H2: 备注 | I2: 修订人 | J2: 修订日期
B3: awe_group_catalog | C3: GROUPID | D3: varchar(32) | E3: NO | F3: 组合编号 | J3: 2023/01/12
B4: awe_group_catalog | C4: GROUPNAME | D4: varchar(80) | E4: YES | F4: 组合名称 | J4: 2023/01/12
B5: awe_group_catalog | C5: GROUPDESCRIBE | D5: varchar(200) | E5: YES | F5: 描述 | J5: 2023/01/12
B6: awe_group_catalog | C6: CLASSIFYID | D6: varchar(32) | E6: YES | F6: 分类编号 | J6: 2023/01/12
B7: awe_group_catalog | C7: DISPLAYTYPE | D7: varchar(18) | E7: YES | F7: 展现类型 | G7: =HYPERLINK("#码值映射清单!B4203","DisplayType") | J7: 2023/01/12
B8: awe_group_catalog | C8: DEFAULTPAGE | D8: varchar(500) | E8: YES | F8: 默认页面 | J8: 2023/01/12
B9: awe_group_catalog | C9: ISINUSE | D9: varchar(6) | E9: YES | F9: 是否使用 | G9: =HYPERLINK("#码值映射清单!B5150","YesNo") | J9: 2023/01/12
B10: awe_group_catalog | C10: ATTRIBUTE1 | D10: varchar(200) | E10: YES | F10: 属性1 | G10: =HYPERLINK("#码值映射清单!B10029","有无") | J10: 2023/01/12
B11: awe_group_catalog | C11: ATTRIBUTE2 | D11: varchar(200) | E11: YES | F11: 属性2 | J11: 2023/01/12
B12: awe_group_catalog | C12: ATTRIBUTE3 | D12: varchar(200) | E12: YES | F12: 属性3 | J12: 2023/01/12
B13: awe_group_catalog | C13: ATTRIBUTE4 | D13: varchar(200) | E13: YES | F13: 属性4 | J13: 2023/01/12
B14: awe_group_catalog | C14: ATTRIBUTE5 | D14: varchar(200) | E14: YES | F14: 属性5 | J14: 2023/01/12
B15: awe_group_catalog | C15: INPUTORG | D15: varchar(32) | E15: YES | F15: 创建机构 | J15: 2023/01/12
B16: awe_group_catalog | C16: INPUTUSER | D16: varchar(32) | E16: YES | F16: 创建人员 | J16: 2023/01/12
B17: awe_group_catalog | C17: INPUTTIME | D17: datetime | E17: YES | F17: 创建日期 | J17: 2023/01/12
B18: awe_group_catalog | C18: UPDATEUSER | D18: varchar(32) | E18: YES | F18: 更新人 | J18: 2023/01/12
B19: awe_group_catalog | C19: UPDATETIME | D19: datetime | E19: YES | F19: 更新日期 | J19: 2023/01/12
B20: awe_group_catalog | C20: REMARK | D20: varchar(500) | E20: YES | F20: 备注 | J20: 2023/01/12

Sheet awe_group_classify
A1: =HYPERLINK("#表结构清单!A1","返回") | B1: 组合页面分类信息表
B2: 表名 | C2: 列名 | D2: 字段类型 | E2: 是否为空 | F2: 字段注释 | G2: 码值 | H2: 备注 | I2: 修订人 | J2: 修订日期
B3: awe_group_classify | C3: CLASSIFYID | D3: varchar(32) | E3: NO | F3: 分类编号 | J3: 2023/01/12
B4: awe_group_classify | C4: CLASSIFYNAME | D4: varchar(200) | E4: YES | F4: 分类名称 | J4: 2023/01/12
B5: awe_group_classify | C5: SORTNO | D5: varchar(32) | E5: YES | F5: 排序号 | J5: 2023/01/12
B6: awe_group_classify | C6: ISINUSE | D6: varchar(6) | E6: YES | F6: 是否使用 | G6: =HYPERLINK("#码值映射清单!B1110","IsInUse") | J6: 2023/01/12
B7: awe_group_classify | C7: INPUTUSER | D7: varchar(80) | E7: YES | F7: 创建人员 | J7: 2023/01/12
B8: awe_group_classify | C8: INPUTORG | D8: varchar(80) | E8: YES | F8: 创建机构 | J8: 2023/01/12
B9: awe_group_classify | C9: INPUTTIME | D9: varchar(80) | E9: YES | F9: 创建日期 | J9: 2023/01/12
B10: awe_group_classify | C10: UPDATEUSER | D10: varchar(80) | E10: YES | F10: 更新机构 | J10: 2023/01/12
B11: awe_group_classify | C11: UPDATEORG | D11: varchar(80) | E11: YES | F11: 更新人 | J11: 2023/01/12
B12: awe_group_classify | C12: UPDATETIME | D12: varchar(32) | E12: YES | F12: 更新日期 | J12: 2023/01/12

Sheet awe_group_item
A1: =HYPERLINK("#表结构清单!A1","返回") | B1: 组合页面详细信息表
B2: 表名 | C2: 列名 | D2: 字段类型 | E2: 是否为空 | F2: 字段注释 | G2: 码值 | H2: 备注 | I2: 修订人 | J2: 修订日期
B3: awe_group_item | C3: GROUPID | D3: varchar(32) | E3: NO | F3: 组合编号 | J3: 2023/01/12
B4: awe_group_item | C4: ITEMNO | D4: varchar(32) | E4: NO | F4: 项目编号 | J4: 2023/01/12
B5: awe_group_item | C5: ITEMNAME | D5: varchar(80) | E5: YES | F5: 项目名称 | J5: 2023/01/12
B6: awe_group_item | C6: ITEMDESCRIBE | D6: varchar(200) | E6: YES | F6: 描述 | J6: 2023/01/12
B7: awe_group_item | C7: SORTNO | D7: varchar(32) | E7: YES | F7: 排序号 | J7: 2023/01/12
B8: awe_group_item | C8: URL | D8: varchar(500) | E8: YES | F8: 页面路径 | J8: 2023/01/12
B9: awe_group_item | C9: PARAMS | D9: varchar(500) | E9: YES | F9: 参数 | J9: 2023/01/12
B10: awe_group_item | C10: CHECKMETHOD | D10: varchar(500) | E10: YES | F10: 检验方法 | J10: 2023/01/12
B11: awe_group_item | C11: ISINUSE | D11: varchar(6) | E11: YES | F11: 是否使用 | G11: =HYPERLINK("#码值映射清单!B5150","YesNo") | J11: 2023/01/12
B12: awe_group_item | C12: ATTRIBUTE1 | D12: varchar(200) | E12: YES | F12: 属性1 | J12: 2023/01/12
B13: awe_group_item | C13: ATTRIBUTE2 | D13: varchar(200) | E13: YES | F13: 属性2 | J13: 2023/01/12
B14: awe_group_item | C14: ATTRIBUTE3 | D14: varchar(200) | E14: YES | F14: 属性3 | J14: 2023/01/12
B15: awe_group_item | C15: ATTRIBUTE4 | D15: varchar(200) | E15: YES | F15: 属性4 | J15: 2023/01/12
B16: awe_group_item | C16: ATTRIBUTE5 | D16: varchar(200) | E16: YES | F16: 属性5 | J16: 2023/01/12
B17: awe_group_item | C17: INPUTORG | D17: varchar(32) | E17: YES | F17: 创建机构 | J17: 2023/01/12
B18: awe_group_item | C18: INPUTUSER | D18: varchar(32) | E18: YES | F18: 创建人员 | J18: 2023/01/12
B19: awe_group_item | C19: INPUTTIME | D19: datetime | E19: YES | F19: 创建日期 | J19: 2023/01/12
B20: awe_group_item | C20: UPDATEUSER | D20: varchar(32) | E20: YES | F20: 更新人 | J20: 2023/01/12
B21: awe_group_item | C21: UPDATETIME | D21: datetime | E21: YES | F21: 更新日期 | J21: 2023/01/12
B22: awe_group_item | C22: REMARK | D22: varchar(500) | E22: YES | F22: 备注 | J22: 2023/01/12

Sheet awe_href_info
A1: =HYPERLINK("#表结构清单!A1","返回") | B1: 链接信息
B2: 表名 | C2: 列名 | D2: 字段类型 | E2: 是否为空 | F2: 字段注释 | G2: 码值 | H2: 备注 | I2: 修订人 | J2: 修订日期
B3: awe_href_info | C3: HREF | D3: varchar(500) | E3: NO | F3: 链接 | J3: 2023/01/12
B4: awe_href_info | C4: HREFTYPE | D4: varchar(500) | E4: YES | F4: 链接类型 | J4: 2023/01/12
B5: awe_href_info | C5: HREFDESCRIBE | D5: varchar(500) | E5: YES | F5: 描述 | J5: 2023/01/12
B6: awe_href_info | C6: INPUTORGID | D6: varchar(32) | E6: YES | F6: 登记机构 | J6: 2023/01/12
B7: awe_href_info | C7: INPUTUSERID | D7: varchar(32) | E7: YES | F7: 登记人 | J7: 2023/01/12
B8: awe_href_info | C8: INPUTTIME | D8: datetime | E8: YES | F8: 登记时间 | J8: 2023/01/12
B9: awe_href_info | C9: UPDATEORGID | D9: varchar(32) | E9: YES | F9: 更新机构 | J9: 2023/01/12
B10: awe_href_info | C10: UPDATEUSERID | D10: varchar(32) | E10: YES | F10: 更新人 | J10: 2023/01/12
B11: awe_href_info | C11: UPDATETIME | D11: datetime | E11: YES | F11: 更新时间 | J11: 2023/01/12

Sheet awe_jsp_runtime
A1: =HYPERLINK("#表结构清单!A1","返回") | B1: jsp页面访问统计表
B2: 表名 | C2: 列名 | D2: 字段类型 | E2: 是否为空 | F2: 字段注释 | G2: 码值 | H2: 备注 | I2: 修订人 | J2: 修订日期
B3: awe_jsp_runtime | C3: JRTYPE | D3: varchar(6) | E3: YES | F3: 统计类型 | J3: 2023/01/12
B4: awe_jsp_runtime | C4: JRTERM | D4: varchar(18) | E4: YES | F4: 统计周期 | J4: 2023/01/12
B5: awe_jsp_runtime | C5: SERVERID | D5: varchar(200) | E5: YES | F5: 服务标识 | J5: 2023/01/12
B6: awe_jsp_runtime | C6: JRCOUNT | D6: int | E6: YES | F6: 运行次数 | J6: 2023/01/12
B7: awe_jsp_runtime | C7: JRTIME | D7: decimal(18,2) | E7: YES | F7: 耗时 | J7: 2023/01/12

Sheet awe_menu_info
A1: =HYPERLINK("#表结构清单!A1","返回") | B1: 系统菜单表
B2: 表名 | C2: 列名 | D2: 字段类型 | E2: 是否为空 | F2: 字段注释 | G2: 码值 | H2: 备注 | I2: 修订人 | J2: 修订日期
B3: awe_menu_info | C3: MENUID | D3: varchar(32) | E3: NO | F3: 菜单编号 | J3: 2023/01/12
B4: awe_menu_info | C4: MENUNAME | D4: varchar(500) | E4: YES | F4: 菜单名称 | J4: 2023/01/12
B5: awe_menu_info | C5: DISPLAYNAME | D5: varchar(32) | E5: YES | F5: 展示名称 | J5: 2023/01/12
B6: awe_menu_info | C6: SORTNO | D6: varchar(32) | E6: YES | F6: 排序号 | J6: 2023/01/12
B7: awe_menu_info | C7: URL | D7: varchar(500) | E7: YES | F7: URL路径 | J7: 2023/01/12
B8: awe_menu_info | C8: URLPARAM | D8: varchar(500) | E8: YES | F8: 参数 | J8: 2023/01/12
B9: awe_menu_info | C9: TARGET | D9: varchar(32) | E9: YES | F9: 目标窗口 | J9: 2023/01/12
B10: awe_menu_info | C10: STYLE | D10: varchar(32) | E10: YES | F10: 样式 | J10: 2023/01/12
B11: awe_menu_info | C11: ISINUSE | D11: varchar(6) | E11: YES | F11: 是否使用 | G11: =HYPERLINK("#码值映射清单!B10081","MenuStatus") | J11: 2023/01/12
B12: awe_menu_info | C12: REMARK | D12: varchar(500) | E12: YES | F12: 备注 | J12: 2023/01/12
B13: awe_menu_info | C13: INPUTORGID | D13: varchar(32) | E13: YES | F13: 录入机构 | J13: 2023/01/12
B14: awe_menu_info | C14: INPUTUSERID | D14: varchar(32) | E14: YES | F14: 录入人 | J14: 2023/01/12
B15: awe_menu_info | C15: INPUTTIME | D15: varchar(32) | E15: YES | F15: 录入时间 | J15: 2023/01/12
B16: awe_menu_info | C16: UPDATEORGID | D16: varchar(32) | E16: YES | F16: 更新机构 | J16: 2023/01/12
B17: awe_menu_info | C17: UPDATEUSERID | D17: varchar(32) | E17: YES | F17: 更新人 | J17: 2023/01/12
B18: awe_menu_info | C18: UPDATETIME | D18: varchar(32) | E18: YES | F18: 更新时间 | J18: 2023/01/12
B19: awe_menu_info | C19: ACCESSTYPE | D19: varchar(32) | E19: YES | F19: 打开方式 | G19: =HYPERLINK("#码值映射清单!B10084","AccessType") | J19: 2023/01/12
B20: awe_menu_info | C20: ICON | D20: varchar(80) | E20: YES | F20: 图标 | J20: 2023/01/12
B21: awe_menu_info | C21: APPICON | D21: varchar(80) | E21: YES | F21: 子系统图标 | J21: 2023/01/12
B22: awe_menu_info | C22: USERID | D22: varchar(32) | E22: YES | F22: 用户Id | J22: 2023/01/12
B23: awe_menu_info | C23: QUICKMENUID | D23: varchar(32) | E23: YES | F23: 快捷菜单ID | J23: 2023/01/12
B24: awe_menu_info | C24: INPUTDATE | D24: datetime | E24: YES | F24: 录入日期 | J24: 2023/01/12
B25: awe_menu_info | C25: UPDATEDATE | D25: datetime | E25: YES | F25: 更新日期 | J25: 2023/01/12

Sheet awe_message_info
A1: =HYPERLINK("#表结构清单!A1","返回") | B1: 站内信对象
B2: 表名 | C2: 列名 | D2: 字段类型 | E2: 是否为空 | F2: 字段注释 | G2: 码值 | H2: 备注 | I2: 修订人 | J2: 修订日期
B3: awe_message_info | C3: MESSAGEID | D3: varchar(32) | E3: NO | F3: 消息编号 | J3: 2023/01/12
B4: awe_message_info | C4: RELATIVEID | D4: varchar(32) | E4: YES | F4: 回复消息编号 | J4: 2023/01/12
B5: awe_message_info | C5: MESSAGETITLE | D5: varchar(200) | E5: YES | F5: 消息标题 | J5: 2023/01/12
B6: awe_message_info | C6: SENDTIME | D6: varchar(32) | E6: YES | F6: 发送时间 | J6: 2023/01/12
B7: awe_message_info | C7: USERID | D7: varchar(32) | E7: YES | F7: 发送人 | J7: 2023/01/12
B8: awe_message_info | C8: MESSAGEDESC | D8: varchar(4000) | E8: YES | F8: 消息主体 | J8: 2023/01/12

Sheet awe_message_user
A1: =HYPERLINK("#表结构清单!A1","返回") | B1: 站内信发送/关联用户
B2: 表名 | C2: 列名 | D2: 字段类型 | E2: 是否为空 | F2: 字段注释 | G2: 码值 | H2: 备注 | I2: 修订人 | J2: 修订日期
B3: awe_message_user | C3: MESSAGEID | D3: varchar(32) | E3: NO | F3: 消息编号 | J3: 2023/01/12
B4: awe_message_user | C4: USERID | D4: varchar(32) | E4: NO | F4: 发送用户 | J4: 2023/01/12
B5: awe_message_user | C5: FIRSTSHOWTIME | D5: varchar(32) | E5: YES | F5: 收到时间 | J5: 2023/01/12
B6: awe_message_user | C6: READTIME | D6: varchar(32) | E6: YES | F6: 读取时间 | J6: 2023/01/12
B7: awe_message_user | C7: DELETETIME | D7: varchar(32) | E7: YES | F7: 删除时间 | J7: 2023/01/12

Sheet awe_query_info
A1: =HYPERLINK("#表结构清单!A1","返回") | B1: 查询配置基本信息
B2: 表名 | C2: 列名 | D2: 字段类型 | E2: 是否为空 | F2: 字段注释 | G2: 码值 | H2: 备注 | I2: 修订人 | J2: 修订日期
B3: awe_query_info | C3: QUERYSCHEMENO | D3: varchar(32) | E3: NO | F3: 查询方案编号 | J3: 2023/01/12
B4: awe_query_info | C4: QUERYSCHEMENAME | D4: varchar(80) | E4: YES | F4: 查询方案名称 | J4: 2023/01/12
B5: awe_query_info | C5: BIZOBJCLASS | D5: varchar(80) | E5: NO | F5: 主对象 | J5: 2023/01/12
B6: awe_query_info | C6: RELATEDCLASS | D6: varchar(500) | E6: YES | F6: 关联对象串;JSON格式） | J6: 2023/01/12
B7: awe_query_info | C7: GROUPITEMS | D7: varchar(500) | E7: YES | F7: 汇总信息项 | J7: 2023/01/12
B8: awe_query_info | C8: SUMMARYITEMS | D8: varchar(500) | E8: YES | F8: 合计信息项 | J8: 2023/01/12
B9: awe_query_info | C9: ISPRIVATE | D9: varchar(6) | E9: YES | F9: 是否私有 | J9: 2023/01/12
B10: awe_query_info | C10: FREQUENCY | D10: int | E10: YES | F10: 查询频率 | J10: 2023/01/12
B11: awe_query_info | C11: USERID | D11: varchar(32) | E11: YES | F11: 录入人 | J11: 2023/01/12
B12: awe_query_info | C12: ORGID | D12: varchar(32) | E12: YES | F12: 录入机构 | J12: 2023/01/12
B13: awe_query_info | C13: UPDATEDATE | D13: datetime | E13: YES | F13: 更新时间 | J13: 2023/01/12
B14: awe_query_info | C14: QUERYSQL | D14: text | E14: YES | F14: 查询脚本 | J14: 2023/01/12
... B20: awe_query_info | C20: RELATION | D20: text | E20: YES | F20: 对象间关系 | J20: 2023/01/12

Sheet awe_query_user
A1: =HYPERLINK("#表结构清单!A1","返回") | B1: 快速查询统计表
B2: 表名 | C2: 列名 | D2: 字段类型 | E2: 是否为空 | F2: 字段注释 | G2: 码值 | H2: 备注 | I2: 修订人 | J2: 修订日期
B3: awe_query_user | C3: SERIALNO | D3: varchar(32) | E3: NO | F3: 编号 | J3: 2023/01/12
B4: awe_query_user | C4: USERID | D4: varchar(32) | E4: YES | F4: 用户编号 | J4: 2023/01/12
B5: awe_query_user | C5: QUERYID | D5: varchar(32) | E5: YES | F5: 查询id | J5: 2023/01/12
B6: awe_query_user | C6: STATUS | D6: varchar(6) | E6: YES | F6: 状态 | J6: 2023/01/12
B7: awe_query_user | C7: REMARK | D7: varchar(500) | E7: YES | F7: 备注 | J7: 2023/01/12
B8: awe_query_user | C8: PATH | D8: varchar(500) | E8: YES | F8: 路径 | J8: 2023/01/12
B9: awe_query_user | C9: FILENAME | D9: varchar(500) | E9: YES | F9: 文件名 | J9: 2023/01/12
B10: awe_query_user | C10: BAK1 | D10: varchar(32) | E10: YES | F10: 预留1 | J10: 2023/01/12
B11: awe_query_user | C11: BAK2 | D11: varchar(32) | E11: YES | F11: 预留2 | J11: 2023/01/12

Sheet awe_quick_href
A1: =HYPERLINK("#表结构清单!A1","返回") | B1: 快捷链接
B2: 表名 | C2: 列名 | D2: 字段类型 | E2: 是否为空 | F2: 字段注释 | G2: 码值 | H2: 备注 | I2: 修订人 | J2: 修订日期
B3: awe_quick_href | C3: QUICKID | D3: varchar(32) | E3: NO | F3: 编号 | J3: 2023/01/12
B4: awe_quick_href | C4: QUICKNAME | D4: varchar(80) | E4: NO | F4: 名称 | J4: 2023/01/12
B5: awe_quick_href | C5: QUICKTYPE | D5: varchar(80) | E5: NO | F5: 类型 | J5: 2023/01/12
B6: awe_quick_href | C6: QUICKPARAMS | D6: varchar(500) | E6: YES | F6: 参数 | J6: 2023/01/12
B7: awe_quick_href | C7: REMARK | D7: varchar(500) | E7: YES | F7: 备注 | J7: 2023/01/12
B8: awe_quick_href | C8: FORUSER | D8: varchar(32) | E8: NO | F8: 服务用户 | J8: 2023/01/12
B9: awe_quick_href | C9: ISINUSE | D9: char(1) | E9: YES | F9: 有效标记，代码CODE_LIBRARY.CodeNo=IsInUse | J9: 2023/01/12
B10: awe_quick_href | C10: SORTNO | D10: varchar(32) | E10: YES | F10: 排序 | J10: 2023/01/12
B11: awe_quick_href | C11: INPUTORG | D11: varchar(32) | E11: YES | F11: 录入机构 | J11: 2023/01/12
B12: awe_quick_href | C12: INPUTUSER | D12: varchar(32) | E12: YES | F12: 录入用户 | J12: 2023/01/12
B13: awe_quick_href | C13: INPUTTIME | D13: datetime | E13: YES | F13: 录入时间 | J13: 2023/01/12
B14: awe_quick_href | C14: UPDATEORG | D14: varchar(32) | E14: YES | F14: 更新机构 | J14: 2023/01/12
... B16: awe_quick_href | C16: UPDATETIME | D16: datetime | E16: YES | F16: 更新时间 | J16: 2023/01/12

Sheet awe_record_info
A1: =HYPERLINK("#表结构清单!A1","返回") | B1: 特殊信息记录表
B2: 表名 | C2: 列名 | D2: 字段类型 | E2: 是否为空 | F2: 字段注释 | G2: 码值 | H2: 备注 | I2: 修订人 | J2: 修订日期
B3: awe_record_info | C3: SERIALNO | D3: varchar(32) | E3: NO | F3: 流水号 | J3: 2023/01/12
B4: awe_record_info | C4: RECORDUSER | D4: varchar(32) | E4: YES | F4: 记录员 | J4: 2023/01/12
B5: awe_record_info | C5: RECORDTIME | D5: varchar(32) | E5: YES | F5: 记录时间 | J5: 2023/01/12
B6: awe_record_info | C6: RECORDREASON | D6: varchar(500) | E6: YES | F6: 记录原因 | J6: 2023/01/12
B7: awe_record_info | C7: RECORDCONTENT | D7: varchar(4000) | E7: YES | F7: 记录内容 | J7: 2023/01/12

Sheet awe_right_menu
A1: =HYPERLINK("#表结构清单!A1","返回") | B1: 菜单权限表
B2: 表名 | C2: 列名 | D2: 字段类型 | E2: 是否为空 | F2: 字段注释 | G2: 码值 | H2: 备注 | I2: 修订人 | J2: 修订日期
B3: awe_right_menu | C3: RIGHTID | D3: varchar(32) | E3: NO | F3: 权限编号 | J3: 2023/01/12
B4: awe_right_menu | C4: MENUID | D4: varchar(32) | E4: NO | F4: 菜单编号 | J4: 2023/01/12

Sheet awe_role_function
A1: =HYPERLINK("#表结构清单!A1","返回") | B1: 角色和功能点关联表
B2: 表名 | C2: 列名 | D2: 字段类型 | E2: 是否为空 | F2: 字段注释 | G2: 码值 | H2: 备注 | I2: 修订人 | J2: 修订日期
B3: awe_role_function | C3: ROLEID | D3: varchar(32) | E3: NO | F3: 角色编号 | J3: 2023/01/12
B4: awe_role_function | C4: FUNCTIONID | D4: varchar(32) | E4: NO | F4: 功能点编号 | J4: 2023/01/12

Sheet awe_role_menu
A1: =HYPERLINK("#表结构清单!A1","返回") | B1: 角色、菜单关联
B2: 表名 | C2: 列名 | D2: 字段类型 | E2: 是否为空 | F2: 字段注释 | G2: 码值 | H2: 备注 | I2: 修订人 | J2: 修订日期
B3: awe_role_menu | C3: ROLEID | D3: varchar(32) | E3: NO | F3: 角色编号 | J3: 2023/01/12
B4: awe_role_menu | C4: MENUID | D4: varchar(32) | E4: NO | F4: 菜单编号 | J4: 2023/01/12

Sheet awe_role_right
A1: =HYPERLINK("#表结构清单!A1","返回") | B1: 角色权限系统表
B2: 表名 | C2: 列名 | D2: 字段类型 | E2: 是否为空 | F2: 字段注释 | G2: 码值 | H2: 备注 | I2: 修订人 | J2: 修订日期
B3: awe_role_right | C3: ROLEID | D3: varchar(32) | E3: NO | F3: 角色编号 | J3: 2023/01/12
B4: awe_role_right | C4: RIGHTID | D4: varchar(32) | E4: NO | F4: 权限编号 | J4: 2023/01/12
B5: awe_role_right | C5: REMARK | D5: varchar(500) | E5: YES | F5: 备注 | J5: 2023/01/12
B6: awe_role_right | C6: INPUTORG | D6: varchar(32) | E6: YES | F6: 登记机构 | J6: 2023/01/12
B7: awe_role_right | C7: INPUTUSER | D7: varchar(32) | E7: YES | F7: 登记人 | J7: 2023/01/12
B8: awe_role_right | C8: INPUTTIME | D8: datetime | E8: YES | F8: 登记时间 | J8: 2023/01/12
B9: awe_role_right | C9: UPDATEUSER | D9: varchar(32) | E9: YES | F9: 更新人 | J9: 2023/01/12
B10: awe_role_right | C10: UPDATETIME | D10: datetime | E10: YES | F10: 更新时间 | J10: 2023/01/12

Sheet awe_role_url
A1: =HYPERLINK("#表结构清单!A1","返回") | B1: 角色权限URL
B2: 表名 | C2: 列名 | D2: 字段类型 | E2: 是否为空 | F2: 字段注释 | G2: 码值 | H2: 备注 | I2: 修订人 | J2: 修订日期
B3: awe_role_url | C3: ROLEID | D3: varchar(32) | E3: NO | F3: 角色编号 | J3: 2023/01/12
B4: awe_role_url | C4: URL | D4: varchar(500) | E4: NO | F4: URL路径 | J4: 2023/01/12
B5: awe_role_url | C5: INPUTORGID | D5: varchar(32) | E5: YES | F5: 登记机构 | J5: 2023/01/12
B6: awe_role_url | C6: INPUTUSERID | D6: varchar(32) | E6: YES | F6: 登记人 | J6: 2023/01/12
B7: awe_role_url | C7: INPUTDATE | D7: datetime | E7: YES | F7: 登记日期 | J7: 2023/01/12
B8: awe_role_url | C8: UPDATEORGID | D8: varchar(32) | E8: YES | F8: 更新机构 | J8: 2023/01/12
B9: awe_role_url | C9: UPDATEUSERID | D9: varchar(32) | E9: YES | F9: 更新人 | J9: 2023/01/12
B10: awe_role_url | C10: UPDATEDATE | D10: datetime | E10: YES | F10: 更新日期 | J10: 2023/01/12

Sheet awe_shortcut
A1: =HYPERLINK("#表结构清单!A1","返回") | B1: 系统默认快捷菜单表
B2: 表名 | C2: 列名 | D2: 字段类型 | E2: 是否为空 | F2: 字段注释 | G2: 码值 | H2: 备注 | I2: 修订人 | J2: 修订日期
B3: awe_shortcut | C3: SHORTCUTID | D3: varchar(32) | E3: NO | F3: 快捷编号 | J3: 2023/01/12
B4: awe_shortcut | C4: SHORTCUTNAME | D4: varchar(200) | E4: NO | F4: 快捷名称 | J4: 2023/01/12
B5: awe_shortcut | C5: SORTNO | D5: varchar(32) | E5: YES | F5: 排序号 | J5: 2023/01/12
B6: awe_shortcut | C6: ISINUSE | D6: varchar(6) | E6: NO | F6: 是否使用 | J6: 2023/01/12
B7: awe_shortcut | C7: ISSYSDEFAULT | D7: varchar(6) | E7: YES | F7: 是否系统默认 | J7: 2023/01/12
B8: awe_shortcut | C8: BELONGAPPID | D8: varchar(200) | E8: NO | F8: 所属子系统编号 | J8: 2023/01/12
B9: awe_shortcut | C9: BELONGROLEID | D9: varchar(80) | E9: YES | F9: 所属角色编号 | J9: 2023/01/12
B10: awe_shortcut | C10: REMARK | D10: varchar(500) | E10: YES | F10: 备注 | J10: 2023/01/12
B11: awe_shortcut | C11: INPUTORGID | D11: varchar(80) | E11: YES | F11: 登记机构 | J11: 2023/01/12
B12: awe_shortcut | C12: INPUTUSERID | D12: varchar(80) | E12: YES | F12: 登记人 | J12: 2023/01/12
B13: awe_shortcut | C13: INPUTDATE | D13: datetime | E13: YES | F13: 登记日期 | J13: 2023/01/12
B14: awe_shortcut | C14: UPDATEORGID | D14: varchar(80) | E14: YES | F14: 更新机构 | J14: 2023/01/12
... B17: awe_shortcut | C17: DESCRIBE | D17: varchar(4000) | E17: YES | F17: 描述 | J17: 2023/01/12

Sheet awe_shortcutitem
A1: =HYPERLINK("#表结构清单!A1","返回") | B1: 系统功能库
B2: 表名 | C2: 列名 | D2: 字段类型 | E2: 是否为空 | F2: 字段注释 | G2: 码值 | H2: 备注 | I2: 修订人 | J2: 修订日期
B3: awe_shortcutitem | C3: ITEMNO | D3: varchar(32) | E3: NO | F3: 项目编号 | J3: 2023/01/12
B4: awe_shortcutitem | C4: ITEMNAME | D4: varchar(80) | E4: NO | F4: 项目名称 | J4: 2023/01/12
B5: awe_shortcutitem | C5: ITEMTIP | D5: varchar(80) | E5: YES | F5: 项目提示 | J5: 2023/01/12
B6: awe_shortcutitem | C6: JSACTION | D6: varchar(500) | E6: YES | F6: 脚本事件 | J6: 2023/01/12
B7: awe_shortcutitem | C7: ITEMSHORTCUTKEY | D7: varchar(200) | E7: YES | F7: 项目快捷键 | J7: 2023/01/12
B8: awe_shortcutitem | C8: CSS | D8: varchar(80) | E8: YES | F8: 项目样式 | J8: 2023/01/12
B9: awe_shortcutitem | C9: ISSYSDEFAULT | D9: varchar(6) | E9: YES | F9: 是否系统默认 | J9: 2023/01/12
B10: awe_shortcutitem | C10: ISINUSE | D10: varchar(6) | E10: NO | F10: 是否使用 | J10: 2023/01/12
B11: awe_shortcutitem | C11: BELONGSHORTCUTID | D11: varchar(80) | E11: NO | F11: 所属快捷编号 | J11: 2023/01/12
B12: awe_shortcutitem | C12: REMARK | D12: varchar(500) | E12: YES | F12: 备注 | J12: 2023/01/12
B13: awe_shortcutitem | C13: INPUTORGID | D13: varchar(32) | E13: YES | F13: 登记机构 | J13: 2023/01/12
B14: awe_shortcutitem | C14: INPUTUSERID | D14: varchar(32) | E14: YES | F14: 登记人 | J14: 2023/01/12
... B18: awe_shortcutitem | C18: UPDATEDATE | D18: datetime | E18: YES | F18: 更新日期 | J18: 2023/01/12

Sheet awe_task_info
A1: =HYPERLINK("#表结构清单!A1","返回") | B1: 任务信息
B2: 表名 | C2: 列名 | D2: 字段类型 | E2: 是否为空 | F2: 字段注释 | G2: 码值 | H2: 备注 | I2: 修订人 | J2: 修订日期
B3: awe_task_info | C3: SERIALNO | D3: varchar(32) | E3: NO | F3: 任务编号 | J3: 2023/01/12
B4: awe_task_info | C4: TASKTITLE | D4: varchar(200) | E4: YES | F4: 任务名 | J4: 2023/01/12
B5: awe_task_info | C5: TASKDESC | D5: varchar(500) | E5: YES | F5: 任务描述 | J5: 2023/01/12
B6: awe_task_info | C6: STARTUSERID | D6: varchar(32) | E6: YES | F6: 发起人 | J6: 2023/01/12
B7: awe_task_info | C7: DOUSERID | D7: varchar(32) | E7: YES | F7: 执行人 | J7: 2023/01/12
B8: awe_task_info | C8: STARTTIME | D8: varchar(32) | E8: YES | F8: 发起时间 | J8: 2023/01/12
B9: awe_task_info | C9: PREENDTIME | D9: varchar(32) | E9: YES | F9: 预计完成时间 | J9: 2023/01/12
B10: awe_task_info | C10: TRUEENDTIME | D10: varchar(32) | E10: YES | F10: 实际完成时间 | J10: 2023/01/12
B11: awe_task_info | C11: FINISHFLAG | D11: char(1) | E11: YES | F11: 完成状态 | J11: 2023/01/12
B12: awe_task_info | C12: ACTIONTYPE | D12: varchar(200) | E12: YES | F12: 操作分类 | J12: 2023/01/12
B13: awe_task_info | C13: ACTIONPARAM | D13: varchar(500) | E13: YES | F13: 操作参数 | J13: 2023/01/12
B14: awe_task_info | C14: CATALOGID | D14: varchar(32) | E14: YES | F14: 任务分类编号 | J14: 2023/01/12
... B23: awe_task_info | C23: QUERYINFO | D23: varchar(4000) | E23: YES | F23: 文件描述 | J23: 2023/01/12

Sheet awe_task_process
A1: =HYPERLINK("#表结构清单!A1","返回") | B1: 任务进度信息
B2: 表名 | C2: 列名 | D2: 字段类型 | E2: 是否为空 | F2: 字段注释 | G2: 码值 | H2: 备注 | I2: 修订人 | J2: 修订日期
B3: awe_task_process | C3: TASKID | D3: varchar(32) | E3: NO | F3: 任务编号 | J3: 2023/01/12
B4: awe_task_process | C4: USERID | D4: varchar(32) | E4: YES | F4: 用户名称 | J4: 2023/01/12
B5: awe_task_process | C5: TOTALCOUNT | D5: varchar(32) | E5: YES | F5: 总数量 | J5: 2023/01/12
B6: awe_task_process | C6: EXPORTEDCOUNT | D6: varchar(32) | E6: YES | F6: 任务数量 | J6: 2023/01/12
B7: awe_task_process | C7: THREADID | D7: varchar(32) | E7: YES | F7: 线程号 | J7: 2023/01/12
B8: awe_task_process | C8: UPDATETIME | D8: varchar(32) | E8: YES | F8: 更新时间 | J8: 2023/01/12
B9: awe_task_process | C9: CANRUN | D9: char(1) | E9: YES | F9: 运行状态 | J9: 2023/01/12

Sheet awe_wizard_catalog
A1: =HYPERLINK("#表结构清单!A1","返回") | B1: 向导目录
B2: 表名 | C2: 列名 | D2: 字段类型 | E2: 是否为空 | F2: 字段注释 | G2: 码值 | H2: 备注 | I2: 修订人 | J2: 修订日期
B3: awe_wizard_catalog | C3: WIZARDID | D3: varchar(32) | E3: NO | F3: 向导编号 | J3: 2023/01/12
B4: awe_wizard_catalog | C4: WIZARDNAME | D4: varchar(80) | E4: YES | F4: 向导名称 | J4: 2023/01/12
B5: awe_wizard_catalog | C5: REMARK | D5: varchar(500) | E5: YES | F5: 备注 | J5: 2023/01/12
B6: awe_wizard_catalog | C6: INPUTUSER | D6: varchar(32) | E6: YES | F6: 录入用户 | J6: 2023/01/12
B7: awe_wizard_catalog | C7: INPUTORG | D7: varchar(32) | E7: YES | F7: 录入机构 | J7: 2023/01/12
B8: awe_wizard_catalog | C8: INPUTDATE | D8: datetime | E8: YES | F8: 录入日期 | J8: 2023/01/12
B9: awe_wizard_catalog | C9: UPDATEUSER | D9: varchar(32) | E9: YES | F9: 更新用户 | J9: 2023/01/12
B10: awe_wizard_catalog | C10: UPDATEORG | D10: varchar(32) | E10: YES | F10: 更新机构 | J10: 2023/01/12
B11: awe_wizard_catalog | C11: UPDATEDATE | D11: datetime | E11: YES | F11: 更新日期 | J11: 2023/01/12

Sheet awe_wizard_library
A1: =HYPERLINK("#表结构清单!A1","返回") | B1: 向导定义
B2: 表名 | C2: 列名 | D2: 字段类型 | E2: 是否为空 | F2: 字段注释 | G2: 码值 | H2: 备注 | I2: 修订人 | J2: 修订日期
B3: awe_wizard_library | C3: WIZARDID | D3: varchar(32) | E3: NO | F3: 向导编号 | J3: 2023/01/12
B4: awe_wizard_library | C4: ITEMNO | D4: varchar(80) | E4: NO | F4: 项目编号 | J4: 2023/01/12
B5: awe_wizard_library | C5: ITEMNAME | D5: varchar(80) | E5: YES | F5: 项目名称 | J5: 2023/01/12
B6: awe_wizard_library | C6: SORTNO | D6: varchar(500) | E6: YES | F6: 排序号 | J6: 2023/01/12
B7: awe_wizard_library | C7: URL | D7: varchar(500) | E7: YES | F7: 访问路径 | J7: 2023/01/12
B8: awe_wizard_library | C8: PARAM | D8: varchar(500) | E8: YES | F8: 参数 | J8: 2023/01/12
B9: awe_wizard_library | C9: ISINUSE | D9: char(1) | E9: YES | F9: 是否可用 | J9: 2023/01/12
B10: awe_wizard_library | C10: REMARK | D10: varchar(500) | E10: YES | F10: 备注 | J10: 2023/01/12
B11: awe_wizard_library | C11: INPUTORG | D11: varchar(32) | E11: YES | F11: 登记机构 | J11: 2023/01/12
B12: awe_wizard_library | C12: INPUTUSER | D12: varchar(32) | E12: YES | F12: 登记人 | J12: 2023/01/12
B13: awe_wizard_library | C13: INPUTDATE | D13: datetime | E13: YES | F13: 登记日期 | J13: 2023/01/12
B14: awe_wizard_library | C14: UPDATEORG | D14: varchar(32) | E14: YES | F14: 更新机构 | J14: 2023/01/12
... B16: awe_wizard_library | C16: UPDATEDATE | D16: datetime | E16: YES | F16: 更新日期 | J16: 2023/01/12

Sheet awe_wizard_runner
A1: =HYPERLINK("#表结构清单!A1","返回") | B1: 向导运行记录表
B2: 表名 | C2: 列名 | D2: 字段类型 | E2: 是否为空 | F2: 字段注释 | G2: 码值 | H2: 备注 | I2: 修订人 | J2: 修订日期
B3: awe_wizard_runner | C3: WIZARDID | D3: varchar(32) | E3: NO | F3: 向导编号 | J3: 2023/01/12
B4: awe_wizard_runner | C4: OBJECTNO | D4: varchar(32) | E4: NO | F4: 向导运行对象 | J4: 2023/01/12
B5: awe_wizard_runner | C5: INPUTORGID | D5: varchar(32) | E5: YES | F5: 登记机构 | J5: 2023/01/12
B6: awe_wizard_runner | C6: INPUTUSERID | D6: varchar(32) | E6: YES | F6: 登记人 | J6: 2023/01/12
B7: awe_wizard_runner | C7: INPUTDATE | D7: varchar(18) | E7: YES | F7: 登记日期 | J7: 2023/01/12
B8: awe_wizard_runner | C8: UPDATEORGID | D8: varchar(32) | E8: YES | F8: 更新机构 | J8: 2023/01/12
B9: awe_wizard_runner | C9: UPDATEUSERID | D9: varchar(32) | E9: YES | F9: 更新人 | J9: 2023/01/12
B10: awe_wizard_runner | C10: UPDATEDATE | D10: varchar(18) | E10: YES | F10: 更新日期 | J10: 2023/01/12
B11: awe_wizard_runner | C11: WIZARDINFO | D11: varchar(4000) | E11: YES | F11: 向导运行记录 | J11: 2023/01/12

Sheet bat_task_error
A1: =HYPERLINK("#表结构清单!A1","返回") | B1: 批量错误日志信息表
B2: 表名 | C2: 列名 | D2: 字段类型 | E2: 是否为空 | F2: 字段注释 | G2: 码值 | H2: 备注 | I2: 修订人 | J2: 修订日期
B3: bat_task_error | C3: SERIALNO | D3: varchar(32) | E3: NO | F3: 流水号 | J3: 2023/01/12
B4: bat_task_error | C4: TASKNAME | D4: varchar(80) | E4: YES | F4: 任务名称 | J4: 2023/01/12
B5: bat_task_error | C5: OBJECTTYPE | D5: varchar(80) | E5: YES | F5: 对象类型 | J5: 2023/01/12
B6: bat_task_error | C6: OBJECTNO | D6: varchar(32) | E6: YES | F6: 对象编号 | J6: 2023/01/12
B7: bat_task_error | C7: ERRORDESC | D7: varchar(500) | E7: YES | F7: 错误描述 | J7: 2023/01/12
B8: bat_task_error | C8: INPUTTIME | D8: datetime | E8: YES | F8: 记录时间 | J8: 2023/01/12
B9: bat_task_error | C9: ATTRIBUTE1 | D9: varchar(80) | E9: YES | F9: 参数1 | J9: 2023/01/12
B10: bat_task_error | C10: ATTRIBUTE2 | D10: varchar(80) | E10: YES | F10: 参数2 | J10: 2023/01/12
B11: bat_task_error | C11: ATTRIBUTE3 | D11: varchar(80) | E11: YES | F11: 参数3 | J11: 2023/01/12
B12: bat_task_error | C12: ATTRIBUTE4 | D12: varchar(80) | E12: YES | F12: 参数4 | J12: 2023/01/12
B13: bat_task_error | C13: ATTRIBUTE5 | D13: varchar(80) | E13: YES | F13: 参数5 | J13: 2023/01/12
B14: bat_task_error | C14: ATTRIBUTE6 | D14: decimal(24,6) | E14: YES | F14: 参数6 | J14: 2023/01/12
... B24: bat_task_error | C24: UPDATEDATE | D24: datetime | E24: YES | F24: 更新日期 | J24: 2023/01/12

Sheet bat_task_log
A1: =HYPERLINK("#表结构清单!A1","返回") | B1: 批量记录表
B2: 表名 | C2: 列名 | D2: 字段类型 | E2: 是否为空 | F2: 字段注释 | G2: 码值 | H2: 备注 | I2: 修订人 | J2: 修订日期
B3: bat_task_log | C3: BATCHDATE | D3: varchar(18) | E3: NO | F3: 批量日期 | J3: 2023/01/12
B4: bat_task_log | C4: BUSINESSDATE | D4: varchar(18) | E4: YES | F4: 业务日期 | J4: 2023/01/12
B5: bat_task_log | C5: TASKNAME | D5: varchar(80) | E5: NO | F5: 一级任务名称 | J5: 2023/01/12
B6: bat_task_log | C6: TASKDESCRIBE | D6: varchar(200) | E6: YES | F6: 二级任务描述 | J6: 2023/01/12
B7: bat_task_log | C7: TARGETNAME | D7: varchar(80) | E7: NO | F7: 二级任务名称 | J7: 2023/01/12
B8: bat_task_log | C8: TARGETDESCRIBE | D8: varchar(200) | E8: YES | F8: 一级任务描述 | J8: 2023/01/12
B9: bat_task_log | C9: BEGINTIME | D9: varchar(32) | E9: YES | F9: 记录时间 | J9: 2023/01/12
B10: bat_task_log | C10: ENDTIME | D10: varchar(32) | E10: YES | F10: 结束时间 | J10: 2023/01/12
B11: bat_task_log | C11: STATUS | D11: varchar(18) | E11: YES | F11: 状态;Code:BatchTaskStatus） | J11: 2023/01/12
B12: bat_task_log | C12: INPUTORGID | D12: varchar(32) | E12: YES | F12: 登记机构 | J12: 2023/01/12
B13: bat_task_log | C13: INPUTUSERID | D13: varchar(32) | E13: YES | F13: 登记人 | J13: 2023/01/12
B14: bat_task_log | C14: INPUTDATE | D14: datetime | E14: YES | F14: 登记日期 | J14: 2023/01/12
... B17: bat_task_log | C17: UPDATEDATE | D17: datetime | E17: YES | F17: 更新日期 | J17: 2023/01/12

Sheet bat_upload
A1: =HYPERLINK("#表结构清单!A1","返回") | B1: 批量上传
B2: 表名 | C2: 列名 | D2: 字段类型 | E2: 是否为空 | F2: 字段注释 | G2: 码值 | H2: 备注 | I2: 修订人 | J2: 修订日期
B3: bat_upload | C3: SERIALNO | D3: varchar(32) | E3: NO | F3: 批次编号 | J3: 2023/01/12
B4: bat_upload | C4: TRANSDATE | D4: varchar(18) | E4: YES | F4: 交易日期 | J4: 2023/01/12
B5: bat_upload | C5: RCNT | D5: int | E5: YES | F5: 总记录 | J5: 2023/01/12
B6: bat_upload | C6: RAMT | D6: decimal(24,6) | E6: YES | F6: 总金额 | J6: 2023/01/12
B7: bat_upload | C7: NRCNT | D7: int | E7: YES | F7: 正常记录 | J7: 2023/01/12
B8: bat_upload | C8: NRAMT | D8: decimal(24,6) | E8: YES | F8: 正常金额;用于支付的金额） | J8: 2023/01/12
B9: bat_upload | C9: ABNRCNT1 | D9: int | E9: YES | F9: 异常记录;信息不匹配 | J9: 2023/01/12
B10: bat_upload | C10: ABNRAMT1 | D10: decimal(24,6) | E10: YES | F10: 异常金额;信息不匹配 | J10: 2023/01/12
B11: bat_upload | C11: ABNRCNT2 | D11: int | E11: YES | F11: 异常记录;运营商缺失 | J11: 2023/01/12
B12: bat_upload | C12: ABNRAMT2 | D12: decimal(24,6) | E12: YES | F12: 异常金额;运营商缺失 | J12: 2023/01/12
B13: bat_upload | C13: ABNRCNT3 | D13: int | E13: YES | F13: 异常记录;主系统缺失 | J13: 2023/01/12
B14: bat_upload | C14: ABNRAMT3 | D14: decimal(24,6) | E14: YES | F14: 异常金额;主系统缺失 | J14: 2023/01/12
... B16: bat_upload | C16: ABNRAMT4 | D16: decimal(24,6) | E16: YES | F16: 异常金额;其他 | J16: 2023/01/12
B17: bat_upload | C17: STATUS | D17: varchar(18) | E17: YES | F17: 当前状态 | G17: =HYPERLINK("#码值映射清单!B7618","BatUploadStatus") | J17: 2023/01/12
B18: bat_upload | C18: INPUTUSERID | D18: varchar(32) | E18: YES | F18: 登记人人 | J18: 2023/01/12
B19: bat_upload | C19: INPUTORGID | D19: varchar(32) | E19: YES | F19: 登记机构 | J19: 2023/01/12
B20: bat_upload | C20: UPDATEUSERID | D20: varchar(32) | E20: YES | F20: 更新人 | J20: 2023/01/12
B21: bat_upload | C21: UPDATEORGID | D21: varchar(32) | E21: YES | F21: 更新机构 | J21: 2023/01/12
B22: bat_upload | C22: BATCHTYPE | D22: varchar(18) | E22: YES | F22: 导入类型 | G22: =HYPERLINK("#码值映射清单!B462","BatchType") | J22: 2023/01/12
B23: bat_upload | C23: ERRORCODE | D23: varchar(500) | E23: YES | F23: 错误代码 | J23: 2023/01/12
B24: bat_upload | C24: FILEPATH | D24: varchar(200) | E24: YES | F24: 文件路径 | J24: 2023/01/12
B25: bat_upload | C25: FILENAME | D25: varchar(200) | E25: YES | F25: 文件名 | J25: 2023/01/12
B26: bat_upload | C26: REMARK | D26: varchar(500) | E26: YES | F26: 备注 | J26: 2023/01/12
B27: bat_upload | C27: INPUTDATE | D27: datetime | E27: YES | F27: 登记日期 | J27: 2023/01/12
B28: bat_upload | C28: UPDATEDATE | D28: datetime | E28: YES | F28: 更新日期 | J28: 2023/01/12

Sheet bill_info
B1: 票据信息表
B2: 表名 | C2: 列名 | D2: 字段类型 | E2: 是否为空 | F2: 字段注释 | G2: 码值 | H2: 备注 | I2: 修订人 | J2: 修订日期
B3: bill_info | C3: SERIALNO | D3: varchar(32) | E3: NO | F3: 流水号 | J3: 2023/01/12
B4: bill_info | C4: BILLNO | D4: varchar(32) | E4: YES | F4: 票据编号 | J4: 2023/01/12
B5: bill_info | C5: OBJECTNO | D5: varchar(32) | E5: YES | F5: 对象编号 | J5: 2023/01/12
B6: bill_info | C6: OBJECTTYPE | D6: varchar(32) | E6: YES | F6: 对象类型 | J6: 2023/01/12
B7: bill_info | C7: BILLFORM | D7: varchar(18) | E7: YES | F7: 票据形式;电票/纸票) | G7: =HYPERLINK("#码值映射清单!B6600","BillForm") | J7: 2023/01/12
B8: bill_info | C8: BILLRESOURCE | D8: varchar(18) | E8: YES | F8: 票据来源;0 同城;1 异地;) | J8: 2023/01/12
B9: bill_info | C9: CURRENCY | D9: varchar(18) | E9: YES | F9: 币种 | G9: =HYPERLINK("#码值映射清单!B2469","Currency") | J9: 2023/01/12
B10: bill_info | C10: PARVALUE | D10: decimal(24,6) | E10: YES | F10: 票面金额 | J10: 2023/01/12
B11: bill_info | C11: INTERESTSUM | D11: decimal(24,6) | E11: YES | F11: 利息金额 | J11: 2023/01/12
B12: bill_info | C12: ISREALDEALCONDITION | D12: varchar(6) | E12: YES | F12: 是否具有真实的交易背景 | J12: 2023/01/12
B13: bill_info | C13: ISHONORBYSELF | D13: varchar(6) | E13: YES | F13: 是否我行承兑 | J13: 2023/01/12
B14: bill_info | C14: HONORCODE | D14: varchar(32) | E14: YES | F14: 承兑人编号 | J14: 2023/01/12
B15: bill_info | C15: HONORNAME | D15: varchar(80) | E15: YES | F15: 承兑人名称 | J15: 2023/01/12
B16: bill_info | C16: HONORBANKNO | D16: varchar(32) | E16: YES | F16: 承兑行编号/承兑人开户行行号 | J16: 2023/01/12
B17: bill_info | C17: HONORBANKNAME | D17: varchar(80) | E17: YES | F17: 承兑行名称/承兑人开户行名称 | J17: 2023/01/12
B18: bill_info | C18: SPECIFICHONORBANK | D18: varchar(80) | E18: YES | F18: 承兑行具体分支行 | J18: 2023/01/12
B19: bill_info | C19: HONORBANKISACCEPTED | D19: varchar(6) | E19: YES | F19: 承兑行是否我行认可 | J19: 2023/01/12
B20: bill_info | C20: HONORBANKISAUTHORIZED | D20: varchar(6) | E20: YES | F20: 承兑行是否在授权范围内 | J20: 2023/01/12
B21: bill_info | C21: BILLPUBLISHDATE | D21: datetime | E21: YES | F21: 票据签发日期 | J21: 2023/01/12
... B26: bill_info | C26: DISCOUNTRATE | D26: decimal(18,8) | E26: YES | F26: 转贴现利率 | J26: 2023/01/12
B27: bill_info | C27: INTERESTPAYTYPE | D27: varchar(18) | E27: YES | F27: 贴现付息方式 | G27: =HYPERLINK("#码值映射清单!B5669","InterestPayType") | J27: 2023/01/12
B28: bill_info | C28: PAYINTERESTACCOUNT | D28: varchar(32) | E28: YES | F28: 买方付息帐号 | J28: 2023/01/12
B29: bill_info | C29: BILLISSUEDATE | D29: datetime | E29: YES | F29: 出票日期 | J29: 2023/01/12
B30: bill_info | C30: BILLISSUERNAME | D30: varchar(80) | E30: YES | F30: 出票人名称 | J30: 2023/01/12
B31: bill_info | C31: ENDORSETIMES | D31: int | E31: YES | F31: 背书次数 | J31: 2023/01/12
B32: bill_info | C32: ACTUALPAYSUM | D32: decimal(24,6) | E32: YES | F32: 实付金额 | J32: 2023/01/12
B33: bill_info | C33: REDISCOUNTTYPE | D33: varchar(18) | E33: YES | F33: 再贴现方式 | J33: 2023/01/12
B34: bill_info | C34: PAYMENTBANK | D34: varchar(32) | E34: YES | F34: 付款行 | J34: 2023/01/12
B35: bill_info | C35: PAYMENTBANKNAME | D35: varchar(80) | E35: YES | F35: 付款行全称 | J35: 2023/01/12
B36: bill_info | C36: TRANSACTIONBANK | D36: varchar(80) | E36: YES | F36: 交易行 | J36: 2023/01/12
B37: bill_info | C37: TRANSACTIONBANKNO | D37: varchar(32) | E37: YES | F37: 交易行号 | J37: 2023/01/12
B38: bill_info | C38: BUSINESSCHARACTER | D38: varchar(18) | E38: YES | F38: 业务性质;正回购/逆回购/到期返售/到期回购/买断/卖断/行内转贴现) | J38: 2023/01/12
B39: bill_info | C39: TRANSACTIONDATE | D39: datetime | E39: YES | F39: 交易日期 | J39: 2023/01/12
... B52: bill_info | C52: CORPORGID | D52: varchar(32) | E52: YES | F52: 法人机构编号 | J52: 2023/01/12

Sheet board_list
A1: =HYPERLINK("#表结构清单!A1","返回") | B1: 通告栏
B2: 表名 | C2: 列名 | D2: 字段类型 | E2: 是否为空 | F2: 字段注释 | G2: 码值 | H2: 备注 | I2: 修订人 | J2: 修订日期
B3: board_list | C3: BOARDNO | D3: varchar(32) | E3: NO | F3: 公告编号 | J3: 2023/01/12
B4: board_list | C4: BOARDNAME | D4: varchar(80) | E4: YES | F4: 公告名称 | J4: 2023/01/12
B5: board_list | C5: BOARDTITLE | D5: varchar(80) | E5: YES | F5: 公告标题 | J5: 2023/01/12
B6: board_list | C6: BOARDDESC | D6: varchar(500) | E6: YES | F6: 公告描述 | J6: 2023/01/12
B7: board_list | C7: ISPUBLISH | D7: varchar(32) | E7: YES | F7: 是否发布 | G7: =HYPERLINK("#码值映射清单!B5150","YesNo") | J7: 2023/01/12
B8: board_list | C8: ISNEW | D8: varchar(32) | E8: YES | F8: 是否新 | G8: =HYPERLINK("#码值映射清单!B5150","YesNo") | J8: 2023/01/12
B9: board_list | C9: ISEJECT | D9: varchar(32) | E9: YES | F9: 是否弹出 | G9: =HYPERLINK("#码值映射清单!B5150","YesNo") | J9: 2023/01/12
B10: board_list | C10: FILENAME | D10: varchar(500) | E10: YES | F10: 公告文件名 | J10: 2023/01/12
B11: board_list | C11: CONTENTTYPE | D11: varchar(80) | E11: YES | F11: 内容类型 | J11: 2023/01/12
B12: board_list | C12: CONTENTLENGTH | D12: varchar(32) | E12: YES | F12: 内容长度 | J12: 2023/01/12
B13: board_list | C13: UPLOADTIME | D13: varchar(32) | E13: YES | F13: 上传时间 | J13: 2023/01/12
B14: board_list | C14: SHOWTOROLES | D14: varchar(80) | E14: YES | F14: 可查看角色列表 | J14: 2023/01/12
B15: board_list | C15: SHOWTOORG | D15: varchar(32) | E15: YES | F15: 可查看机构;含下属) | J15: 2023/01/12
B16: board_list | C16: SHOWTOORGS | D16: varchar(32) | E16: YES | F16: 可查看机构清单;不含下属) | J16: 2023/01/12
B17: board_list | C17: FILEPATH | D17: varchar(200) | E17: YES | F17: 文件路径 | J17: 2023/01/12
B18: board_list | C18: FULLPATH | D18: varchar(500) | E18: YES | F18: 全路径 | J18: 2023/01/12
B19: board_list | C19: FILESAVEMODE | D19: varchar(32) | E19: YES | F19: 文件保存模型 | J19: 2023/01/12
B20: board_list | C20: ENDTIME | D20: varchar(32) | E20: YES | F20: 结束时间 | J20: 2023/01/12
B21: board_list | C21: DOCNO | D21: varchar(32) | E21: YES | F21: 附件编号 | J21: 2023/01/12
... B29: board_list | C29: DOCCONTENT | D29: text | E29: YES | F29: 文档内容 | J29: 2023/01/12

Sheet board_user
A1: =HYPERLINK("#表结构清单!A1","返回") | B1: 用户通告
B2: 表名 | C2: 列名 | D2: 字段类型 | E2: 是否为空 | F2: 字段注释 | G2: 码值 | H2: 备注 | I2: 修订人 | J2: 修订日期
B3: board_user | C3: SERIALNO | D3: varchar(32) | E3: NO | F3: 流水号; | J3: 2023/01/12
B4: board_user | C4: INPUTUSERID | D4: varchar(32) | E4: YES | F4: 登记人; | J4: 2023/01/12
B5: board_user | C5: ISALREADYREAD | D5: varchar(18) | E5: YES | F5: 是否查看; | J5: 2023/01/12
B6: board_user | C6: INPUTDATE | D6: datetime | E6: YES | F6: 登记时间; | J6: 2023/01/12

Sheet business_contract
A1: =HYPERLINK("#表结构清单!A1","返回") | B1: 合同信息表
B2: 表名 | C2: 列名 | D2: 字段类型 | E2: 是否为空 | F2: 字段注释 | G2: 码值 | H2: 备注 | I2: 修订人 | J2: 修订日期
B3: business_contract | C3: SERIALNO | D3: varchar(32) | E3: NO | F3: 合同编号 | J3: 2023/01/12
B4: business_contract | C4: CUSTOMERID | D4: varchar(32) | E4: YES | F4: 客户编号 | G4: =HYPERLINK("#码值映射清单!B2469","Currency") | J4: 2023/01/12
B5: business_contract | C5: CUSTOMERNAME | D5: varchar(80) | E5: YES | F5: 客户名称 | G5: =HYPERLINK("#码值映射清单!B2469","Currency") | J5: 2023/01/12
B6: business_contract | C6: CURRENCY | D6: varchar(18) | E6: YES | F6: 额度/业务币种 | G6: =HYPERLINK("#码值映射清单!B2469","Currency") | J6: 2023/01/12
B7: business_contract | C7: BUSINESSSUM | D7: decimal(24,6) | E7: YES | F7: 合同金额 | J7: 2023/01/12
B8: business_contract | C8: PRODUCTID | D8: varchar(32) | E8: YES | F8: 产品编号 | J8: 2023/01/12
B9: business_contract | C9: STARTDATE | D9: datetime | E9: YES | F9: 合同起始日 | J9: 2023/01/12
B10: business_contract | C10: MATURITY | D10: datetime | E10: YES | F10: 合同到期日 | J10: 2023/01/12
B11: business_contract | C11: INPUTUSERID | D11: varchar(32) | E11: YES | F11: 登记人 | J11: 2023/01/12
B12: business_contract | C12: INPUTORGID | D12: varchar(32) | E12: YES | F12: 登记机构 | J12: 2023/01/12
B13: business_contract | C13: INPUTDATE | D13: datetime | E13: YES | F13: 登记日期 | J13: 2023/01/12
B14: business_contract | C14: UPDATEUSERID | D14: varchar(32) | E14: YES | F14: 更新人 | J14: 2023/01/12
B15: business_contract | C15: UPDATEORGID | D15: varchar(32) | E15: YES | F15: 更新机构 | J15: 2023/01/12
B16: business_contract | C16: UPDATEDATE | D16: datetime | E16: YES | F16: 更新日期 | J16: 2023/01/12
B17: business_contract | C17: CORPORGID | D17: varchar(32) | E17: YES | F17: 法人机构编号 | J17: 2023/01/12
B18: business_contract | C18: PRODUCTNAME | D18: varchar(80) | E18: YES | F18: 产品名称 | J18: 2023/01/12
... B20: business_contract | C20: BUSINESSFLAG | D20: varchar(6) | E20: YES | F20: 额度/业务标志 | J20: 2023/01/12
B21: business_contract | C21: STATUS | D21: varchar(18) | E21: YES | F21: 合同状态 | G21: =HYPERLINK("#码值映射清单!B8642","ContractStatus") | J21: 2023/01/12
B22: business_contract | C22: CONTRACTTYPE | D22: varchar(18) | E22: YES | F22: 合同类型 | J22: 2023/01/12
B23: business_contract | C23: nationalindustrytype | D23: varchar(32) | E23: YES | F23: 国标行业投向 | G23: =HYPERLINK("#码值映射清单!B5150","YesNo") | J23: 2023/01/12
B24: business_contract | C24: operateOrgId | D24: varchar(32) | E24: YES | F24: 经办机构 | J24: 2023/01/12
B25: business_contract | C25: balance | D25: decimal(24,6) | E25: YES | F25: 合同余额 | J25: 2023/01/12

Sheet class_catalog
A1: =HYPERLINK("#表结构清单!A1","返回") | B1: 方法库目录
B2: 表名 | C2: 列名 | D2: 字段类型 | E2: 是否为空 | F2: 字段注释 | G2: 码值 | H2: 备注 | I2: 修订人 | J2: 修订日期
B3: class_catalog | C3: CLASSNAME | D3: varchar(200) | E3: NO | F3: 类名称 | J3: 2023/01/12
B4: class_catalog | C4: CLASSTYPE | D4: varchar(32) | E4: YES | F4: 类分类 | J4: 2023/01/12
B5: class_catalog | C5: CLASSDESCRIBE | D5: varchar(500) | E5: YES | F5: 类描述 | J5: 2023/01/12
B6: class_catalog | C6: PARENTCLASS | D6: varchar(200) | E6: YES | F6: 父类名称 | J6: 2023/01/12
B7: class_catalog | C7: REMARK | D7: varchar(500) | E7: YES | F7: 备注 | J7: 2023/01/12
B8: class_catalog | C8: INPUTORG | D8: varchar(80) | E8: YES | F8: 登记机构 | J8: 2023/01/12
B9: class_catalog | C9: INPUTUSER | D9: varchar(80) | E9: YES | F9: 登记人 | J9: 2023/01/12
B10: class_catalog | C10: INPUTDATE | D10: datetime | E10: YES | F10: 登记日期 | J10: 2023/01/12
B11: class_catalog | C11: UPDATEORG | D11: varchar(80) | E11: YES | F11: 更新机构 | J11: 2023/01/12
B12: class_catalog | C12: UPDATEUSER | D12: varchar(80) | E12: YES | F12: 更新人 | J12: 2023/01/12
B13: class_catalog | C13: UPDATEDATE | D13: datetime | E13: YES | F13: 更新日期 | J13: 2023/01/12
B14: class_catalog | C14: INPUTTIME | D14: datetime | E14: YES | F14: 登记日期 | J14: 2023/01/12
B15: class_catalog | C15: UPDATETIME | D15: datetime | E15: YES | F15: 更新日期 | J15: 2023/01/12

Sheet class_method
A1: =HYPERLINK("#表结构清单!A1","返回") | B1: 方法库明细
B2: 表名 | C2: 列名 | D2: 字段类型 | E2: 是否为空 | F2: 字段注释 | G2: 码值 | H2: 备注 | I2: 修订人 | J2: 修订日期
B3: class_method | C3: CLASSNAME | D3: varchar(80) | E3: NO | F3: 类名称 | J3: 2023/01/12
B4: class_method | C4: METHODNAME | D4: varchar(80) | E4: NO | F4: 方法名称 | J4: 2023/01/12
B5: class_method | C5: METHODTYPE | D5: varchar(18) | E5: YES | F5: 方法类型 | G5: =HYPERLINK("#码值映射清单!B5641","MethodType") | J5: 2023/01/12
B6: class_method | C6: METHODDESCRIBE | D6: varchar(500) | E6: YES | F6: 方法描述 | J6: 2023/01/12
B7: class_method | C7: RETURNTYPE | D7: varchar(18) | E7: YES | F7: 返回值类型 | J7: 2023/01/12
B8: class_method | C8: METHODARGS | D8: varchar(500) | E8: YES | F8: 方法参数 | J8: 2023/01/12
B9: class_method | C9: METHODCODE | D9: varchar(4000) | E9: YES | F9: 方法实现代码 | J9: 2023/01/12
B10: class_method | C10: REMARK | D10: varchar(500) | E10: YES | F10: 备注 | J10: 2023/01/12
B11: class_method | C11: INPUTUSER | D11: varchar(80) | E11: YES | F11: 登记人 | J11: 2023/01/12
B12: class_method | C12: INPUTORG | D12: varchar(80) | E12: YES | F12: 登记机构 | J12: 2023/01/12
B13: class_method | C13: INPUTDATE | D13: datetime | E13: YES | F13: 登记日期 | J13: 2023/01/12
B14: class_method | C14: UPDATEUSER | D14: varchar(80) | E14: YES | F14: 更新人 | J14: 2023/01/12
B15: class_method | C15: UPDATEORG | D15: varchar(80) | E15: YES | F15: 更新机构 | J15: 2023/01/12
B16: class_method | C16: UPDATEDATE | D16: datetime | E16: YES | F16: 登记日期 | J16: 2023/01/12
B17: class_method | C17: INPUTTIME | D17: datetime | E17: YES | F17: 登记时间 | J17: 2023/01/12
B18: class_method | C18: UPDATETIME | D18: datetime | E18: YES | F18: 更新时间 | J18: 2023/01/12

Sheet clr_asset_finance
A1: =HYPERLINK("#表结构清单!A1","返回") | B1: 金融类质押品
B2: 表名 | C2: 列名 | D2: 字段类型 | E2: 是否为空 | F2: 字段注释 | G2: 码值 | H2: 备注 | I2: 修订人 | J2: 修订日期
B3: clr_asset_finance | C3: CLRID | D3: varchar(32) | E3: NO | F3: 押品编号 | J3: 2023/01/12
B4: clr_asset_finance | C4: DEPOSITNO | D4: varchar(32) | E4: YES | F4: 存单号码 | J4: 2023/01/12
B5: clr_asset_finance | C5: SAVINGMODE | D5: varchar(6) | E5: YES | F5: 储蓄方式 | G5: =HYPERLINK("#码值映射清单!B758","SavingMode") | J5: 2023/01/12
B6: clr_asset_finance | C6: SAVEDATE | D6: datetime | E6: YES | F6: 存入日期 | J6: 2023/01/12
B7: clr_asset_finance | C7: DRAWMODE | D7: varchar(6) | E7: YES | F7: 存单支取方式 | J7: 2023/01/12
B8: clr_asset_finance | C8: BANKBOOKCARDNO | D8: varchar(32) | E8: YES | F8: 存折卡号 | J8: 2023/01/12
B9: clr_asset_finance | C9: OPENDATE | D9: datetime | E9: YES | F9: 开户日期 | J9: 2023/01/12
B10: clr_asset_finance | C10: BAILCOMESOURCE | D10: varchar(80) | E10: YES | F10: 保证金来源 | J10: 2023/01/12
B11: clr_asset_finance | C11: ACCOUNTTYPE | D11: varchar(18) | E11: YES | F11: 账户类型/上市类型 | G11: =HYPERLINK("#码值映射清单!B6265","StockMarketType") | J11: 2023/01/12
B12: clr_asset_finance | C12: ACCOUNTNO | D12: varchar(32) | E12: YES | F12: 账号/资金帐号/收款人账号/股票账户/基金持有人的资金账号/保险缴纳账号/持有人自己账户 | G12: =HYPERLINK("#码值映射清单!B5150","YesNo") | J12: 2023/01/12
B13: clr_asset_finance | C13: ACCOUNTNAME | D13: varchar(80) | E13: YES | F13: 户名 | J13: 2023/01/12
B14: clr_asset_finance | C14: OPENBANKNO | D14: varchar(80) | E14: YES | F14: 开户银行行号/存单所属行行号/保险费用缴纳开户行号 | J14: 2023/01/12
B15: clr_asset_finance | C15: OPENBANKNAME | D15: varchar(80) | E15: YES | F15: 开户行名称/债券发行人/收款人开户银行/存单所属行名称/保险费用缴纳开户行 | J15: 2023/01/12
B16: clr_asset_finance | C16: DATEOFVALUE | D16: datetime | E16: YES | F16: 起息日期/债券开户日/发行日/出票日期/保单生效日 | J16: 2023/01/12
B17: clr_asset_finance | C17: MATURITYDATE | D17: datetime | E17: YES | F17: 到期日期/债券到期日/到期日期/保单到期日期 | J17: 2023/01/12
B18: clr_asset_finance | C18: CASHDEVTYPE | D18: varchar(6) | E18: YES | F18: 票据类型 | G18: =HYPERLINK("#码值映射清单!B4072","InsuranceType") | J18: 2023/01/12
B19: clr_asset_finance | C19: DESPOSITTYPE | D19: varchar(6) | E19: YES | F19: 存单类型/债券市场类型/票据类型/基金投资类型/保险种类/保证金账户类型/我行理财产品类型 | G19: =HYPERLINK("#码值映射清单!B1934","DepositType") | J19: 2023/01/12
B20: clr_asset_finance | C20: BALANCE | D20: decimal(24,6) | E20: YES | F20: 余额/最近一个交易日市价;净值）/保险承保金额 | J20: 2023/01/12
B21: clr_asset_finance | C21: TRADECONTRACTNO | D21: varchar(50) | E21: YES | F21: 贵金属交易合约号/汇票交易合同号码/保险合同号/理财协议编号 | J21: 45740
B22: clr_asset_finance | C22: GOLDACCOUNTNUMBER | D22: varchar(32) | E22: YES | F22: 黄金交易账户编码/股东代码/贵金属交易账号 | J22: 2023/01/12
B23: clr_asset_finance | C23: TRADENO | D23: varchar(32) | E23: YES | F23: 交易号 | J23: 2023/01/12
B24: clr_asset_finance | C24: NOBLEMETALTYPE | D24: varchar(18) | E24: YES | F24: 贵金属品种 | G24: =HYPERLINK("#码值映射清单!B1421","MyNobleMetalType") | J24: 2023/01/12
B25: clr_asset_finance | C25: NOBLEMETALNORMS | D25: varchar(80) | E25: YES | F25: 贵金属规格 | J25: 2023/01/12
B26: clr_asset_finance | C26: NOBLEMETALQUANTITY | D26: int | E26: YES | F26: 贵金属数量/持有股票数量/持有基金份数 | J26: 2023/01/12
B27: clr_asset_finance | C27: PURCHASEDATE | D27: datetime | E27: YES | F27: 贵金属购入日期/债券购入日期/签发日期/最近一个交易日日期 | J27: 2023/01/12
B28: clr_asset_finance | C28: PURCHASEVALUE | D28: decimal(24,6) | E28: YES | F28: 贵金属购入价值/最近一年;净值）均价 | J28: 2023/01/12
B29: clr_asset_finance | C29: CURRPRICE | D29: decimal(24,6) | E29: YES | F29: 贵金属当前市场价格/保险价值/折合人民币 | J29: 2023/01/12
B30: clr_asset_finance | C30: CURRPRICEEVALDATE | D30: date | E30: YES | F30: 贵金属市场价格评估日期 | J30: 2023/01/12
B31: clr_asset_finance | C31: BILLNO | D31: varchar(32) | E31: YES | F31: 债券券号/票据号/股票代码/基金代码 | J31: 2023/01/12
B32: clr_asset_finance | C32: BILLNAME | D32: varchar(80) | E32: YES | F32: 债券名称/股票名称/基金名称/保险机构名称/理财产品名称 | G32: =HYPERLINK("#码值映射清单!B5791","InsuranceCompany") | J32: 2023/01/12
B33: clr_asset_finance | C33: OWNER | D33: varchar(80) | E33: YES | F33: 债券持有人/持票人/未上市股票的托管单位/被保险人/基金持有人 | J33: 2023/01/12
B34: clr_asset_finance | C34: INTERESTPAYTYPE | D34: varchar(18) | E34: YES | F34: 利息支付方式 | G34: =HYPERLINK("#码值映射清单!B2868","BondInterestType") | J34: 2023/01/12
B35: clr_asset_finance | C35: INCOMERATE | D35: decimal(18,8) | E35: YES | F35: 债券到期收益率 | J35: 2023/01/12
B36: clr_asset_finance | C36: INTERESTPERIOD | D36: varchar(18) | E36: YES | F36: 计息周期 | G36: =HYPERLINK("#码值映射清单!B7853","CalcCircle") | J36: 2023/01/12
B37: clr_asset_finance | C37: BILLVALUE | D37: decimal(24,6) | E37: YES | F37: 债券票面价值/票面金额/保险费用/存单金额 | J37: 2023/01/12
B38: clr_asset_finance | C38: BONDAGENCYPUBLISHER | D38: varchar(80) | E38: YES | F38: 债券代理发行机构/出票人/公司名称/基金发行公司名称/投保人/标的公司名称 | J38: 2023/01/12
B39: clr_asset_finance | C39: BONDCREDITLEVEL | D39: varchar(1000) | E39: YES | F39: 债券信用等级 | J39: 2023/01/12
B40: clr_asset_finance | C40: BILLPAYEE | D40: varchar(80) | E40: YES | F40: 收款人/受益人 | J40: 2023/01/12
B41: clr_asset_finance | C41: DRAWERACCOUNTNO | D41: varchar(32) | E41: YES | F41: 出票人账号 | J41: 2023/01/12
B42: clr_asset_finance | C42: ACCEPTORNAME | D42: varchar(80) | E42: YES | F42: 承兑人名称 | J42: 2023/01/12
B43: clr_asset_finance | C43: ACCEPTORBANKNAME | D43: varchar(80) | E43: YES | F43: 承兑行名称 | J43: 2023/01/12
B44: clr_asset_finance | C44: ACCEPTORBANKNO | D44: varchar(32) | E44: YES | F44: 承兑行行号 | J44: 2023/01/12
B45: clr_asset_finance | C45: DRAWEEBANKNO | D45: varchar(32) | E45: YES | F45: 付款行行号 | J45: 2023/01/12
B46: clr_asset_finance | C46: DRAWEEBANK | D46: varchar(80) | E46: YES | F46: 汇票付款行 | J46: 2023/01/12
B47: clr_asset_finance | C47: BILLUSAGE | D47: varchar(1000) | E47: YES | F47: 票据用途 | G47: =HYPERLINK("#码值映射清单!B8534","BillUsageType") | J47: 2023/01/12
B48: clr_asset_finance | C48: CIRCULATIONQUANTITY | D48: int | E48: YES | F48: 流通数量 | J48: 2023/01/12
B49: clr_asset_finance | C49: PERATIO | D49: decimal(18,8) | E49: YES | F49: 市盈率(P/E) | J49: 2023/01/12
B50: clr_asset_finance | C50: STOCKHOLDERTYPE | D50: varchar(18) | E50: YES | F50: 股权/股票持有类型/基金契约类型/缴费方式/理财来源 | G50: =HYPERLINK("#码值映射清单!B2895","StockHolderType") | J50: 2023/01/12
B51: clr_asset_finance | C51: NAVPS | D51: decimal(24,6) | E51: YES | F51: 每股净资产 | J51: 2023/01/12
B52: clr_asset_finance | C52: PAYMENTSTARTDATE | D52: datetime | E52: YES | F52: 缴费起始日期 | J52: 45740
B53: clr_asset_finance | C53: PAYMENTENDDATE | D53: datetime | E53: YES | F53: 缴费终止日期 | J53: 45740
B54: clr_asset_finance | C54: ABOUTBONUS | D54: varchar(1000) | E54: YES | F54: 分红情况 | J54: 2023/01/12
B55: clr_asset_finance | C55: INTERESTRATE | D55: decimal(18,8) | E55: YES | F55: 利率/债券利率 | J55: 2023/01/12
B56: clr_asset_finance | C56: CURRENCY | D56: varchar(18) | E56: YES | F56: 币种 | G56: =HYPERLINK("#码值映射清单!B2469","Currency") | J56: 2023/01/12
B57: clr_asset_finance | C57: TRADETYPE | D57: varchar(6) | E57: YES | F57: 交易类型 | J57: 2023/01/12
B58: clr_asset_finance | C58: HOLDPERIOD | D58: int | E58: YES | F58: 持有期 | J58: 2023/01/12
B59: clr_asset_finance | C59: MTMDAYS | D59: int | E59: YES | F59: 盯市天数 | J59: 2023/01/12
B60: clr_asset_finance | C60: BONDFLAG01 | D60: char(1) | E60: YES | F60: 是否为通过总行认定的政策性金融债 | G60: =HYPERLINK("#码值映射清单!B5150","YesNo") | J60: 2023/01/12
B61: clr_asset_finance | C61: BONDFLAG02 | D61: char(1) | E61: YES | F61: 是否经中国人民银行批准可在全国银行间债券市场上市 | G61: =HYPERLINK("#码值映射清单!B5150","YesNo") | J61: 2023/01/12
B62: clr_asset_finance | C62: BONDFLAG03 | D62: char(1) | E62: YES | F62: 是否是记名债券 | G62: =HYPERLINK("#码值映射清单!B5150","YesNo") | J62: 2023/01/12
B63: clr_asset_finance | C63: BONDFLAG04 | D63: char(1) | E63: YES | F63: 是否需要办理止付 | G63: =HYPERLINK("#码值映射清单!B5150","YesNo") | J63: 2023/01/12
B64: clr_asset_finance | C64: BONDFLAG05 | D64: char(1) | E64: YES | F64: 是否已提交其他相关股权凭证 | G64: =HYPERLINK("#码值映射清单!B5150","YesNo") | J64: 2023/01/12
B65: clr_asset_finance | C65: BONDFLAG06 | D65: char(1) | E65: YES | F65: 是否为集中公开交易的债券 | G65: =HYPERLINK("#码值映射清单!B5150","YesNo") | J65: 2023/01/12
B66: clr_asset_finance | C66: BONDFLAG07 | D66: char(1) | E66: YES | F66: 是否已提交债券凭证 | G66: =HYPERLINK("#码值映射清单!B5150","YesNo") | J66: 2023/01/12
B67: clr_asset_finance | C67: BONDFLAG08 | D67: char(1) | E67: YES | F67: 是否已提交相关债券评级证书 | G67: =HYPERLINK("#码值映射清单!B5150","YesNo") | J67: 2023/01/12
B68: clr_asset_finance | C68: BONDFLAG09 | D68: char(1) | E68: YES | F68: 是否已提交债券募集说明书 | G68: =HYPERLINK("#码值映射清单!B5150","YesNo") | J68: 2023/01/12
B69: clr_asset_finance | C69: NOBLEMETALFLAG1 | D69: char(1) | E69: YES | F69: 是否已提交贵金属购买合约 | G69: =HYPERLINK("#码值映射清单!B5150","YesNo") | J69: 2023/01/12
B70: clr_asset_finance | C70: NOBLEMETALFLAG2 | D70: char(1) | E70: YES | F70: 是否已提交黄金交易账户卡 | J70: 2023/01/12
B71: clr_asset_finance | C71: NOBLEMETALFLAG3 | D71: char(1) | E71: YES | F71: 是否已提交金交所托管合约 | J71: 2023/01/12
B72: clr_asset_finance | C72: NOBLEMETALFLAG4 | D72: char(1) | E72: YES | F72: 是否已提交贵金属交易账户凭证 | G72: =HYPERLINK("#码值映射清单!B5150","YesNo") | J72: 2023/01/12
B73: clr_asset_finance | C73: DEPCTFFLAG01 | D73: char(1) | E73: YES | F73: 是否为借款人公开向不特定的自然人、法人和其他组织募集的个人存单 | G73: =HYPERLINK("#码值映射清单!B5150","YesNo") | J73: 2023/01/12
B74: clr_asset_finance | C74: DEPCTFFLAG02 | D74: char(1) | E74: YES | F74: 是否已取得存款行出具的个人定期存单真实性确认书，并且存款行已落实登记止付手续 | G74: =HYPERLINK("#码值映射清单!B5150","YesNo") | J74: 2023/01/12
B75: clr_asset_finance | C75: DEPCTFFLAG03 | D75: char(1) | E75: YES | F75: 是否已提交存单所有人名下所有东方卡号 | G75: =HYPERLINK("#码值映射清单!B5150","YesNo") | J75: 2023/01/12
B76: clr_asset_finance | C76: DEPCTFFLAG04 | D76: char(1) | E76: YES | F76: 是否已提交“存单凭证” | G76: =HYPERLINK("#码值映射清单!B5150","YesNo") | J76: 2023/01/12
B77: clr_asset_finance | C77: DEPCTFFLAG05 | D77: char(1) | E77: YES | F77: 是否已提交“个人定期存单真实性确认书” | G77: =HYPERLINK("#码值映射清单!B5150","YesNo") | J77: 2023/01/12
B78: clr_asset_finance | C78: DEPCTFFLAG06 | D78: char(1) | E78: YES | F78: 是否已提交“单位定期存单确认书” | G78: =HYPERLINK("#码值映射清单!B5150","YesNo") | J78: 2023/01/12
B79: clr_asset_finance | C79: BAILFLAG01 | D79: char(1) | E79: YES | F79: 是否子账户 | J79: 2023/01/12
B80: clr_asset_finance | C80: BAILFLAG02 | D80: varchar(32) | E80: YES | F80: 是否已提交保证金相关存单凭证 | G80: =HYPERLINK("#码值映射清单!B5150","YesNo") | J80: 2023/01/12
B81: clr_asset_finance | C81: NDEPCTFFLAG01 | D81: char(1) | E81: YES | F81: 是否已提交存款所有人名下所有东方卡号 | J81: 2023/01/12
B82: clr_asset_finance | C82: NDEPCTFFLAG02 | D82: char(1) | E82: YES | F82: 是否已提交相关存款证明 | J82: 2023/01/12
B83: clr_asset_finance | C83: MARGINLEVEL | D83: varchar(6) | E83: YES | F83: 保证金层级 | G83: =HYPERLINK("#码值映射清单!B9423","MarginLevel") | J83: 2023/01/12
B84: clr_asset_finance | C84: RELATEDBUSINESSNO | D84: varchar(32) | E84: YES | F84: 对应业务编号 | J84: 2023/01/12
B85: clr_asset_finance | C85: BONDTYPE | D85: varchar(18) | E85: YES | F85: 债券形态 | G85: =HYPERLINK("#码值映射清单!B2575","BondMode") | J85: 2023/01/12
B86: clr_asset_finance | C86: BONDVALUE | D86: decimal(24,6) | E86: YES | F86: 债券发行价值 | J86: 2023/01/12
B87: clr_asset_finance | C87: BONDLISTTYPE | D87: varchar(6) | E87: YES | F87: 债券上市类别 | G87: =HYPERLINK("#码值映射清单!B2399","BondStockType") | J87: 2023/01/12
B88: clr_asset_finance | C88: BONDRATING | D88: varchar(18) | E88: YES | F88: 债券评级 | G88: =HYPERLINK("#码值映射清单!B5914","BondRating") | J88: 2023/01/12
B89: clr_asset_finance | C89: RATINGAGENCY | D89: varchar(32) | E89: YES | F89: 债券评级机构 | G89: =HYPERLINK("#码值映射清单!B9086","RatingAgency") | J89: 2023/01/12
B90: clr_asset_finance | C90: DRAWEROPENBANKNAME | D90: varchar(80) | E90: YES | F90: 出票人开户行 | J90: 2023/01/12
B91: clr_asset_finance | C91: SECURITYTYPE | D91: varchar(6) | E91: YES | F91: 证券类型 | G91: =HYPERLINK("#码值映射清单!B8172","ShareType01") | J91: 2023/01/12
B92: clr_asset_finance | C92: STOCKHOLDERNAME | D92: varchar(80) | E92: YES | F92: 股票持有人名称/持有人名称/基金持有人名称 | J92: 2023/01/12
B93: clr_asset_finance | C93: BAILACCOUNTNO | D93: varchar(80) | E93: YES | F93: 保证金账户号码 | J93: 2023/01/12
B94: clr_asset_finance | C94: DRAWBILLPLACE | D94: varchar(80) | E94: YES | F94: 出票地 | J94: 2023/01/12
B95: clr_asset_finance | C95: PAYPLACE | D95: varchar(80) | E95: YES | F95: 付款地 | J95: 2023/01/12
B96: clr_asset_finance | C96: STOCKHOLDERCODE | D96: varchar(32) | E96: YES | F96: 基金持有人代码/股票持有人代码 | J96: 2023/01/12
B97: clr_asset_finance | C97: CURRTRANSDATE | D97: datetime | E97: YES | F97: 当前交易日日期 | J97: 2023/01/12
B98: clr_asset_finance | C98: CURRTRANSPRICE | D98: decimal(24,6) | E98: YES | F98: 当前交易日市价;净值) | J98: 2023/01/12
B99: clr_asset_finance | C99: AVGPRICE | D99: decimal(24,6) | E99: YES | F99: 最近一年均价;净值） | J99: 2023/01/12
B100: clr_asset_finance | C100: BONDDENOMINATION | D100: decimal(24,6) | E100: YES | F100: 债券面额;或数量 | J100: 2023/01/12
...

Sheet clr_asset_others_equipment
A1: =HYPERLINK("#表结构清单!A1","返回") | B1: 交通和机械设备
B2: 表名 | C2: 列名 | D2: 字段类型 | E2: 是否为空 | F2: 字段注释 | G2: 码值 | H2: 备注 | I2: 修订人 | J2: 修订日期
B3: clr_asset_others_equipment | C3: CLRID | D3: varchar(32) | E3: NO | F3: 押品编号 | J3: 2023/01/12
B4: clr_asset_others_equipment | C4: TRANPORTNAME | D4: varchar(80) | E4: YES | F4: 车辆/船舶/航空器名称 | J4: 2023/01/12
B5: clr_asset_others_equipment | C5: VEHICLETYPE | D5: varchar(18) | E5: YES | F5: 车辆类型 | G5: =HYPERLINK("#码值映射清单!B5645","VehicleType") | J5: 2023/01/12
B6: clr_asset_others_equipment | C6: EQUIPMENTNAME | D6: varchar(80) | E6: YES | F6: 设备名称/押品具体名称 | J6: 2023/01/12
B7: clr_asset_others_equipment | C7: ENGINENO | D7: varchar(80) | E7: YES | F7: 发动机号 | J7: 2023/01/12
B8: clr_asset_others_equipment | C8: ENGINETYPE | D8: varchar(18) | E8: YES | F8: 航空器、在建航空器的发动机型号 | J8: 2023/01/12
B9: clr_asset_others_equipment | C9: ENGINEPRODUCTIONDATE | D9: varchar(18) | E9: YES | F9: 发动机出厂日期 | J9: 2023/01/12
B10: clr_asset_others_equipment | C10: SHIPTYPE | D10: varchar(6) | E10: YES | F10: 船舶类型 | G10: =HYPERLINK("#码值映射清单!B8615","ShipType") | J10: 2023/01/12
B11: clr_asset_others_equipment | C11: MODELNO | D11: varchar(80) | E11: YES | F11: 设备型号 | J11: 2023/01/12
B12: clr_asset_others_equipment | C12: BRAND | D12: varchar(80) | E12: YES | F12: 品牌型号/品牌/型号 | J12: 2023/01/12
B13: clr_asset_others_equipment | C13: MANUFACTURER | D13: varchar(80) | E13: YES | F13: 生产厂家 | J13: 2023/01/12
B14: clr_asset_others_equipment | C14: ORIGIN | D14: varchar(32) | E14: YES | F14: 生产地 | J14: 2023/01/12
B15: clr_asset_others_equipment | C15: ORIGINCOUNTRY | D15: varchar(18) | E15: YES | F15: 生产国别 | J15: 2023/01/12
B16: clr_asset_others_equipment | C16: SPECIFICATION | D16: varchar(500) | E16: YES | F16: 主要规格/设备规格 | J16: 2023/01/12
B17: clr_asset_others_equipment | C17: COLOR | D17: varchar(18) | E17: YES | F17: 颜色 | J17: 2023/01/12
B18: clr_asset_others_equipment | C18: VIN | D18: varchar(32) | E18: YES | F18: 车架号 | J18: 2023/01/12
B19: clr_asset_others_equipment | C19: LPN | D19: varchar(32) | E19: YES | F19: 车牌号 | J19: 2023/01/12
B20: clr_asset_others_equipment | C20: MAINTAINENCE | D20: varchar(500) | E20: YES | F20: 技术故障及维修状况 | J20: 2023/01/12
B21: clr_asset_others_equipment | C21: SHIPRGISTNO | D21: varchar(32) | E21: YES | F21: 船舶登记号/航空器编号 | J21: 2023/01/12
B22: clr_asset_others_equipment | C22: AIRCRAFTTYPE | D22: varchar(18) | E22: YES | F22: 航空器类型 | J22: 2023/01/12
... B34: clr_asset_others_equipment | C34: COMPLETIONDATE | D34: varchar(18) | E34: YES | F34: 完工日期/到期日期 | J34: 2023/01/12
B35: clr_asset_others_equipment | C35: ISDELIVERED | D35: char(1) | E35: YES | F35: 是否已交付 | G35: =HYPERLINK("#码值映射清单!B5150","YesNo") | J35: 2023/01/12
B36: clr_asset_others_equipment | C36: DEIVERYDATE | D36: varchar(18) | E36: YES | F36: 交付使用日期/航空器、在建航空器的交付使用日期 | J36: 2023/01/12
B37: clr_asset_others_equipment | C37: MARKETDATE | D37: varchar(18) | E37: YES | F37: 市场价格评估日期 | J37: 2023/01/12
B38: clr_asset_others_equipment | C38: HOMEAGRMPRICE | D38: decimal(24,6) | E38: YES | F38: 国内合同售价/最新参考购置价 | J38: 2023/01/12
B39: clr_asset_others_equipment | C39: EXECUTEDTIME | D39: int | E39: YES | F39: 已投入运营时间/已行驶公里数 | J39: 2023/01/12
B40: clr_asset_others_equipment | C40: SERVICEYEARSTATED | D40: int | E40: YES | F40: 规定使用年限/使用年限说明 | J40: 2023/01/12
B41: clr_asset_others_equipment | C41: SURPLUSSERVICELIFE | D41: int | E41: YES | F41: 船舶、在建船舶的剩余使用年限 | J41: 2023/01/12
B42: clr_asset_others_equipment | C42: SERVICEHOURSTATED | D42: int | E42: YES | F42: 规定总寿命小时/起落 | J42: 2023/01/12
B43: clr_asset_others_equipment | C43: REBUILDHOURSTATED | D43: int | E43: YES | F43: 翻修;含D检）时限小时/飞行起落 | J43: 2023/01/12
B44: clr_asset_others_equipment | C44: REBUILDHOURPASSED | D44: int | E44: YES | F44: 翻修;含D检）后已用小时/飞行起落 | J44: 2023/01/12
B45: clr_asset_others_equipment | C45: REBUILDTIMES | D45: int | E45: YES | F45: 翻修;含D检）次数 | J45: 2023/01/12
B46: clr_asset_others_equipment | C46: FOB | D46: decimal(24,6) | E46: YES | F46: 离岸合同价;美元） | J46: 2023/01/12
B47: clr_asset_others_equipment | C47: CIF | D47: decimal(24,6) | E47: YES | F47: 到岸合同价;美元）/到手价格 | J47: 2023/01/12
... B63: clr_asset_others_equipment | C63: PURCHASEDATE | D63: varchar(18) | E63: YES | F63: 购置日期/购入日期 | J63: 2023/01/12
B64: clr_asset_others_equipment | C64: EQUIPMENTTYPE | D64: varchar(6) | E64: YES | F64: 设备类型 | G64: =HYPERLINK("#码值映射清单!B8382","EquipmentType") | J64: 2023/01/12
B65: clr_asset_others_equipment | C65: EFFICIENCY | D65: varchar(200) | E65: YES | F65: 生产能力 | J65: 2023/01/12
B66: clr_asset_others_equipment | C66: OVERHAULTIMES | D66: int | E66: YES | F66: 大修次数 | J66: 2023/01/12
B67: clr_asset_others_equipment | C67: BILLPRICE | D67: decimal(24,6) | E67: YES | F67: 发票价格/合同价格/合同建造价格 | J67: 2023/01/12
B68: clr_asset_others_equipment | C68: CONTRACTCURRENCY | D68: varchar(18) | E68: YES | F68: 合同建造价格币种 | G68: =HYPERLINK("#码值映射清单!B2469","Currency") | J68: 2023/01/12
B69: clr_asset_others_equipment | C69: ASSEMBLEFEE | D69: decimal(24,6) | E69: YES | F69: 设备安装费 | J69: 2023/01/12
B70: clr_asset_others_equipment | C70: REASONABLEBUILDPERIOD | D70: int | E70: YES | F70: 合理工期;年） | J70: 2023/01/12
B71: clr_asset_others_equipment | C71: SEVICELIFE | D71: int | E71: YES | F71: 使用年限 | J71: 2023/01/12
B72: clr_asset_others_equipment | C72: SURPLUSSERVICELIFEOTHER | D72: int | E72: YES | F72: 剩余使用年限 | J72: 2023/01/12
B73: clr_asset_others_equipment | C73: RUNNEDHOURSOTHER | D73: int | E73: YES | F73: 已运转小时数 | J73: 2023/01/12
B74: clr_asset_others_equipment | C74: ANNUALSURVEY | D74: varchar(500) | E74: YES | F74: 年检情况 | J74: 2023/01/12
B75: clr_asset_others_equipment | C75: TRANSPORTFLAG01 | D75: char(1) | E75: YES | F75: 是否已提交购置合同与发票 | G75: =HYPERLINK("#码值映射清单!B5150","YesNo") | J75: 2023/01/12
B76: clr_asset_others_equipment | C76: TRANSPORTFLAG02 | D76: char(1) | E76: YES | F76: 是否已提交相关的行驶证 | G76: =HYPERLINK("#码值映射清单!B5150","YesNo") | J76: 2023/01/12
B77: clr_asset_others_equipment | C77: TRANSPORTFLAG03 | D77: char(1) | E77: YES | F77: 是否已提交相关的年检记录 | G77: =HYPERLINK("#码值映射清单!B5150","YesNo") | J77: 2023/01/12
B78: clr_asset_others_equipment | C78: TRANSPORTFLAG04 | D78: char(1) | E78: YES | F78: 是否有行驶证 | G78: =HYPERLINK("#码值映射清单!B5150","YesNo") | J78: 2023/01/12
B79: clr_asset_others_equipment | C79: SHIPFLAG01 | D79: char(1) | E79: YES | F79: 是否满足其他认定条件 | G79: =HYPERLINK("#码值映射清单!B5150","YesNo") | J79: 2023/01/12
B80: clr_asset_others_equipment | C80: SHIPFLAG02 | D80: char(1) | E80: YES | F80: 是否已提交船舶所有权登记证书/是否已提交航空器所有权证明文件 | G80: =HYPERLINK("#码值映射清单!B5150","YesNo") | J80: 2023/01/12
B81: clr_asset_others_equipment | C81: SHIPFLAG03 | D81: char(1) | E81: YES | F81: 是否已提交船舶检验证书簿 | G81: =HYPERLINK("#码值映射清单!B5150","YesNo") | J81: 2023/01/12
B82: clr_asset_others_equipment | C82: SHIPFLAG04 | D82: char(1) | E82: YES | F82: 是否已提交船舶船级证书 | G82: =HYPERLINK("#码值映射清单!B5150","YesNo") | J82: 2023/01/12
B83: clr_asset_others_equipment | C83: SHIPFLAG05 | D83: char(1) | E83: YES | F83: 是否已提交航行日志/是否已提交飞行记录本 | G83: =HYPERLINK("#码值映射清单!B5150","YesNo") | J83: 2023/01/12
B84: clr_asset_others_equipment | C84: SHIPFLAG06 | D84: char(1) | E84: YES | F84: 是否已提交相关租赁合同 | G84: =HYPERLINK("#码值映射清单!B5150","YesNo") | J84: 2023/01/12
B85: clr_asset_others_equipment | C85: SHIPFLAG07 | D85: char(1) | E85: YES | F85: 是否已提交船舶适航证书/是否已提交适航证 | G85: =HYPERLINK("#码值映射清单!B5150","YesNo") | J85: 2023/01/12
B86: clr_asset_others_equipment | C86: SHIPFLAG09 | D86: char(1) | E86: YES | F86: 是否已提交船舶保险单正本（原件） | G86: =HYPERLINK("#码值映射清单!B5150","YesNo") | J86: 2023/01/12
... B101: clr_asset_others_equipment | C101: EQUIPMENTFLAG05 | D101: char(1) | E101: YES | F101: 该设备是否市场普遍流通 | G101: =HYPERLINK("#码值映射清单!B5150","YesNo") | J101: 2023/01/12
B102: clr_asset_others_equipment | C102: INPUTORGID | D102: varchar(32) | E102: YES | F102: 登记机构 | J102: 2023/01/12
B103: clr_asset_others_equipment | C103: INPUTUSERID | D103: varchar(32) | E103: YES | F103: 登记人 | J103: 2023/01/12
B104: clr_asset_others_equipment | C104: INPUTDATE | D104: datetime | E104: YES | F104: 登记日期 | J104: 2023/01/12
B105: clr_asset_others_equipment | C105: UPDATEORGID | D105: varchar(32) | E105: YES | F105: 更新机构 | J105: 2023/01/12
B106: clr_asset_others_equipment | C106: UPDATEUSERID | D106: varchar(32) | E106: YES | F106: 更新人 | J106: 2023/01/12
B107: clr_asset_others_equipment | C107: UPDATEDATE | D107: datetime | E107: YES | F107: 更新日期 | J107: 2023/01/12
B108: clr_asset_others_equipment | C108: REMARK | D108: varchar(500) | E108: YES | F108: 备注 | J108: 2023/01/12
B109: clr_asset_others_equipment | C109: CORPORGID | D109: varchar(32) | E109: YES | F109: 法人机构编号 | J109: 2023/01/12
B110: clr_asset_others_equipment | C110: LOANCARDNO | D110: varchar(32) | E110: YES | F110: 权利人贷款卡号 | J110: 45740 | K110: LINE
B111: clr_asset_others_equipment | C111: EQUIPSTATUS | D111: varchar(6) | E111: YES | F111: 设备现状 | H111: 01 -出租、02-占用、03-闲置、04-自用、05-其他 | J111: 45740
B112: clr_asset_others_equipment | C112: GUARANTYDESCRIPT | D112: varchar(800) | E112: YES | F112: 抵押物说明 | J112: 45740
B113: clr_asset_others_equipment | C113: GUARANTYRIGHTID | D113: varchar(800) | E113: YES | F113: 权证号 | J113: 45740
B114: clr_asset_others_equipment | C114: ISPARTMORTGAGED | D114: varchar(6) | E114: YES | F114: 是否部分抵押 | J114: 45740
B115: clr_asset_others_equipment | C115: REALIZATIONVALUE | D115: decimal(24,6) | E115: YES | F115: 预计变现值 | J115: 45740
B116: clr_asset_others_equipment | C116: REALIZATIONCOST | D116: decimal(24,6) | E116: YES | F116: 预计变现成本 | J116: 45740
B117: clr_asset_others_equipment | C117: OTHERSRIGHTID | D117: varchar(100) | E117: YES | F117: 他项权证号 | J117: 45740
B118: clr_asset_others_equipment | C118: HASVEHICLEBUYTAX | D118: varchar(6) | E118: YES | F118: 是否有车辆购置附加税证 | J118: 45740
B119: clr_asset_others_equipment | C119: HASVEHICLEUSETAX | D119: varchar(6) | E119: YES | F119: 是否有当年车船使用税证 | J119: 45740
B120: clr_asset_others_equipment | C120: OTHERSRIGHTDATE | D120: datetime | E120: YES | F120: 取得他项权证时间 | J120: 45740
B121: clr_asset_others_equipment | C121: REGISTERINFO | D121: varchar(500) | E121: YES | F121: 抵押物登记情况 | J121: 45740
B122: clr_asset_others_equipment | C122: ISMORTGAGEDSELF | D122: varchar(6) | E122: YES | F122: 此抵押物是否当前申请所购/所抵资产 | J122: 45740
B123: clr_asset_others_equipment | C123: CHASSISNUMBER | D123: varchar(50) | E123: YES | F123: 底盘编号 | J123: 45740
... B132: clr_asset_others_equipment | C132: VEHICLEDATE | D132: datetime | E132: YES | F132: 提车日期 | J132: 45740
B133: clr_asset_others_equipment | C133: PAYOUTTYPE | D133: varchar(6) | E133: YES | F133: 支出类型 | H133: 01 -密码 、 02- 证件 、03 -印鉴 | J133: 45740
B134: clr_asset_others_equipment | C134: ISANNUALTEST | D134: varchar(6) | E134: YES | F134: 年检是否正常 | J134: 45740
B135: clr_asset_others_equipment | C135: VEHICLETYPE | D135: varchar(200) | E135: YES | F135: 运输工具类型 | J135: 45740
B136: clr_asset_others_equipment | C136: SHIPNATIONALITY | D136: varchar(32) | E136: YES | F136: 船籍 | J136: 45740
B137: clr_asset_others_equipment | C137: ISSHIPPINGCERT | D137: varchar(6) | E137: YES | F137: 是否有航运证 | J137: 45740
B138: clr_asset_others_equipment | C138: MILEAGE | D138: decimal(24,6) | E138: YES | F138: 已行驶里程数 | J138: 45740
B139: clr_asset_others_equipment | C139: RIGHTHOLDER | D139: varchar(80) | E139: YES | F139: 权利人 | J139: 45740

Sheet clr_asset_others_inventory
A1: =HYPERLINK("#表结构清单!A1","返回") | B1: 实物存货/货权/出口退税账户
B2: 表名 | C2: 列名 | D2: 字段类型 | E2: 是否为空 | F2: 字段注释 | G2: 码值 | H2: 备注 | I2: 修订人 | J2: 修订日期
B3: clr_asset_others_inventory | C3: CLRID | D3: varchar(32) | E3: NO | F3: 押品编号 | J3: 2023/01/12
B4: clr_asset_others_inventory | C4: INVENTORYID | D4: varchar(32) | E4: YES | F4: 存货编号/存货号 | J4: 2023/01/12
B5: clr_asset_others_inventory | C5: WAREHOUSERECENO | D5: varchar(32) | E5: YES | F5: 仓单号/提单号 | J5: 2023/01/12
B6: clr_asset_others_inventory | C6: REGNUMBER | D6: varchar(32) | E6: YES | F6: 出口退税登记号码 | J6: 2023/01/12
B7: clr_asset_others_inventory | C7: ACCOUNTNAME | D7: varchar(80) | E7: YES | F7: 出口退税账户户名 | J7: 2023/01/12
B8: clr_asset_others_inventory | C8: ACCOUNTBANKNO | D8: varchar(80) | E8: YES | F8: 出口退税账户开户行 | J8: 2023/01/12
B9: clr_asset_others_inventory | C9: TRANSPORTCONTRACTNO | D9: varchar(32) | E9: YES | F9: 运输合同号码 | J9: 2023/01/12
B10: clr_asset_others_inventory | C10: TRANSPORTCONTRACTNAME | D10: varchar(80) | E10: YES | F10: 运输合同名称 | J10: 2023/01/12
B11: clr_asset_others_inventory | C11: CARRIER | D11: varchar(80) | E11: YES | F11: 承运人 | J11: 2023/01/12
B12: clr_asset_others_inventory | C12: CONSIGNOR | D12: varchar(80) | E12: YES | F12: 托运人 | J12: 2023/01/12
B13: clr_asset_others_inventory | C13: CONSIGNEE | D13: varchar(80) | E13: YES | F13: 收货人 | J13: 2023/01/12
B14: clr_asset_others_inventory | C14: RECIVEPLACE | D14: varchar(500) | E14: YES | F14: 接货地 | J14: 2023/01/12
... B20: clr_asset_others_inventory | C20: SUBPLACE | D20: varchar(500) | E20: YES | F20: 交货地 | J20: 2023/01/12
B21: clr_asset_others_inventory | C21: CARGOTYPE | D21: varchar(6) | E21: YES | F21: 货物类型 | G21: =HYPERLINK("#码值映射清单!B2740","CargoType") | J21: 2023/01/12
B22: clr_asset_others_inventory | C22: CARGONAME | D22: varchar(80) | E22: YES | F22: 货物名称 | J22: 2023/01/12
B23: clr_asset_others_inventory | C23: CARGOQUANTITY | D23: decimal(18,2) | E23: YES | F23: 货物数量;或重量）/毛重/数量 | J23: 2023/01/12
B24: clr_asset_others_inventory | C24: MEASUREUNIT | D24: varchar(18) | E24: YES | F24: 货物计量单位 | J24: 2023/01/12
B25: clr_asset_others_inventory | C25: SPECIFICATION | D25: varchar(500) | E25: YES | F25: 规格 | J25: 2023/01/12
B26: clr_asset_others_inventory | C26: ORIGIN | D26: varchar(80) | E26: YES | F26: 产地 | J26: 2023/01/12
B27: clr_asset_others_inventory | C27: UNITPRICE | D27: decimal(24,6) | E27: YES | F27: 单价 | J27: 2023/01/12
B28: clr_asset_others_inventory | C28: STORAGECOMPANYNAME | D28: varchar(80) | E28: YES | F28: 仓储公司名称 | J28: 2023/01/12
B29: clr_asset_others_inventory | C29: STORAGESTARTDATE | D29: datetime | E29: YES | F29: 存放起始日期/存储起始日 | J29: 2023/01/12
B30: clr_asset_others_inventory | C30: STORAGEDUEDATE | D30: datetime | E30: YES | F30: 存储到期日/提单到期日期 | J30: 2023/01/12
B31: clr_asset_others_inventory | C31: INSURANCE | D31: varchar(500) | E31: YES | F31: 保险情况 | J31: 2023/01/12
B32: clr_asset_others_inventory | C32: CURRMARKETPRICE | D32: decimal(24,6) | E32: YES | F32: 当前市场价格 | J32: 2023/01/12
B33: clr_asset_others_inventory | C33: STORINGADDRESS | D33: varchar(80) | E33: YES | F33: 货物存放地 | J33: 2023/01/12
... B45: clr_asset_others_inventory | C45: WREFFECTIVEDATE | D45: datetime | E45: YES | F45: 仓单生效日 | J45: 2023/01/12
B46: clr_asset_others_inventory | C46: COMMODITYFUTURE | D46: varchar(6) | E46: YES | F46: 所属商品期货交易所 | G46: =HYPERLINK("#码值映射清单!B9899","CommodityFuture") | J46: 2023/01/12
B47: clr_asset_others_inventory | C47: HOLDINGLOT | D47: varchar(500) | E47: YES | F47: 持有手数 | J47: 2023/01/12
B48: clr_asset_others_inventory | C48: HOLDINGLOTCOUNT | D48: int | E48: YES | F48: 持有手数数量/签发份数 | J48: 2023/01/12
B49: clr_asset_others_inventory | C49: WRAPTYPE | D49: varchar(500) | E49: YES | F49: 货物包装种类 | J49: 2023/01/12
B50: clr_asset_others_inventory | C50: FREIGHTPAYTYPE | D50: varchar(18) | E50: YES | F50: 运费支付类型 | G50: =HYPERLINK("#码值映射清单!B1667","CarriagePaymentType") | J50: 2023/01/12
B51: clr_asset_others_inventory | C51: FREIGHTSUM | D51: decimal(24,6) | E51: YES | F51: 运费金额 | J51: 2023/01/12
B52: clr_asset_others_inventory | C52: EXPORTREBATESCERTID | D52: varchar(32) | E52: YES | F52: 出口退税账户相关营业执照编号 | J52: 2023/01/12
B53: clr_asset_others_inventory | C53: EXPORTREBATESACCOUNT | D53: varchar(32) | E53: YES | F53: 出口退税账户账号 | J53: 2023/01/12
B54: clr_asset_others_inventory | C54: ENTREBATESLEVEL | D54: varchar(6) | E54: YES | F54: 企业退税等级 | J54: 2023/01/12
B55: clr_asset_others_inventory | C55: EXPORTREBATESRATE | D55: decimal(18,8) | E55: YES | F55: 出口退税率 | J55: 2023/01/12
B56: clr_asset_others_inventory | C56: ARRIVALTIME | D56: datetime | E56: YES | F56: 预计到账时间 | J56: 2023/01/12
B57: clr_asset_others_inventory | C57: REBATEMETHOD | D57: varchar(500) | E57: YES | F57: 退付办法 | J57: 2023/01/12
B58: clr_asset_others_inventory | C58: COMMODITYNAME | D58: varchar(80) | E58: YES | F58: 商品名称 | J58: 2023/01/12
B59: clr_asset_others_inventory | C59: COMMODITYPRICE | D59: decimal(24,6) | E59: YES | F59: 商品单价 | J59: 2023/01/12
B60: clr_asset_others_inventory | C60: EXPORTVOLUME | D60: decimal(18,2) | E60: YES | F60: 出口量 | J60: 2023/01/12
B61: clr_asset_others_inventory | C61: PRODUCTSALEPLACE | D61: varchar(80) | E61: YES | F61: 产品销往地 | J61: 2023/01/12
B62: clr_asset_others_inventory | C62: ISCOMMITCONTRACT | D62: char(1) | E62: YES | F62: 是否已提交商品买卖合同 | G62: =HYPERLINK("#码值映射清单!B5150","YesNo") | J62: 2023/01/12
B63: clr_asset_others_inventory | C63: INVENTORYFLAG06 | D63: char(1) | E63: YES | F63: 是否已提交商品交易发票 | G63: =HYPERLINK("#码值映射清单!B5150","YesNo") | J63: 2023/01/12
B64: clr_asset_others_inventory | C64: INVENTORYFLAG09 | D64: char(1) | E64: YES | F64: 是否已提交相关保险证明 | G64: =HYPERLINK("#码值映射清单!B5150","YesNo") | J64: 2023/01/12
B65: clr_asset_others_inventory | C65: INVENTORYFLAG01 | D65: char(1) | E65: YES | F65: 是否为法律和行规法规禁止流通的货物 | G65: =HYPERLINK("#码值映射清单!B5150","YesNo") | J65: 2023/01/12
B66: clr_asset_others_inventory | C66: INVENTORYFLAG02 | D66: char(1) | E66: YES | F66: 是否已提交质检单 | G66: =HYPERLINK("#码值映射清单!B5150","YesNo") | J66: 2023/01/12
B67: clr_asset_others_inventory | C67: INVENTORYFLAG03 | D67: char(1) | E67: YES | F67: 是否已提交合格证 | G67: =HYPERLINK("#码值映射清单!B5150","YesNo") | J67: 2023/01/12
B68: clr_asset_others_inventory | C68: INVENTORYFLAG04 | D68: char(1) | E68: YES | F68: 是否已提交商检证明 | G68: =HYPERLINK("#码值映射清单!B5150","YesNo") | J68: 2023/01/12
B69: clr_asset_others_inventory | C69: INVENTORYFLAG07 | D69: char(1) | E69: YES | F69: 是否已提交货物存放证明 | G69: =HYPERLINK("#码值映射清单!B5150","YesNo") | J69: 2023/01/12
B70: clr_asset_others_inventory | C70: INVENTORYFLAG08 | D70: char(1) | E70: YES | F70: 是否已提交货运合同 | G70: =HYPERLINK("#码值映射清单!B5150","YesNo") | J70: 2023/01/12
B71: clr_asset_others_inventory | C71: INVENTORYFLAG10 | D71: char(1) | E71: YES | F71: 是否已提交由托管机构指定仓库提供的出质人名下的贵金属的证明文件 | G71: =HYPERLINK("#码值映射清单!B5150","YesNo") | J71: 2023/01/12
B72: clr_asset_others_inventory | C72: INVENTORYFLAG11 | D72: char(1) | E72: YES | F72: 是否已提交信用证项下的货物、权利凭证 | G72: =HYPERLINK("#码值映射清单!B5150","YesNo") | J72: 2023/01/12
B73: clr_asset_others_inventory | C73: ISCOMMITWR | D73: char(1) | E73: YES | F73: 是否已提交仓单凭证 | G73: =HYPERLINK("#码值映射清单!B5150","YesNo") | J73: 2023/01/12
... B88: clr_asset_others_inventory | C88: ETRA11 | D88: char(1) | E88: YES | F88: 是否已提交出口退税账号相关存折或凭证 | G88: =HYPERLINK("#码值映射清单!B5150","YesNo") | J88: 2023/01/12
B89: clr_asset_others_inventory | C89: ETRA12 | D89: char(1) | E89: YES | F89: 市价是否由独立的价值评估者所估计 | J89: 2023/01/12
B90: clr_asset_others_inventory | C90: INPUTORGID | D90: varchar(32) | E90: YES | F90: 登记机构 | J90: 2023/01/12
B91: clr_asset_others_inventory | C91: INPUTUSERID | D91: varchar(32) | E91: YES | F91: 登记人 | J91: 2023/01/12
B92: clr_asset_others_inventory | C92: INPUTDATE | D92: datetime | E92: YES | F92: 登记日期 | J92: 2023/01/12
B93: clr_asset_others_inventory | C93: UPDATEORGID | D93: varchar(32) | E93: YES | F93: 更新机构 | J93: 2023/01/12
B94: clr_asset_others_inventory | C94: UPDATEUSERID | D94: varchar(32) | E94: YES | F94: 更新人 | J94: 2023/01/12
B95: clr_asset_others_inventory | C95: UPDATEDATE | D95: datetime | E95: YES | F95: 更新日期 | J95: 2023/01/12
B96: clr_asset_others_inventory | C96: REMARK | D96: varchar(500) | E96: YES | F96: 备注 | J96: 2023/01/12
B97: clr_asset_others_inventory | C97: CORPORGID | D97: varchar(32) | E97: YES | F97: 法人机构编号 | J97: 2023/01/12
B98: clr_asset_others_inventory | C98: LOANCARDNO | D98: varchar(32) | E98: YES | F98: 出质人贷款卡号 | J98: 45740
B99: clr_asset_others_inventory | C99: GUARANTYAMOUNT | D99: decimal(24,6) | E99: YES | F99: 质押物数量 | J99: 45740
B100: clr_asset_others_inventory | C100: GUARANTYRIGHTID | D100: varchar(800) | E100: YES | F100: 权证号 | J100: 45740
B101: clr_asset_others_inventory | C101: GUARANTYVALUE | D101: decimal(24,6) | E101: YES | F101: 存货价值 | J101: 45740
B102: clr_asset_others_inventory | C102: CURRENCY | D102: varchar(18) | E102: YES | F102: 质押物原币种 | G102: =HYPERLINK("#码值映射清单!B2469","Currency") | J102: 45740
B103: clr_asset_others_inventory | C103: ORIGINALVALUE | D103: decimal(24,6) | E103: YES | F103: 质押物原价值 | J103: 45740
B104: clr_asset_others_inventory | C104: REALIZATIONVALUE | D104: decimal(24,6) | E104: YES | F104: 预计变现值 | J104: 45740
B105: clr_asset_others_inventory | C105: REALIZATIONCOST | D105: decimal(24,6) | E105: YES | F105: 预计变现成本 | J105: 45740
B106: clr_asset_others_inventory | C106: PURCHASEDVALUE | D106: decimal(24,6) | E106: YES | F106: 货物购入价值 | J106: 45740
B107: clr_asset_others_inventory | C107: STORAGELOCATION | D107: varchar(200) | E107: YES | F107: 存放地点/提货地点 | J107: 45740
B108: clr_asset_others_inventory | C108: SUPPLIERNAME | D108: varchar(80) | E108: YES | F108: 供应商名称 | J108: 45740
B109: clr_asset_others_inventory | C109: DUETAX | D109: decimal(24,6) | E109: YES | F109: 应退未退税金额 | J109: 45740
B110: clr_asset_others_inventory | C110: LIVESTOCKTYPE | D110: varchar(32) | E110: YES | F110: 活畜种类 | J110: 45740
B111: clr_asset_others_inventory | C111: RIGHTHOLDER | D111: varchar(80) | E111: YES | F111: 权利人 | J111: 45740

Sheet clr_asset_others_resource
A1: =HYPERLINK("#表结构清单!A1","返回") | B1: 资源资产
B2: 表名 | C2: 列名 | D2: 字段类型 | E2: 是否为空 | F2: 字段注释 | G2: 码值 | H2: 备注 | I2: 修订人 | J2: 修订日期
B3: clr_asset_others_resource | C3: CLRID | D3: varchar(32) | E3: NO | F3: 押品编号 | J3: 2023/01/12
B4: clr_asset_others_resource | C4: LEGALREPRESENTATIVE | D4: varchar(80) | E4: YES | F4: 法定代表人/森林或林木所有权权利人/资产权利人 | J4: 2023/01/12
B5: clr_asset_others_resource | C5: FORESTLANDUSETYPE | D5: varchar(6) | E5: YES | F5: 林地用途类型 | G5: =HYPERLINK("#码值映射清单!B7213","ForestUseType") | J5: 2023/01/12
B6: clr_asset_others_resource | C6: RESOURCERIGHTTYPE | D6: varchar(6) | E6: YES | F6: 林地资源权属类型 | G6: =HYPERLINK("#码值映射清单!B3620","ResourceRightType") | J6: 2023/01/12
B7: clr_asset_others_resource | C7: FOURBOUNDARY | D7: varchar(200) | E7: YES | F7: 四至/荒地四至 | J7: 2023/01/12
B8: clr_asset_others_resource | C8: FORESTCATEGORY | D8: varchar(80) | E8: YES | F8: 林地林种 | J8: 2023/01/12
B9: clr_asset_others_resource | C9: TREESPECY | D9: varchar(80) | E9: YES | F9: 林地树种 | J9: 2023/01/12
B10: clr_asset_others_resource | C10: TREEAGE | D10: int | E10: YES | F10: 林地树龄 | J10: 2023/01/12
B11: clr_asset_others_resource | C11: FORESTAGE | D11: int | E11: YES | F11: 林地林龄 | J11: 2023/01/12
B12: clr_asset_others_resource | C12: TREEAMOUNT | D12: int | E12: YES | F12: 林地株数 | J12: 2023/01/12
B13: clr_asset_others_resource | C13: SAVEUP | D13: int | E13: YES | F13: 林地蓄积 | J13: 2023/01/12
B14: clr_asset_others_resource | C14: DOMINANTSHAREHOLDER | D14: varchar(80) | E14: YES | F14: 控股股东 | J14: 2023/01/12
B15: clr_asset_others_resource | C15: MINENAME | D15: varchar(80) | E15: YES | F15: 矿山名称/项目名称 | J15: 2023/01/12
B16: clr_asset_others_resource | C16: MINERALTYPE | D16: varchar(200) | E16: YES | F16: 矿产种类 | J16: 2023/01/12
B17: clr_asset_others_resource | C17: MRSTARTDATE | D17: varchar(18) | E17: YES | F17: 采矿权起始日/探矿权起始日/许可证起始日/发证起始日 | J17: 2023/01/12
B18: clr_asset_others_resource | C18: MRDUEDATE | D18: varchar(18) | E18: YES | F18: 采矿权到期日/探矿权到期日/许可证到期日/发证到期日 | J18: 2023/01/12
... B37: clr_asset_others_resource | C37: MININGATT05 | D37: varchar(200) | E37: YES | F37: 年度审查情况 | J37: 2023/01/12
B38: clr_asset_others_resource | C38: MININGFLAG01 | D38: varchar(200) | E38: YES | F38: 是否需要申请项目融资 | G38: =HYPERLINK("#码值映射清单!B5150","YesNo") | J38: 2023/01/12
B39: clr_asset_others_resource | C39: WOODLANDOBLIGEE | D39: varchar(80) | E39: YES | F39: 林地所有权权利人 | J39: 2023/01/12
B40: clr_asset_others_resource | C40: FORESTOBLIGEE | D40: varchar(80) | E40: YES | F40: 森林或林木所有权权利人 | J40: 2023/01/12
B41: clr_asset_others_resource | C41: WOODLANDSECONDLEVELTYPE | D41: varchar(18) | E41: YES | F41: 林地二级地类 | G41: =HYPERLINK("#码值映射清单!B7958","WoodlandSubType") | J41: 2023/01/12
B42: clr_asset_others_resource | C42: NATURALCALAMITY | D42: varchar(200) | E42: YES | F42: 自然灾害发生情况 | J42: 2023/01/12
B43: clr_asset_others_resource | C43: ROWSPACING | D43: varchar(200) | E43: YES | F43: 株行距情况 | J43: 2023/01/12
B44: clr_asset_others_resource | C44: RCP | D44: decimal(18,2) | E44: YES | F44: 轮伐期 | J44: 2023/01/12
B45: clr_asset_others_resource | C45: OTHERVEGETATION | D45: varchar(200) | E45: YES | F45: 其他植被情况 | J45: 2023/01/12
B46: clr_asset_others_resource | C46: WOODANNUALOUTPUT | D46: varchar(200) | E46: YES | F46: 林木年产量情况 | J46: 2023/01/12
B47: clr_asset_others_resource | C47: WOODPRICEMEMO | D47: varchar(200) | E47: YES | F47: 木材价格描述 | J47: 2023/01/12
B48: clr_asset_others_resource | C48: MECHANIZATIONLEVEL | D48: varchar(200) | E48: YES | F48: 机械化水平/农业技术水平 | J48: 2023/01/12
B49: clr_asset_others_resource | C49: USAGEPERIOD | D49: decimal(18,2) | E49: YES | F49: 林地使用期 | J49: 2023/01/12
B50: clr_asset_others_resource | C50: TIMEPASSED | D50: decimal(18,2) | E50: YES | F50: 林地已使用时间 | J50: 2023/01/12
B51: clr_asset_others_resource | C51: WOODLANDRIGHTDUEDATE | D51: varchar(18) | E51: YES | F51: 林地使用权终止日期 | J51: 2023/01/12
B52: clr_asset_others_resource | C52: TRAFFICCONDITON | D52: varchar(200) | E52: YES | F52: 交通条件 | J52: 2023/01/12
B53: clr_asset_others_resource | C53: NATIONPOLICY | D53: varchar(200) | E53: YES | F53: 国家政策 | J53: 2023/01/12
B54: clr_asset_others_resource | C54: LANDRENTINCOME | D54: decimal(24,6) | E54: YES | F54: 土地租金年收入 | J54: 2023/01/12
B55: clr_asset_others_resource | C55: MININGFLAG02 | D55: char(1) | E55: YES | F55: 采矿权是否符合转让条件 | G55: =HYPERLINK("#码值映射清单!B5150","YesNo") | J55: 2023/01/12
B56: clr_asset_others_resource | C56: MININGFLAG03 | D56: char(1) | E56: YES | F56: 采矿权是否已出租 | G56: =HYPERLINK("#码值映射清单!B5150","YesNo") | J56: 2023/01/12
B57: clr_asset_others_resource | C57: RESOURCERIGHTNO | D57: varchar(80) | E57: YES | F57: 采矿权权证号/海域使用权登记号/探矿权权证号/林权证编号/资产权证号/证书编号 | J57: 2023/01/12
B58: clr_asset_others_resource | C58: BOUNDARY | D58: varchar(200) | E58: YES | F58: 海域界址 | J58: 2023/01/12
B59: clr_asset_others_resource | C59: GNTWATERSAREA | D59: decimal(18,2) | E59: YES | F59: 宗海面积 | J59: 2023/01/12
B60: clr_asset_others_resource | C60: ANNUALSURVEY | D60: varchar(200) | E60: YES | F60: 海域使用权的年度审查情况 | J60: 2023/01/12
B61: clr_asset_others_resource | C61: WATERSGRADE | D61: varchar(200) | E61: YES | F61: 海域等级 | J61: 2023/01/12
B62: clr_asset_others_resource | C62: USAGETYPE | D62: varchar(6) | E62: YES | F62: 用海类型 | G62: =HYPERLINK("#码值映射清单!B7690","WatersUsageType") | J62: 2023/01/12
B63: clr_asset_others_resource | C63: ASSIGNMENTFEE | D63: decimal(24,6) | E63: YES | F63: 海域出让金/海域转让金 | J63: 2023/01/12
B64: clr_asset_others_resource | C64: USAGESTARTDATE | D64: varchar(18) | E64: YES | F64: 海域使用权批准使用起始日期 | J64: 2023/01/12
B65: clr_asset_others_resource | C65: USAGEDUEDATE | D65: varchar(18) | E65: YES | F65: 海域使用权批准使用终止日期 | J65: 2023/01/12
B66: clr_asset_others_resource | C66: WASTELANDCONTRACTNO | D66: varchar(32) | E66: YES | F66: 荒地承包合同编号 | J66: 2023/01/12
B67: clr_asset_others_resource | C67: WASTELANDCERTTID | D67: varchar(80) | E67: YES | F67: 荒地所属土地使用权证号 | J67: 2023/01/12
B68: clr_asset_others_resource | C68: WASTELANDDUEDATE | D68: varchar(18) | E68: YES | F68: 荒地所属土地使用权到期日 | J68: 2023/01/12
B69: clr_asset_others_resource | C69: WASTELANDUSAGE | D69: varchar(6) | E69: YES | F69: 荒地用途 | G69: =HYPERLINK("#码值映射清单!B7307","WasteLandUsageType") | J69: 2023/01/12
B70: clr_asset_others_resource | C70: CONTRACTPERIOD | D70: int | E70: YES | F70: 荒地承包期限 | J70: 2023/01/12
B71: clr_asset_others_resource | C71: CONTRACTSUM | D71: decimal(24,6) | E71: YES | F71: 荒地承包金额/资产金额 | J71: 2023/01/12
B72: clr_asset_others_resource | C72: LUR03ATT01 | D72: varchar(200) | E72: YES | F72: 合同终止时地上附着物处置方式 | J72: 2023/01/12
B73: clr_asset_others_resource | C73: LUR03ATT02 | D73: varchar(200) | E73: YES | F73: 荒地地貌 | J73: 2023/01/12
B74: clr_asset_others_resource | C74: LUR03ATT03 | D74: varchar(200) | E74: YES | F74: 荒地所属土地流转情况 | J74: 2023/01/12
B75: clr_asset_others_resource | C75: OWNERNAME | D75: varchar(80) | E75: YES | F75: 权利人名称/探矿权人名称 | J75: 2023/01/12
B76: clr_asset_others_resource | C76: APPROVEORG | D76: varchar(80) | E76: YES | F76: 权利批准机关 | J76: 2023/01/12
B77: clr_asset_others_resource | C77: LUR03FLAG01 | D77: char(1) | E77: YES | F77: 荒地可否续期 | G77: =HYPERLINK("#码值映射清单!B5150","YesNo") | J77: 2023/01/12
B78: clr_asset_others_resource | C78: LUR03FLAG02 | D78: char(1) | E78: YES | F78: 是否已提交荒地所属土地使用权证 | G78: =HYPERLINK("#码值映射清单!B5150","YesNo") | J78: 2023/01/12
B79: clr_asset_others_resource | C79: LUR03FLAG03 | D79: char(1) | E79: YES | F79: 是否已提交四荒地承包合同 | G79: =HYPERLINK("#码值映射清单!B5150","YesNo") | J79: 2023/01/12
B80: clr_asset_others_resource | C80: LUR03FLAG04 | D80: char(1) | E80: YES | F80: 是否已提交农村土地承包经营权证书 | G80: =HYPERLINK("#码值映射清单!B5150","YesNo") | J80: 2023/01/12
B81: clr_asset_others_resource | C81: MININGFLAG04 | D81: char(1) | E81: YES | F81: 矿山是否已经按要求关闭或被列入关闭计划 | G81: =HYPERLINK("#码值映射清单!B5150","YesNo") | J81: 2023/01/12
B82: clr_asset_others_resource | C82: MININGFLAG05 | D82: char(1) | E82: YES | F82: 是否已提交采矿权许可证 | G82: =HYPERLINK("#码值映射清单!B5150","YesNo") | J82: 2023/01/12
B83: clr_asset_others_resource | C83: MININGFLAG06 | D83: char(1) | E83: YES | F83: 是否已提交与采矿权相关的企业法人营业执照 | G83: =HYPERLINK("#码值映射清单!B5150","YesNo") | J83: 2023/01/12
B84: clr_asset_others_resource | C84: MININGFLAG07 | D84: char(1) | E84: YES | F84: 是否已提交企业财务会计报表 | G84: =HYPERLINK("#码值映射清单!B5150","YesNo") | J84: 2023/01/12
B85: clr_asset_others_resource | C85: MININGFLAG08 | D85: char(1) | E85: YES | F85: 是否已提交资源储量核实报告 | G85: =HYPERLINK("#码值映射清单!B5150","YesNo") | J85: 2023/01/12
B86: clr_asset_others_resource | C86: MININGFLAG09 | D86: char(1) | E86: YES | F86: 是否已提交地质勘查报告 | G86: =HYPERLINK("#码值映射清单!B5150","YesNo") | J86: 2023/01/12
B87: clr_asset_others_resource | C87: MININGFLAG10 | D87: char(1) | E87: YES | F87: 是否已提交（预）可行性研究报告 | G87: =HYPERLINK("#码值映射清单!B5150","YesNo") | J87: 2023/01/12
B88: clr_asset_others_resource | C88: MININGFLAG11 | D88: char(1) | E88: YES | F88: 是否已提交矿产资源开发利用方案 | G88: =HYPERLINK("#码值映射清单!B5150","YesNo") | J88: 2023/01/12
... B105: clr_asset_others_resource | C105: FOREST01FLAG02 | D105: char(1) | E105: YES | F105: 是否已提交森林和林木所属的土地使用权证 | G105: =HYPERLINK("#码值映射清单!B5150","YesNo") | J105: 2023/01/12
B106: clr_asset_others_resource | C106: WOODLANDDESCRIPTION | D106: varchar(200) | E106: YES | F106: 林地描述 | J106: 2023/01/12
B107: clr_asset_others_resource | C107: ACREAGE | D107: decimal(18,2) | E107: YES | F107: 面积/勘察面积 | J107: 2023/01/12
B108: clr_asset_others_resource | C108: INPUTORGID | D108: varchar(32) | E108: YES | F108: 登记机构 | J108: 2023/01/12
B109: clr_asset_others_resource | C109: INPUTUSERID | D109: varchar(32) | E109: YES | F109: 登记人 | J109: 2023/01/12
B110: clr_asset_others_resource | C110: INPUTDATE | D110: datetime | E110: YES | F110: 登记日期 | J110: 2023/01/12
B111: clr_asset_others_resource | C111: UPDATEORGID | D111: varchar(32) | E111: YES | F111: 更新机构 | J111: 2023/01/12
B112: clr_asset_others_resource | C112: UPDATEUSERID | D112: varchar(32) | E112: YES | F112: 更新人 | J112: 2023/01/12
B113: clr_asset_others_resource | C113: UPDATEDATE | D113: datetime | E113: YES | F113: 更新日期 | J113: 2023/01/12
B114: clr_asset_others_resource | C114: REMARK | D114: varchar(500) | E114: YES | F114: 备注 | J114: 2023/01/12
B115: clr_asset_others_resource | C115: CORPORGID | D115: varchar(32) | E115: YES | F115: 法人机构编号 | J115: 2023/01/12
B116: clr_asset_others_resource | C116: MININGADDRESS | D116: varchar(32) | E116: YES | F116: 矿区地址/注册地址 | J116: 45740
B117: clr_asset_others_resource | C117: RIGHTSRANK | D117: INTEGER(4) | E117: YES | F117: 我行抵押权顺位 | J117: 45740
B118: clr_asset_others_resource | C118: LOANCARDNO | D118: varchar(32) | E118: YES | F118: 权利人贷款卡号 | J118: 45740
B119: clr_asset_others_resource | C119: AMOUNTPAID | D119: decimal(24,6) | E119: YES | F119: 已交采矿权价款 | J119: 45740
B120: clr_asset_others_resource | C120: COALTONNAGE | D120: decimal(24,6) | E120: YES | F120: 已交采矿权价款折合煤炭吨数 | J120: 45740
B121: clr_asset_others_resource | C121: MININGSEAMNO | D121: varchar(40) | E121: YES | F121: 开采层号 | J121: 45740
B122: clr_asset_others_resource | C122: SAFECERTNO | D122: varchar(40) | E122: YES | F122: 安全生产许可证编号 | J122: 45740
B123: clr_asset_others_resource | C123: SAFECERTPERIOD | D123: varchar(10) | E123: YES | F123: 安全生产许可证有效期 | J123: 45740
B124: clr_asset_others_resource | C124: COALPRDNO | D124: varchar(40) | E124: YES | F124: 煤炭生产许可证编号 | J124: 45740
B125: clr_asset_others_resource | C125: COALPRDPERIOD | D125: varchar(10) | E125: YES | F125: 煤炭生产许可证有效期 | J125: 45740
B126: clr_asset_others_resource | C126: FILENO1 | D126: varchar(40) | E126: YES | F126: 《矿产资源评审备案证明》编号 | J126: 45740
B127: clr_asset_others_resource | C127: FILEDATE1 | D127: varchar(10) | E127: YES | F127: 《矿产资源评审备案证明》评审基准日 | J127: 45740
... B137: clr_asset_others_resource | C137: RIGHTHOLDER | D137: varchar(80) | E137: YES | F137: 林地使用权人/海域使用权人 | J137: 45740
B138: clr_asset_others_resource | C138: ASSETPURPOSE | D138: varchar(6) | E138: YES | F138: 资产用途 | H138: 01-种植业、02-林业、03-畜牧业、04-渔业生产、05-其他 | J138: 45740
B139: clr_asset_others_resource | C139: ISSUINGAUTHORITY | D139: varchar(32) | E139: YES | F139: 发证机关 | J139: 45740
B140: clr_asset_others_resource | C140: ISSUINGDATE | D140: datetime | E140: YES | F140: 发证日期 | J140: 45740
B141: clr_asset_others_resource | C141: PRDADDRESS | D141: varchar(80) | E141: YES | F141: 生产经营场所地址 | J141: 45740
B142: clr_asset_others_resource | C142: RIGHTSGEOSCOPE | D142: varchar(80) | E142: YES | F142: 权利地域范围 | J142: 45740

Sheet clr_asset_others_sbc
A1: =HYPERLINK("#表结构清单!A1","返回") | B1: 特殊建筑构造物
B2: 表名 | C2: 列名 | D2: 字段类型 | E2: 是否为空 | F2: 字段注释 | G2: 码值 | H2: 备注 | I2: 修订人 | J2: 修订日期
B3: clr_asset_others_sbc | C3: CLRID | D3: varchar(32) | E3: NO | F3: 押品编号 | J3: 2023/01/12
B4: clr_asset_others_sbc | C4: REFTOLLRIGHTOWNER | D4: varchar(80) | E4: YES | F4: 相关收费权所有人 | J4: 2023/01/12
B5: clr_asset_others_sbc | C5: STRUCTURENAME | D5: varchar(80) | E5: YES | F5: 构造物名称 | J5: 2023/01/12
B6: clr_asset_others_sbc | C6: STRUCTUREHOLDER | D6: varchar(80) | E6: YES | F6: 构造物持有人 | J6: 2023/01/12
B7: clr_asset_others_sbc | C7: STRUCTURELOCATION | D7: varchar(500) | E7: YES | F7: 构造物的坐落位置/详细地址 | J7: 2023/01/12
B8: clr_asset_others_sbc | C8: STRUCTUREDEVELOPER | D8: varchar(80) | E8: YES | F8: 构造物开发商名称 | J8: 2023/01/12
B9: clr_asset_others_sbc | C9: ZIPCODE | D9: varchar(18) | E9: YES | F9: 邮政编码 | J9: 2023/01/12
B10: clr_asset_others_sbc | C10: LANDNO | D10: varchar(32) | E10: YES | F10: 构造物所属土地地号 | J10: 2023/01/12
B11: clr_asset_others_sbc | C11: LANDUSER | D11: varchar(80) | E11: YES | F11: 构造物所属土地使用权人 | J11: 2023/01/12
B12: clr_asset_others_sbc | C12: LANDCERTID | D12: varchar(32) | E12: YES | F12: 构造物所属土地使用权证号 | J12: 2023/01/12
B13: clr_asset_others_sbc | C13: STRUCTURETYPE | D13: varchar(6) | E13: YES | F13: 构造物类型 | G13: =HYPERLINK("#码值映射清单!B8937","SpecialStructureType") | J13: 2023/01/12
B14: clr_asset_others_sbc | C14: STRUCTURESOURCE | D14: varchar(6) | E14: YES | F14: 构造物来源/权属来源 | G14: =HYPERLINK("#码值映射清单!B9119","RealtyRightSource") | J14: 2023/01/12
B15: clr_asset_others_sbc | C15: STRUCTURELEVEL | D15: varchar(80) | E15: YES | F15: 构造物等级 | J15: 2023/01/12
B16: clr_asset_others_sbc | C16: STRUCTUREUSEAREA | D16: decimal(18,2) | E16: YES | F16: 构造物所属土地使用权面积 | J16: 2023/01/12
B17: clr_asset_others_sbc | C17: STRUCTUREUSETYPE | D17: varchar(6) | E17: YES | F17: 构造物所属土地使用权类型 | G17: =HYPERLINK("#码值映射清单!B4520","LandUseType") | J17: 2023/01/12
B18: clr_asset_others_sbc | C18: STRUCTURELANDLEVEL | D18: varchar(80) | E18: YES | F18: 构造物所属土地分级 | G18: =HYPERLINK("#码值映射清单!B4530","CopyrightOwnerShip") | J18: 2023/01/12
B19: clr_asset_others_sbc | C19: STRUCTUREACHIEVECOST | D19: decimal(24,6) | E19: YES | F19: 构造物所属土地使用权取得价格/使用权购入价值 | J19: 2023/01/12
B20: clr_asset_others_sbc | C20: COMPLETIONDATE | D20: datetime | E20: YES | F20: 构造物竣工日期 | J20: 2023/01/12
B21: clr_asset_others_sbc | C21: RUNNEDPERIOD | D21: decimal(18,2) | E21: YES | F21: 构造物已运营时间 | J21: 2023/01/12
B22: clr_asset_others_sbc | C22: RUNNINGSCALE | D22: varchar(1000) | E22: YES | F22: 构造物运营规模 | J22: 2023/01/12
B23: clr_asset_others_sbc | C23: ANNUALINCOME | D23: decimal(24,6) | E23: YES | F23: 构造物年平均运营收入 | J23: 2023/01/12
B24: clr_asset_others_sbc | C24: STRUCTUREEQUIPMENT | D24: varchar(500) | E24: YES | F24: 构造物配套设施设备 | J24: 2023/01/12
B25: clr_asset_others_sbc | C25: MATCHBUILDING | D25: varchar(500) | E25: YES | F25: 构造物配套建筑 | J25: 2023/01/12
B26: clr_asset_others_sbc | C26: STRUCTUREDESCRIBE | D26: varchar(500) | E26: YES | F26: 构造物基础设施情况描述 | J26: 2023/01/12
B27: clr_asset_others_sbc | C27: VACANCYPERIOD | D27: decimal(18,2) | E27: YES | F27: 构造物空置时间 | J27: 2023/01/12
B28: clr_asset_others_sbc | C28: REMAINUSEYEARS | D28: decimal(18,2) | E28: YES | F28: 构造物所属土地剩余使用年限 | J28: 2023/01/12
B29: clr_asset_others_sbc | C29: RENTTYPE | D29: varchar(6) | E29: YES | F29: 构造物租赁形式 | G29: =HYPERLINK("#码值映射清单!B1217","RentType") | J29: 2023/01/12
B30: clr_asset_others_sbc | C30: LEASEMENTSTARTDATE | D30: datetime | E30: YES | F30: 构造物租赁合同生效日 | J30: 2023/01/12
B31: clr_asset_others_sbc | C31: LEASEMENTENDDATE | D31: datetime | E31: YES | F31: 构造物租赁合同到期日 | J31: 2023/01/12
B32: clr_asset_others_sbc | C32: LANDUSEYEARS | D32: decimal(18,2) | E32: YES | F32: 所属土地使用权年限 | J32: 2023/01/12
B33: clr_asset_others_sbc | C33: LANDUSEENDDATE | D33: datetime | E33: YES | F33: 所属土地使用权到期日 | J33: 2023/01/12
B34: clr_asset_others_sbc | C34: BUILDINGSTAUTS | D34: varchar(500) | E34: YES | F34: 房屋状况 | J34: 2023/01/12
B35: clr_asset_others_sbc | C35: ISINDEPENDENTCERT | D35: char(1) | E35: YES | F35: 构造物是否已办妥独立产权证或能办理独立产权证 | G35: =HYPERLINK("#码值映射清单!B5150","YesNo") | J35: 2023/01/12
B36: clr_asset_others_sbc | C36: ISSTATEPROPERTY | D36: char(1) | E36: YES | F36: 构造物是否为国家财产 | G36: =HYPERLINK("#码值映射清单!B5150","YesNo") | J36: 2023/01/12
B37: clr_asset_others_sbc | C37: ISMEANINGFULBUIDING | D37: char(1) | E37: YES | F37: 构造物是否包含被列为文物保护的古建筑或是有重要纪念意义的建筑物 | G37: =HYPERLINK("#码值映射清单!B5150","YesNo") | J37: 2023/01/12
B38: clr_asset_others_sbc | C38: ISDEMOLITIONBUILDING | D38: char(1) | E38: YES | F38: 构造物是否包含已依法公告在国家建设征用拆迁范围内的房地产 | G38: =HYPERLINK("#码值映射清单!B5150","YesNo") | J38: 2023/01/12
B39: clr_asset_others_sbc | C39: ISQUESTIONABLEBUILDING | D39: char(1) | E39: YES | F39: 构造物是否为违法、违章建筑物或依法被查封、扣押、监管或采用其他强制性措施的财产 | G39: =HYPERLINK("#码值映射清单!B5150","YesNo") | J39: 2023/01/12
B40: clr_asset_others_sbc | C40: ISQUALIFIED | D40: char(1) | E40: YES | F40: 构造物是否已竣工验收并通过最近一次年检 | G40: =HYPERLINK("#码值映射清单!B5150","YesNo") | J40: 2023/01/12
B41: clr_asset_others_sbc | C41: OWNERCERTIFICATION | D41: char(1) | E41: YES | F41: 是否已提交构造物相关权属证明 | G41: =HYPERLINK("#码值映射清单!B5150","YesNo") | J41: 2023/01/12
B42: clr_asset_others_sbc | C42: RELATIVECERTIFY | D42: char(1) | E42: YES | F42: 是否已提交构造物相关的出租合同与相关登记证明 | G42: =HYPERLINK("#码值映射清单!B5150","YesNo") | J42: 2023/01/12
B43: clr_asset_others_sbc | C43: FINANCEREPORTFLAG | D43: char(1) | E43: YES | F43: 是否已提交构造物相关的企业财务报表 | G43: =HYPERLINK("#码值映射清单!B5150","YesNo") | J43: 2023/01/12
B44: clr_asset_others_sbc | C44: LANDUSEFLAG | D44: char(1) | E44: YES | F44: 是否已提交构造物相关的土地使用权证 | G44: =HYPERLINK("#码值映射清单!B5150","YesNo") | J44: 2023/01/12
B45: clr_asset_others_sbc | C45: LANDUSESELLFLAG | D45: char(1) | E45: YES | F45: 是否已提交构造物相关的土地使用权出让合同 | G45: =HYPERLINK("#码值映射清单!B5150","YesNo") | J45: 2023/01/12
B46: clr_asset_others_sbc | C46: ANNUALSURVEYDATA | D46: char(1) | E46: YES | F46: 是否已提交构造物相关的年检材料 | G46: =HYPERLINK("#码值映射清单!B5150","YesNo") | J46: 2023/01/12
B47: clr_asset_others_sbc | C47: CORPORGID | D47: varchar(32) | E47: YES | F47: 法人机构编号 | J47: 2023/01/12
B48: clr_asset_others_sbc | C48: URBANPLANNING | D48: varchar(1000) | E48: YES | F48: 当前或未来设计押品所在区域的城市规划计划或特殊政策 | J48: 2023/01/12
B49: clr_asset_others_sbc | C49: ISCOMBINEDCERT | D49: varchar(6) | E49: YES | F49: 是否双证合一 | J49: 45740
B50: clr_asset_others_sbc | C50: LANDNO | D50: varchar(32) | E50: YES | F50: 所属土地宗地号 | J50: 45740
B51: clr_asset_others_sbc | C51: FACILITIES | D51: varchar(200) | E51: YES | F51: 配套设施情况 | J51: 45740

Sheet clr_asset_others_tlpr
A1: =HYPERLINK("#表结构清单!A1","返回") | B1: 可转让知识产权中的财产权
B2: 表名 | C2: 列名 | D2: 字段类型 | E2: 是否为空 | F2: 字段注释 | G2: 码值 | H2: 备注 | I2: 修订人 | J2: 修订日期
B3: clr_asset_others_tlpr | C3: CLRID | D3: varchar(32) | E3: NO | F3: 押品编号 | J3: 2023/01/12
B4: clr_asset_others_tlpr | C4: PATENTNAME | D4: varchar(80) | E4: YES | F4: 专利名称/权利名称 | J4: 2023/01/12
B5: clr_asset_others_tlpr | C5: COPYRIGHTRGSTNO | D5: varchar(80) | E5: YES | F5: 著作权登记号/专利号/商标注册证号码 | J5: 2023/01/12
B6: clr_asset_others_tlpr | C6: AUTHOR | D6: varchar(80) | E6: YES | F6: 作者/专利设计人 | J6: 2023/01/12
B7: clr_asset_others_tlpr | C7: RIGHTOWNER | D7: varchar(80) | E7: YES | F7: 专利权人/著作权人/有权人 | J7: 2023/01/12
B8: clr_asset_others_tlpr | C8: PUBLICAITONSERAILNO | D8: varchar(18) | E8: YES | F8: 出版物序列号 | J8: 2023/01/12
B9: clr_asset_others_tlpr | C9: COMPLETIONDATE | D9: varchar(18) | E9: YES | F9: 作品创作完成时间 | J9: 2023/01/12
B10: clr_asset_others_tlpr | C10: FIRSTRELEASEDATE | D10: date | E10: YES | F10: 首次发表时间 | J10: 2023/01/12
B11: clr_asset_others_tlpr | C11: OWNERSHIP | D11: varchar(200) | E11: YES | F11: 著作权所有关系/著作权享有关系 | G11: =HYPERLINK("#码值映射清单!B4530","CopyrightOwnerShip") | J11: 2023/01/12
